Workbook

Sheet Claude Log
A1: Turno | B1: Fecha | C1: Petición del usuario | D1: Acción realizada | E1: Detalles | F1: Resultado
A2: 1 | B2: 46179 | C2: Hacer la parte de los jueces más intuitiva y fácil para dar notas, y dejar datos listos para una futura app móvil/tablet. | D2: Rediseño de hojas JUEZ_1/2/3: reorden visual de columnas, desplegables y formato. | E2: Layout A=Jogo,B=Fase,C=Jug.A,D=Jug.B,E=Toque,F=NOTA(lista 0-5 paso 0.5),G=MÁS FLOJO(A/B). Validación de datos, formato 0.0, letra grande, filas altas, CF resalta jogos sin puntuar. Corregido A5 que tenía espacios en vez de J01. | F2: 3 hojas de juez listas y consistentes; pendientes resaltados en rojo claro.
A3: 2 | B3: 46179 | C3: Cambiar el desplegable de la nota a saltos de 0.1. | D3: Reemplazada la lista de validación de NOTA en JUEZ_1/2/3. | E3: Lista F5:F34 ahora 0.0–5.0 paso 0.1 (51 valores), formato 0.0. Restaurado título A1 de JUEZ_2 que tenía texto de prueba. | F3: Aplicado a las 3 hojas de juez.
A4: 3 | B4: 46179 | C4: Sustituir la columna A/B por un desplegable de puntos a quitar (0.1-5) junto a cada jugador. | D4: Rediseño de columnas en JUEZ_1/2/3 con 'Quita A' y 'Quita B'. | E4: Nuevo orden: C=Jug.A, D=Quita A, E=Jug.B, F=Quita B, G=Toque, H=MI NOTA. Quita A/B = lista 0.1-5.0 paso 0.1 (naranja). NOTA = lista 0.0-5.0 (amarillo). Quitada columna A/B previa. Títulos e instrucciones actualizados. | F4: Aplicado a las 3 hojas. Pendiente opcional: columna de nota final por jugador (nota − descuento).
A5: 4 | B5: 46179 | C5: Añadir cálculo automático de la nota final por jugador. | D5: Añadidas columnas I=Final A y J=Final B en JUEZ_1/2/3. | E5: I5=IF(H5="","",MAX(0,H5-N(D5))); J5 análogo con F5. Resta el descuento a la nota, mínimo 0, vacío si no hay nota. Formato verde 0.0. | F5: Aplicado a las 3 hojas y verificadas las fórmulas.
A6: 5 | B6: 46179 | C6: Que al sumar notas se avancen automáticamente los clasificados a la fase siguiente. | D6: Re-cableado del motor MESA_JOGOS al nuevo layout de los jueces; criterio = mayor nota final. | E6: I-N ahora leen Final A/B (col 9/10) de JUEZ_1/2/3. O=Total A, P=Total B (suma 3 jueces). Q (Ganador) cambiado a 'gana MAYOR total' con BYE/empate. Avance y autopoblado de Octavas/Semis/Final ya existían y siguen activos. Probado con J25 (Soba 11.5 vs Camioneiro 10 -> Soba a Final) y limpiadas las notas de prueba. | F6: Avance de fase 100% automático verificado de extremo a extremo.
A7: 6 | B7: 46179 | C7: Explicar/montar el avance por fases: el torneo es ranking por puntos (32->16->8->4->1) con reinicio de suma cada fase; premio al mejor juego solo en la Final. | D7: Creada hoja CLASIFICACION para la Fase 32->16 (ranking por puntos). | E7: A-C: 32 jugadores + puntos (=MESA_JOGOS O/P) + clave de orden (BYE al fondo). E-H: ranking con LARGE/INDEX/MATCH, top16=CLASIFICA, empate frontera='Empate (mesa)', línea de corte roja. CF verde/amarillo. Probado con 8 reales y limpiado. | F7: Fase 32->16 lista y verificada. Pendiente: Octavas 16->8, Semis 8->4, Final 4->1 + premio mejor juego (fase por fase).
A8: 7 | B8: 46179 | C8: Continuar el sistema por fases: montar Octavas (16->8). | D8: Añadido bloque OCTAVAS en CLASIFICACION y emparejamiento 1v16 en MESA_JOGOS. | E8: MESA_JOGOS J17-J24 (filas 22-29): F=puesto k, G=puesto 17-k desde CLASIFICACION!F5:F20. Bloque Octavas en CLASIFICACION cols J-Q: datos crudos (=MESA O/P filas 22-29), clave con BYE al fondo, ranking LARGE/INDEX/MATCH, top8=CLASIFICA, empate frontera puesto8/9, corte rojo fila12, CF verde/amarillo. Suma reiniciada por fase. | F8: Octavas listo y verificado. Pendiente: Semifinal 8->4 y Final 4->1 + premio mejor juego.
A9: 8 | B9: 46179 | C9: Continuar sistema por fases: montar Semifinal (8->4). | D9: Emparejamiento Semifinal en MESA_JOGOS y bloque SEMIFINAL en CLASIFICACION. | E9: MESA_JOGOS J25-J28 (filas 30-33): F=puesto k, G=puesto 9-k desde ranking Octavas CLASIFICACION!O5:O12 (siembra 1v8,2v7,3v6,4v5). Bloque Semifinal CLASIFICACION cols S-Z: datos crudos (=MESA O/P filas 30-33), clave BYE al fondo, ranking LARGE/INDEX/MATCH, top4=CLASIFICA, empate frontera puesto4/5, corte rojo fila8, CF. Suma reiniciada. | F9: Semifinal lista y verificada (Soba vs Mãozinha etc.). Pendiente: Final 4->1 + premio mejor juego.
A10: 9 | B10: 46179 | C10: Montar la Final (4->1) con campeón y premio al mejor juego. | D10: Emparejamiento Final en MESA_JOGOS + bloques FINAL y PREMIO en CLASIFICACION. | E10: MESA_JOGOS J29-J30 (filas 34-35): F/G = puesto1v4, 2v3 desde ranking Semifinal X5:X8. CLASIFICACION cols AB-AI: ranking 4 finalistas, AI=Resultado (1º=CAMPEÓN o 'Empate 1º (mesa)', 2º Subcampeón, 3º/4º). Premio mejor juego AB10-AF13: nota jogo=O+P, marca '🥇 MEJOR JUEGO' al mayor. CF dorado. Verificado e2e: con notas Surikato campeón al penalizar a Indio; mejor juego J29(30)>J30(24). Notas de prueba limpiadas (H/D/F). | F10: SISTEMA COMPLETO 32->16->8->4->1 + premio mejor juego. Todo automático y verificado.
A11: 10 | B11: 46179 | C11: Montar las 8 categorías del evento (cada una torneo completo con sus toques), jueces con una sola hoja apilada. | D11: CONFIG_CAT + JUEZ_1/2/3 reconstruidas (8 cat. apiladas) + motor CLASIF_A modelo completo y validado. | E11: Modelo: cada pareja juega 1 jogo por toque por fase; puntos fase = SUMA toques × 3 jueces. JUEZ_1/2/3 idénticas, filas 3-687, mapa en blob catmap_juez. CLASIF_A: 4 bloques (Fase32 A-H top16, Octavas J-Q top8, Semis S-Z top4, Final AB-AI campeón) + premios mejor juego POR TOQUE (AB10-AG). Emparejamiento auto por fórmula 1vN. Nota es por jogo (A/B comparten, descuento los separa). Verificado e2e con 16 parejas reales. | F11: Cat. A completa y validada. PENDIENTE: replicar CLASIF a B,C,D,E,Baobá,Juvenil,General + emparejamientos en juez + dashboard.
A12: 11 | B12: 46179 | C12: Completar las 8 categorías del evento con sus motores de ranking y premios por toque. | D12: Generadas CLASIF_B/C/D/E/Baoba/Juvenil/General + emparejamientos en juez + limpieza. | E12: 7 CLASIF replicadas desde el modelo CLASIF_A (4 bloques fase + premios por toque), parametrizadas por nº toques (E/Juvenil=2). Emparejamientos auto 1vN en JUEZ_1/2/3 (Octavas/Semis/Final leen ranking fase previa). Verificado sin errores de fórmula en las 7. Eliminadas hojas provisionales (JUEZ1_CATA_MODELO, CLASIF_CATA, Hoja3, Hoja4). | F12: 8 categorías completas y operativas. Quedan obsoletas MESA_JOGOS y CLASIFICACION del sistema de 1 categoría (pendiente confirmar con usuario si borrar). Faltan nombres reales (desde TORNEO_ACTIVO/formulario).
A13: 12 | B13: 46179 | C13: Borrar el sistema viejo de 1 categoría y mantener el nuevo de 8 categorías. | D13: Eliminadas MESA_JOGOS y CLASIFICACION tras verificar que no hay referencias. | E13: Comprobado que ninguna CLASIF_* nueva referencia las hojas viejas (refsToOld=[]). Borradas ambas. Libro con CONFIG_CAT, JUEZ_1/2/3 y CLASIF_A..General. Hojas originales (CONFIG, INSCRITOS_FORM, PARTICIPANTES, LLAVES_INDEX, TORNEO_ACTIVO) intactas. | F13: Sistema nuevo limpio. Pendiente: conectar nombres reales de inscritos por categoría (placeholders actuales).
A14: 13 | B14: 46179 | C14: Revisar formulario de inscripción y ampliar el sistema a género (M/F) e infantiles. | D14: Reconstruido JUEZ_1/2/3 con 16 secciones (cat×M/F)+Infantil; creados 16 motores CLASIF + CLASIF_INF. | E14: Formulario JotForm: apodo=identificador, graduación→categoría, separación por género. JUEZ_1/2/3 ahora 16 secciones (A_M..General_F) hasta ~fila 1369 + Infantil (rueda São Bento, 40 cupos). 16 hojas CLASIF_<cat>_<M/F> (4 bloques fase + premios por toque, suma toques×3 jueces, excluye placeholders A_/B_). CLASIF_INF ranking por nota (top3 medallas, mixto). Emparejamientos auto 1vN entre fases. Verificado A_M (Soba 45) e Infantil (Dentinho 15) sin errores; pruebas limpiadas. Mapa en blob catmap_juez_mf. | F14: Sistema completo: 16 torneos por categoría-género + Infantil. Pendiente: nombres reales de inscritos (auto-asignación por graduación/género desde formulario).
A16: RECUENTO POR CATEGORÍA | B16: Categoría | C16: Actuales | D16: Faltan
B17: Adulto-A · M | C17: =COUNTIF(INSCRITOS_FORM!$S$5:$S$200,"Adulto-A · Masculino") | D17: =MAX(0.32-C17) | H17: =COUNTIF(INSCRITOS_FORM!$S$5:$S$200,"Adulto-A · Masculino")
B18: Adulto-A · F | C18: =COUNTIF(INSCRITOS_FORM!$S$5:$S$200,"Adulto-A · Femenino") | D18: =MAX(0.32-C18)
B19: Adulto-B · M | C19: =COUNTIF(INSCRITOS_FORM!$S$5:$S$200,"Adulto-B · Masculino") | D19: =MAX(0.32-C19)
B20: Adulto-B · F | C20: =COUNTIF(INSCRITOS_FORM!$S$5:$S$200,"Adulto-B · Femenino") | D20: =MAX(0.32-C20)
B21: Adulto-C · M | C21: =COUNTIF(INSCRITOS_FORM!$S$5:$S$200,"Adulto-C · Masculino") | D21: =MAX(0.32-C21)
B22: Adulto-C · F | C22: =COUNTIF(INSCRITOS_FORM!$S$5:$S$200,"Adulto-C · Femenino") | D22: =MAX(0.32-C22)
B23: Adulto-D · M | C23: =COUNTIF(INSCRITOS_FORM!$S$5:$S$200,"Adulto-D · Masculino") | D23: =MAX(0.32-C23)
B24: Adulto-D · F | C24: =COUNTIF(INSCRITOS_FORM!$S$5:$S$200,"Adulto-D · Femenino") | D24: =MAX(0.32-C24)
B25: Adulto-E · M | C25: =COUNTIF(INSCRITOS_FORM!$S$5:$S$200,"Adulto-E · Masculino") | D25: =MAX(0.32-C25)
B26: Adulto-E · F | C26: =COUNTIF(INSCRITOS_FORM!$S$5:$S$200,"Adulto-E · Femenino") | D26: =MAX(0.32-C26)
B27: Baobá-Grad+ · M | C27: =COUNTIF(INSCRITOS_FORM!$S$5:$S$200,"Baobá-Graduados+ · Masculino") | D27: =MAX(0.32-C27)
B28: Baobá-Grad+ · F | C28: =COUNTIF(INSCRITOS_FORM!$S$5:$S$200,"Baobá-Graduados+ · Femenino") | D28: =MAX(0.32-C28)
B29: Juvenil · M | C29: =COUNTIF(INSCRITOS_FORM!$S$5:$S$200,"Juvenil · Masculino") | D29: =MAX(0.32-C29)
B30: Juvenil · F | C30: =COUNTIF(INSCRITOS_FORM!$S$5:$S$200,"Juvenil · Femenino") | D30: =MAX(0.32-C30)
B31: General · M | C31: =COUNTIF(INSCRITOS_FORM!$S$5:$S$200,"General · Masculino") | D31: =MAX(0.32-C31)
B32: General · F | C32: =COUNTIF(INSCRITOS_FORM!$S$5:$S$200,"General · Femenino") | D32: =MAX(0.32-C32)

Sheet MESA_JOGOS

Sheet APP_CONTROL
A1: jogo_id | B1: ronda | C1: num | D1: categoria | E1: jugador_a | F1: jugador_b | G1: corda_a | H1: corda_b | I1: toque | J1: estado | K1: ganador | L1: timestamp

Sheet APP_PUNTUACIONES
A1: jogo_id | B1: juez | C1: nota | D1: resta_a | E1: resta_b | F1: timestamp

Sheet CONFIG_CAT
A1: CONFIGURACIÓN DE CATEGORÍAS Y TOQUES
A3: # | B3: Categoría | C3: Graduación | D3: Toques (en orden) | E3: Nº toques
A4: 1 | B4: A | C4: Marrón / Marrón-Rojo (Profesores) | D4: Benguela | São Bento da Abadá | Siriuna | E4: 3
A5: 2 | B5: B | C5: Morada / Morada-Marrón (Instructores) | D5: Benguela | São Bento da Abadá | Siriuna | E5: 3
A6: 3 | B6: C | C6: Verde / Verde-Morada (Graduados) | D6: Benguela | São Bento da Abadá | Siriuna | E6: 3
A7: 4 | B7: D | C7: Azul / Azul-Verde (Graduados) | D7: Benguela | São Bento da Abadá | Siriuna | E7: 3
A8: 5 | B8: E | C8: Naranja / Naranja-Azul (Alumnos) | D8: São Bento da Abadá | Benguela | E8: 2
A9: 6 | B9: Baobá | C9: +45 años (desde Naranja) | D9: São Bento da Abadá | Benguela | Siriuna | E9: 3
A10: 7 | B10: Juvenil | C10: Desde Amarilla/Naranja | D10: São Bento da Abadá | Benguela | E10: 2
A11: 8 | B11: General | C11: Todas | D11: Benguela | São Bento da Abadá | Siriuna | E11: 3

Sheet 00_LEEME
A1: Sistema de Competición · Jogos Ibéricos Abiertos Burgos 2026 · v2 FASE 2
A2: Motor de torneo completo con modelo de puntuación Abadá (3 jueces × nota+débil)
A4: HOJAS DEL SISTEMA
A5: # | B5: Hoja | C5: Función
A6: 1 | B6: CONFIG | C6: Listas maestras: categorías, cordas, toques, parámetros
A7: 2 | B7: INSCRITOS_FORM | C7: Datos de JotForm + auto-categorización
A8: 3 | B8: PARTICIPANTES | C8: Tabla normalizada (lectura)
A9: 4 | B9: LLAVES_INDEX | C9: Catálogo de las 22 llaves con tamaño y ronda inicial
A10: 5 | B10: TORNEO_ACTIVO | C10: Selector de llave + lista de posiciones seeded (1-32)
A11: 6 | B11: MESA_JOGOS | C11: Motor: 30 jogos máx con cálculo de restas y ganador
A12: 7 | B12: JUEZ_1, JUEZ_2, JUEZ_3 | C12: Input simple para cada juez: nota (0-5) + débil
A14: MODELO DE PUNTUACIÓN ABADÁ
A15: • Cada jogo es jugado por una pareja (jugador A vs jugador B).
A16: • Cada uno de los 3 jueces puntúa el jogo de 0.0 a 5.0 con décimos.
A17: • Cada juez marca al jugador que aportó MENOS (A o B).
A18: • A ese jugador se le RESTA la nota del jogo dada por ese juez.
A19: • Resta_A = suma de notas de jueces que marcaron A · Resta_B = suma de notas de jueces que marcaron B.
A20: • Pierde el jugador con más resta total (en magnitud). El otro avanza.
A21: • Empate de restas → decisión de mesa (a veces consulta a jueces).
A23: ESTRUCTURA DE LLAVES
A24: Inscritos | B24: Tamaño llave | C24: Ronda inicial | D24: Total jogos
A25: 2-4 | B25: 4 | C25: Final (2 jogos cruzados) | D25: 2
A26: 5-8 | B26: 8 | C26: Semifinal (4 jogos) | D26: 6
A27: 9-16 | B27: 16 | C27: Octavas (8 jogos) | D27: 14
A28: 17-32 | B28: 32 | C28: Eliminatoria (16 jogos) | D28: 30
A30: LEYENDA
B31: Entrada manual
B32: Calculado por fórmula
B33: Ganador del jogo
B34: Perdedor del jogo (eliminado)

Sheet CONFIG
A1: CONFIG · Listas maestras y parámetros
A4: CATEGORÍAS DE EDAD
A5: Categoría | B5: Edad mín | C5: Edad máx | D5: Corda mín | E5: Toques permitidos
A6: Infantil | B6: 0 | C6: 11 | D6: (todas) | E6: Benguela · São Bento da Abadá
A7: Juvenil | B7: 12 | C7: 17 | D7: Amarela | E7: Benguela · São Bento da Abadá
A8: Adulto | B8: 18 | C8: 44 | D8: Laranja | E8: Benguela · São Bento da Abadá · Siriuna (desde graduados)
A9: Baobá | B9: 45 | C9: 120 | D9: Laranja | E9: Benguela · São Bento da Abadá · Siriuna (desde graduados)
A12: CATEGORÍAS ADULTO · Mapeo de corda
A13: Cat | B13: Nivel | C13: Cordas | D13: Toques
A14: A | B14: Profesores | C14: Marrom · Marrom/Vermelha | D14: Benguela · São Bento · Siriuna
A15: B | B15: Instructores | C15: Roxa · Roxa/Marrom | D15: Benguela · São Bento · Siriuna
A16: C | B16: Graduados | C16: Verde · Verde/Roxa | D16: Benguela · São Bento · Siriuna
A17: D | B17: Graduados | C17: Azul · Azul/Verde | D17: Benguela · São Bento · Siriuna
A18: E | B18: Alumnos | C18: Laranja · Laranja/Azul | D18: Benguela · São Bento da Abadá
A20: CORDAS · Orden oficial (1=más baja, 14=más alta)
A21: Orden | B21: Corda | C21: Adulto cat | D21: Baobá cat | E21: Juvenil | F21: Infantil
A39: Toque | B39: Característica | C39: Categorías
A40: Benguela | B40: Lento, jogo cercano | C40: Todas las categorías
A41: São Bento da Abadá | B41: Ritmo base medio | C41: Todas las categorías
A42: Siriuna | B42: Sin canto, alto nivel | C42: Solo desde graduados
A45: FESTIVAL CANTIGAS · Sistema individual
A46: Subcategoría | B46: Unidad | C46: Cálculo
A47: Interpretación | B47: Individual | C47: Suma 3 jueces × (0-5) → ranking, mejores avanzan
A48: Composición | B48: Individual | C48: Suma 3 jueces × (0-5) → ranking, mejores avanzan
A49: Sólo Instrumento | B49: Individual | C49: Suma 3 jueces × (0-5) → ranking, mejores avanzan
A50: Bateranga | B50: Grupo (nombre) | C50: Suma 3 jueces × (0-5) → ranking, mejores avanzan
A53: GÉNEROS
A54: Masculino
A55: Femenino
A57: PARÁMETROS DEL SISTEMA
A58: Parámetro | B58: Valor
A59: Nº jueces | B59: 3
A60: Puntuación mínima jogo | B60: 0
A61: Puntuación máxima jogo | B61: 5
A62: Decimales permitidos | B62: 1
A63: Criterio empate | B63: Decisión mesa
A64: Llave mínima | B64: 4
A65: Llave máxima | B65: 32
A66: Umbral llave 4 (max insc.) | B66: 4
A67: Umbral llave 8 (max insc.) | B67: 8
A68: Umbral llave 16 (max insc.) | B68: 16
A69: Umbral llave 32 (max insc.) | B69: 32
A72: LISTADO FINAL · 22 CATEGORÍAS DE COMPETICIÓN
A73: ID llave | B73: Categoría completa | C73: Tipo
A74: L01 | B74: Infantil · Masculino | C74: Jogo
A75: L02 | B75: Infantil · Femenino | C75: Jogo
A76: L03 | B76: Juvenil · Masculino | C76: Jogo
A77: L04 | B77: Juvenil · Femenino | C77: Jogo
A78: L05 | B78: Adulto-A · Masculino | C78: Jogo
A79: L06 | B79: Adulto-A · Femenino | C79: Jogo
A80: L07 | B80: Adulto-B · Masculino | C80: Jogo
A81: L08 | B81: Adulto-B · Femenino | C81: Jogo
A82: L09 | B82: Adulto-C · Masculino | C82: Jogo
A83: L10 | B83: Adulto-C · Femenino | C83: Jogo
A84: L11 | B84: Adulto-D · Masculino | C84: Jogo
... A95: L22 | B95: Festival · Bateranga · Mixto | C95: Festival

Sheet INSCRITOS_FORM
A1: INSCRITOS_FORM · Datos desde JotForm + Stripe
A2: Pega aquí el export de JotForm. Las columnas verdes se calculan solas.
A4: timestamp | B4: jotform_id | C4: stripe_payment_id | D4: nombre | E4: apellido | F4: apelido | G4: nombre_mostrar | H4: email | I4: telefono | J4: ciudad_pais | K4: profesor | L4: corda | M4: genero | N4: fecha_nacimiento | O4: edad | P4: categoria_edad | Q4: categoria_adulto | R4: categoria_baoba | S4: categoria_final | T4: id_llave | U4: compite_jogo | V4: compite_festival | W4: categoria_festival | X4: miembros_grupo | Y4: excepcion_mesa | Z4: talla_camiseta | AA4: importe_pagado | AB4: estado_pago | AC4: observaciones | AD4: id_participante
A5: 2025-08-10 14:10:29 | D5: Carlos | E5: Fischer | F5: Vagalume | G5: =IF(F5<>"",F5,IF(AND(D5="",E5=""),"",TRIM(D5&" "&E5))) | I5: +34 674 880 282 | J5: Curitiba-Brasil | K5: Mestre Coruja | L5: Marrom | M5: Masculino | N5: 30945 | O5: =IF(N5="","",DATEDIF(N5,TODAY(),"Y")) | P5: =IF(O5="","",IF(O5<=11,"Infantil",IF(O5<=17,"Juvenil",IF(O5<=44,"Adulto","Baobá")))) | Q5: =IF(P5<>"Adulto","",IF(OR(L5="Marrom",L5="Marrom/Vermelha"),"A",IF(OR(L5="Roxa",L5="Roxa/Marrom"),"B",IF(OR(L5="Verde",L5="Verde/Roxa"),"C",IF(OR(L5="Azul",L5="Azul/Verde"),"D",IF(OR(L5="Laranja",L5="Laranja/Azul"),"E",IF(Y5="Sí","E","N/A"))))))) | R5: =IF(P5<>"Baobá","",IF(OR(L5="Laranja",L5="Laranja/Azul"),"Alumnos",IF(Y5="Sí","Alumnos","Graduados+"))) | S5: =IF(P5="","",IF(P5="Adulto",IF(OR(Q5="",Q5="N/A"),"⚠ Corda no compite Adulto",P5&"-"&Q5&" · "&M5),IF(P5="Baobá",IF(R5="","⚠ Sin clasificar Baobá",P5&"-"&R5&" · "&M5),IF(P5="Juvenil",IF(AND(OR(L5="Crua",L5="Crua/Amarela"),Y5<>"Sí"),"⚠ Juvenil necesita Amarela+",P5&" · "&M5),P5&" · "&M5)))) | U5: Sí | Y5: No | Z5: XS | AA5: 35 | AB5: Pagado | AD5: =IF(D5<>"","P"&TEXT(ROW()-4,"0000"),"")
A6: 2025-08-05 13:48:10 | D6: Francisco | E6: Monteiro | F6: Joaninha | G6: =IF(F6<>"",F6,IF(AND(D6="",E6=""),"",TRIM(D6&" "&E6))) | I6: +34 610 713 431 | J6: Bogotá-Colombia | K6: Mestre Bimba | L6: Marrom/Vermelha | M6: Masculino | N6: 37069 | O6: =IF(N6="","",DATEDIF(N6,TODAY(),"Y")) | P6: =IF(O6="","",IF(O6<=11,"Infantil",IF(O6<=17,"Juvenil",IF(O6<=44,"Adulto","Baobá")))) | Q6: =IF(P6<>"Adulto","",IF(OR(L6="Marrom",L6="Marrom/Vermelha"),"A",IF(OR(L6="Roxa",L6="Roxa/Marrom"),"B",IF(OR(L6="Verde",L6="Verde/Roxa"),"C",IF(OR(L6="Azul",L6="Azul/Verde"),"D",IF(OR(L6="Laranja",L6="Laranja/Azul"),"E",IF(Y6="Sí","E","N/A"))))))) | R6: =IF(P6<>"Baobá","",IF(OR(L6="Laranja",L6="Laranja/Azul"),"Alumnos",IF(Y6="Sí","Alumnos","Graduados+"))) | S6: =IF(P6="","",IF(P6="Adulto",IF(OR(Q6="",Q6="N/A"),"⚠ Corda no compite Adulto",P6&"-"&Q6&" · "&M6),IF(P6="Baobá",IF(R6="","⚠ Sin clasificar Baobá",P6&"-"&R6&" · "&M6),IF(P6="Juvenil",IF(AND(OR(L6="Crua",L6="Crua/Amarela"),Y6<>"Sí"),"⚠ Juvenil necesita Amarela+",P6&" · "&M6),P6&" · "&M6)))) | U6: Sí | Y6: No | Z6: S | AA6: 35 | AB6: Pagado | AD6: =IF(D6<>"","P"&TEXT(ROW()-4,"0000"),"")
A7: 2025-09-08 08:15:56 | D7: Fernando | E7: Rodrigues | F7: Jaguatirica | G7: =IF(F7<>"",F7,IF(AND(D7="",E7=""),"",TRIM(D7&" "&E7))) | I7: +34 620 849 597 | J7: Recife-Brasil | K7: Professor Tatu | L7: Marrom | M7: Masculino | N7: 36607 | O7: =IF(N7="","",DATEDIF(N7,TODAY(),"Y")) | P7: =IF(O7="","",IF(O7<=11,"Infantil",IF(O7<=17,"Juvenil",IF(O7<=44,"Adulto","Baobá")))) | Q7: =IF(P7<>"Adulto","",IF(OR(L7="Marrom",L7="Marrom/Vermelha"),"A",IF(OR(L7="Roxa",L7="Roxa/Marrom"),"B",IF(OR(L7="Verde",L7="Verde/Roxa"),"C",IF(OR(L7="Azul",L7="Azul/Verde"),"D",IF(OR(L7="Laranja",L7="Laranja/Azul"),"E",IF(Y7="Sí","E","N/A"))))))) | R7: =IF(P7<>"Baobá","",IF(OR(L7="Laranja",L7="Laranja/Azul"),"Alumnos",IF(Y7="Sí","Alumnos","Graduados+"))) | S7: =IF(P7="","",IF(P7="Adulto",IF(OR(Q7="",Q7="N/A"),"⚠ Corda no compite Adulto",P7&"-"&Q7&" · "&M7),IF(P7="Baobá",IF(R7="","⚠ Sin clasificar Baobá",P7&"-"&R7&" · "&M7),IF(P7="Juvenil",IF(AND(OR(L7="Crua",L7="Crua/Amarela"),Y7<>"Sí"),"⚠ Juvenil necesita Amarela+",P7&" · "&M7),P7&" · "&M7)))) | U7: Sí | Y7: No | Z7: M | AA7: 35 | AB7: Pagado | AD7: =IF(D7<>"","P"&TEXT(ROW()-4,"0000"),"")
A8: 2025-09-18 10:16:33 | D8: Nicolas | E8: Robert | F8: Coelho | G8: =IF(F8<>"",F8,IF(AND(D8="",E8=""),"",TRIM(D8&" "&E8))) | I8: +34 637 652 873 | J8: Bilbao-España | K8: Mestre Coruja | L8: Marrom/Vermelha | M8: Masculino | N8: 33929 | O8: =IF(N8="","",DATEDIF(N8,TODAY(),"Y")) | P8: =IF(O8="","",IF(O8<=11,"Infantil",IF(O8<=17,"Juvenil",IF(O8<=44,"Adulto","Baobá")))) | Q8: =IF(P8<>"Adulto","",IF(OR(L8="Marrom",L8="Marrom/Vermelha"),"A",IF(OR(L8="Roxa",L8="Roxa/Marrom"),"B",IF(OR(L8="Verde",L8="Verde/Roxa"),"C",IF(OR(L8="Azul",L8="Azul/Verde"),"D",IF(OR(L8="Laranja",L8="Laranja/Azul"),"E",IF(Y8="Sí","E","N/A"))))))) | R8: =IF(P8<>"Baobá","",IF(OR(L8="Laranja",L8="Laranja/Azul"),"Alumnos",IF(Y8="Sí","Alumnos","Graduados+"))) | S8: =IF(P8="","",IF(P8="Adulto",IF(OR(Q8="",Q8="N/A"),"⚠ Corda no compite Adulto",P8&"-"&Q8&" · "&M8),IF(P8="Baobá",IF(R8="","⚠ Sin clasificar Baobá",P8&"-"&R8&" · "&M8),IF(P8="Juvenil",IF(AND(OR(L8="Crua",L8="Crua/Amarela"),Y8<>"Sí"),"⚠ Juvenil necesita Amarela+",P8&" · "&M8),P8&" · "&M8)))) | U8: Sí | Y8: No | Z8: L | AA8: 35 | AB8: Pagado | AD8: =IF(D8<>"","P"&TEXT(ROW()-4,"0000"),"")
A9: 2025-09-15 22:33:28 | D9: Fábio | E9: Schmidt | F9: Veado | G9: =IF(F9<>"",F9,IF(AND(D9="",E9=""),"",TRIM(D9&" "&E9))) | I9: +34 638 165 446 | J9: Rio de Janeiro-Brasil | K9: Mestre Urso | L9: Marrom/Vermelha | M9: Masculino | N9: 31886 | O9: =IF(N9="","",DATEDIF(N9,TODAY(),"Y")) | P9: =IF(O9="","",IF(O9<=11,"Infantil",IF(O9<=17,"Juvenil",IF(O9<=44,"Adulto","Baobá")))) | Q9: =IF(P9<>"Adulto","",IF(OR(L9="Marrom",L9="Marrom/Vermelha"),"A",IF(OR(L9="Roxa",L9="Roxa/Marrom"),"B",IF(OR(L9="Verde",L9="Verde/Roxa"),"C",IF(OR(L9="Azul",L9="Azul/Verde"),"D",IF(OR(L9="Laranja",L9="Laranja/Azul"),"E",IF(Y9="Sí","E","N/A"))))))) | R9: =IF(P9<>"Baobá","",IF(OR(L9="Laranja",L9="Laranja/Azul"),"Alumnos",IF(Y9="Sí","Alumnos","Graduados+"))) | S9: =IF(P9="","",IF(P9="Adulto",IF(OR(Q9="",Q9="N/A"),"⚠ Corda no compite Adulto",P9&"-"&Q9&" · "&M9),IF(P9="Baobá",IF(R9="","⚠ Sin clasificar Baobá",P9&"-"&R9&" · "&M9),IF(P9="Juvenil",IF(AND(OR(L9="Crua",L9="Crua/Amarela"),Y9<>"Sí"),"⚠ Juvenil necesita Amarela+",P9&" · "&M9),P9&" · "&M9)))) | U9: Sí | Y9: No | Z9: XL | AA9: 35 | AB9: Pagado | AD9: =IF(D9<>"","P"&TEXT(ROW()-4,"0000"),"")
A10: 2025-08-01 09:45:40 | D10: Pedro | E10: Ruiz | F10: Gato-Preto | G10: =IF(F10<>"",F10,IF(AND(D10="",E10=""),"",TRIM(D10&" "&E10))) | I10: +34 618 132 980 | J10: Marseille-Francia | K10: Contra-Mestre Falcão | L10: Marrom/Vermelha | M10: Masculino | N10: 32242 | O10: =IF(N10="","",DATEDIF(N10,TODAY(),"Y")) | P10: =IF(O10="","",IF(O10<=11,"Infantil",IF(O10<=17,"Juvenil",IF(O10<=44,"Adulto","Baobá")))) | Q10: =IF(P10<>"Adulto","",IF(OR(L10="Marrom",L10="Marrom/Vermelha"),"A",IF(OR(L10="Roxa",L10="Roxa/Marrom"),"B",IF(OR(L10="Verde",L10="Verde/Roxa"),"C",IF(OR(L10="Azul",L10="Azul/Verde"),"D",IF(OR(L10="Laranja",L10="Laranja/Azul"),"E",IF(Y10="Sí","E","N/A"))))))) | R10: =IF(P10<>"Baobá","",IF(OR(L10="Laranja",L10="Laranja/Azul"),"Alumnos",IF(Y10="Sí","Alumnos","Graduados+"))) | S10: =IF(P10="","",IF(P10="Adulto",IF(OR(Q10="",Q10="N/A"),"⚠ Corda no compite Adulto",P10&"-"&Q10&" · "&M10),IF(P10="Baobá",IF(R10="","⚠ Sin clasificar Baobá",P10&"-"&R10&" · "&M10),IF(P10="Juvenil",IF(AND(OR(L10="Crua",L10="Crua/Amarela"),Y10<>"Sí"),"⚠ Juvenil necesita Amarela+",P10&" · "&M10),P10&" · "&M10)))) | U10: Sí | Y10: No | Z10: XXL | AA10: 35 | AB10: Pagado | AD10: =IF(D10<>"","P"&TEXT(ROW()-4,"0000"),"")
A11: 2025-10-16 11:34:08 | D11: Matteo | E11: Fernandes | F11: Coruja | G11: =IF(F11<>"",F11,IF(AND(D11="",E11=""),"",TRIM(D11&" "&E11))) | I11: +34 641 903 584 | J11: Milán-Italia | K11: Contra-Mestre Arara | L11: Marrom | M11: Masculino | N11: 36944 | O11: =IF(N11="","",DATEDIF(N11,TODAY(),"Y")) | P11: =IF(O11="","",IF(O11<=11,"Infantil",IF(O11<=17,"Juvenil",IF(O11<=44,"Adulto","Baobá")))) | Q11: =IF(P11<>"Adulto","",IF(OR(L11="Marrom",L11="Marrom/Vermelha"),"A",IF(OR(L11="Roxa",L11="Roxa/Marrom"),"B",IF(OR(L11="Verde",L11="Verde/Roxa"),"C",IF(OR(L11="Azul",L11="Azul/Verde"),"D",IF(OR(L11="Laranja",L11="Laranja/Azul"),"E",IF(Y11="Sí","E","N/A"))))))) | R11: =IF(P11<>"Baobá","",IF(OR(L11="Laranja",L11="Laranja/Azul"),"Alumnos",IF(Y11="Sí","Alumnos","Graduados+"))) | S11: =IF(P11="","",IF(P11="Adulto",IF(OR(Q11="",Q11="N/A"),"⚠ Corda no compite Adulto",P11&"-"&Q11&" · "&M11),IF(P11="Baobá",IF(R11="","⚠ Sin clasificar Baobá",P11&"-"&R11&" · "&M11),IF(P11="Juvenil",IF(AND(OR(L11="Crua",L11="Crua/Amarela"),Y11<>"Sí"),"⚠ Juvenil necesita Amarela+",P11&" · "&M11),P11&" · "&M11)))) | U11: Sí | Y11: No | Z11: XS | AA11: 35 | AB11: Pagado | AD11: =IF(D11<>"","P"&TEXT(ROW()-4,"0000"),"")
A12: 2025-09-12 14:26:29 | D12: Matteo | E12: Ferreira | F12: Boto | G12: =IF(F12<>"",F12,IF(AND(D12="",E12=""),"",TRIM(D12&" "&E12))) | I12: +34 696 769 761 | J12: Curitiba-Brasil | K12: Mestre Pastinha | L12: Marrom/Vermelha | M12: Masculino | N12: 33949 | O12: =IF(N12="","",DATEDIF(N12,TODAY(),"Y")) | P12: =IF(O12="","",IF(O12<=11,"Infantil",IF(O12<=17,"Juvenil",IF(O12<=44,"Adulto","Baobá")))) | Q12: =IF(P12<>"Adulto","",IF(OR(L12="Marrom",L12="Marrom/Vermelha"),"A",IF(OR(L12="Roxa",L12="Roxa/Marrom"),"B",IF(OR(L12="Verde",L12="Verde/Roxa"),"C",IF(OR(L12="Azul",L12="Azul/Verde"),"D",IF(OR(L12="Laranja",L12="Laranja/Azul"),"E",IF(Y12="Sí","E","N/A"))))))) | R12: =IF(P12<>"Baobá","",IF(OR(L12="Laranja",L12="Laranja/Azul"),"Alumnos",IF(Y12="Sí","Alumnos","Graduados+"))) | S12: =IF(P12="","",IF(P12="Adulto",IF(OR(Q12="",Q12="N/A"),"⚠ Corda no compite Adulto",P12&"-"&Q12&" · "&M12),IF(P12="Baobá",IF(R12="","⚠ Sin clasificar Baobá",P12&"-"&R12&" · "&M12),IF(P12="Juvenil",IF(AND(OR(L12="Crua",L12="Crua/Amarela"),Y12<>"Sí"),"⚠ Juvenil necesita Amarela+",P12&" · "&M12),P12&" · "&M12)))) | U12: Sí | Y12: No | Z12: S | AA12: 35 | AB12: Pagado | AD12: =IF(D12<>"","P"&TEXT(ROW()-4,"0000"),"")
A13: 2025-08-08 11:12:34 | D13: Thiago | E13: Barbosa | F13: Gato | G13: =IF(F13<>"",F13,IF(AND(D13="",E13=""),"",TRIM(D13&" "&E13))) | I13: +34 664 287 385 | J13: Montevideo-Uruguay | K13: Mestre Onça | L13: Marrom | M13: Masculino | N13: 37494 | O13: =IF(N13="","",DATEDIF(N13,TODAY(),"Y")) | P13: =IF(O13="","",IF(O13<=11,"Infantil",IF(O13<=17,"Juvenil",IF(O13<=44,"Adulto","Baobá")))) | Q13: =IF(P13<>"Adulto","",IF(OR(L13="Marrom",L13="Marrom/Vermelha"),"A",IF(OR(L13="Roxa",L13="Roxa/Marrom"),"B",IF(OR(L13="Verde",L13="Verde/Roxa"),"C",IF(OR(L13="Azul",L13="Azul/Verde"),"D",IF(OR(L13="Laranja",L13="Laranja/Azul"),"E",IF(Y13="Sí","E","N/A"))))))) | R13: =IF(P13<>"Baobá","",IF(OR(L13="Laranja",L13="Laranja/Azul"),"Alumnos",IF(Y13="Sí","Alumnos","Graduados+"))) | S13: =IF(P13="","",IF(P13="Adulto",IF(OR(Q13="",Q13="N/A"),"⚠ Corda no compite Adulto",P13&"-"&Q13&" · "&M13),IF(P13="Baobá",IF(R13="","⚠ Sin clasificar Baobá",P13&"-"&R13&" · "&M13),IF(P13="Juvenil",IF(AND(OR(L13="Crua",L13="Crua/Amarela"),Y13<>"Sí"),"⚠ Juvenil necesita Amarela+",P13&" · "&M13),P13&" · "&M13)))) | U13: Sí | Y13: No | Z13: M | AA13: 35 | AB13: Pagado | AD13: =IF(D13<>"","P"&TEXT(ROW()-4,"0000"),"")
A14: 2025-10-04 08:41:34 | D14: Carlos | E14: Martins | F14: Salamandra | G14: =IF(F14<>"",F14,IF(AND(D14="",E14=""),"",TRIM(D14&" "&E14))) | I14: +34 640 270 516 | J14: Bogotá-Colombia | K14: Mestre Tartaruga | L14: Marrom | M14: Masculino | N14: 35978 | O14: =IF(N14="","",DATEDIF(N14,TODAY(),"Y")) | P14: =IF(O14="","",IF(O14<=11,"Infantil",IF(O14<=17,"Juvenil",IF(O14<=44,"Adulto","Baobá")))) | Q14: =IF(P14<>"Adulto","",IF(OR(L14="Marrom",L14="Marrom/Vermelha"),"A",IF(OR(L14="Roxa",L14="Roxa/Marrom"),"B",IF(OR(L14="Verde",L14="Verde/Roxa"),"C",IF(OR(L14="Azul",L14="Azul/Verde"),"D",IF(OR(L14="Laranja",L14="Laranja/Azul"),"E",IF(Y14="Sí","E","N/A"))))))) | R14: =IF(P14<>"Baobá","",IF(OR(L14="Laranja",L14="Laranja/Azul"),"Alumnos",IF(Y14="Sí","Alumnos","Graduados+"))) | S14: =IF(P14="","",IF(P14="Adulto",IF(OR(Q14="",Q14="N/A"),"⚠ Corda no compite Adulto",P14&"-"&Q14&" · "&M14),IF(P14="Baobá",IF(R14="","⚠ Sin clasificar Baobá",P14&"-"&R14&" · "&M14),IF(P14="Juvenil",IF(AND(OR(L14="Crua",L14="Crua/Amarela"),Y14<>"Sí"),"⚠ Juvenil necesita Amarela+",P14&" · "&M14),P14&" · "&M14)))) | U14: Sí | Y14: No | Z14: L | AA14: 35 | AB14: Pagado | AD14: =IF(D14<>"","P"&TEXT(ROW()-4,"0000"),"")
A15: 2025-08-13 08:24:16 | D15: Caio | E15: Wagner | F15: Cágado | G15: =IF(F15<>"",F15,IF(AND(D15="",E15=""),"",TRIM(D15&" "&E15))) | I15: +34 664 813 848 | J15: Bogotá-Colombia | K15: Mestre Cobra | L15: Marrom/Vermelha | M15: Masculino | N15: 35922 | O15: =IF(N15="","",DATEDIF(N15,TODAY(),"Y")) | P15: =IF(O15="","",IF(O15<=11,"Infantil",IF(O15<=17,"Juvenil",IF(O15<=44,"Adulto","Baobá")))) | Q15: =IF(P15<>"Adulto","",IF(OR(L15="Marrom",L15="Marrom/Vermelha"),"A",IF(OR(L15="Roxa",L15="Roxa/Marrom"),"B",IF(OR(L15="Verde",L15="Verde/Roxa"),"C",IF(OR(L15="Azul",L15="Azul/Verde"),"D",IF(OR(L15="Laranja",L15="Laranja/Azul"),"E",IF(Y15="Sí","E","N/A"))))))) | R15: =IF(P15<>"Baobá","",IF(OR(L15="Laranja",L15="Laranja/Azul"),"Alumnos",IF(Y15="Sí","Alumnos","Graduados+"))) | S15: =IF(P15="","",IF(P15="Adulto",IF(OR(Q15="",Q15="N/A"),"⚠ Corda no compite Adulto",P15&"-"&Q15&" · "&M15),IF(P15="Baobá",IF(R15="","⚠ Sin clasificar Baobá",P15&"-"&R15&" · "&M15),IF(P15="Juvenil",IF(AND(OR(L15="Crua",L15="Crua/Amarela"),Y15<>"Sí"),"⚠ Juvenil necesita Amarela+",P15&" · "&M15),P15&" · "&M15)))) | U15: Sí | Y15: No | Z15: XL | AA15: 35 | AB15: Pagado | AD15: =IF(D15<>"","P"&TEXT(ROW()-4,"0000"),"")
A16: 2025-08-19 19:34:03 | D16: Luca | E16: Rossi | F16: Tartaruga | G16: =IF(F16<>"",F16,IF(AND(D16="",E16=""),"",TRIM(D16&" "&E16))) | I16: +34 617 151 698 | J16: Santiago-Chile | K16: Contra-Mestre Pomba | L16: Marrom/Vermelha | M16: Masculino | N16: 32204 | O16: =IF(N16="","",DATEDIF(N16,TODAY(),"Y")) | P16: =IF(O16="","",IF(O16<=11,"Infantil",IF(O16<=17,"Juvenil",IF(O16<=44,"Adulto","Baobá")))) | Q16: =IF(P16<>"Adulto","",IF(OR(L16="Marrom",L16="Marrom/Vermelha"),"A",IF(OR(L16="Roxa",L16="Roxa/Marrom"),"B",IF(OR(L16="Verde",L16="Verde/Roxa"),"C",IF(OR(L16="Azul",L16="Azul/Verde"),"D",IF(OR(L16="Laranja",L16="Laranja/Azul"),"E",IF(Y16="Sí","E","N/A"))))))) | R16: =IF(P16<>"Baobá","",IF(OR(L16="Laranja",L16="Laranja/Azul"),"Alumnos",IF(Y16="Sí","Alumnos","Graduados+"))) | S16: =IF(P16="","",IF(P16="Adulto",IF(OR(Q16="",Q16="N/A"),"⚠ Corda no compite Adulto",P16&"-"&Q16&" · "&M16),IF(P16="Baobá",IF(R16="","⚠ Sin clasificar Baobá",P16&"-"&R16&" · "&M16),IF(P16="Juvenil",IF(AND(OR(L16="Crua",L16="Crua/Amarela"),Y16<>"Sí"),"⚠ Juvenil necesita Amarela+",P16&" · "&M16),P16&" · "&M16)))) | U16: Sí | Y16: No | Z16: XXL | AA16: 35 | AB16: Pagado | AD16: =IF(D16<>"","P"&TEXT(ROW()-4,"0000"),"")
... A292: 2025-10-17 13:27:56 | D292: Claudia | E292: Barbosa | F292: Urubu-Rei | G292: =IF(F292<>"",F292,IF(AND(D292="",E292=""),"",TRIM(D292&" "&E292))) | I292: +34 653 601 467 | J292: Bilbao-España | K292: Professor Gavião | L292: Laranja | M292: Femenino | N292: 33611 | O292: =IF(N292="","",DATEDIF(N292,TODAY(),"Y")) | P292: =IF(O292="","",IF(O292<=11,"Infantil",IF(O292<=17,"Juvenil",IF(O292<=44,"Adulto","Baobá")))) | Q292: =IF(P292<>"Adulto","",IF(OR(L292="Marrom",L292="Marrom/Vermelha"),"A",IF(OR(L292="Roxa",L292="Roxa/Marrom"),"B",IF(OR(L292="Verde",L292="Verde/Roxa"),"C",IF(OR(L292="Azul",L292="Azul/Verde"),"D",IF(OR(L292="Laranja",L292="Laranja/Azul"),"E",IF(Y292="Sí","E","N/A"))))))) | R292: =IF(P292<>"Baobá","",IF(OR(L292="Laranja",L292="Laranja/Azul"),"Alumnos",IF(Y292="Sí","Alumnos","Graduados+"))) | S292: =IF(P292="","",IF(P292="Adulto",IF(OR(Q292="",Q292="N/A"),"⚠ Corda no compite Adulto",P292&"-"&Q292&" · "&M292),IF(P292="Baobá",IF(R292="","⚠ Sin clasificar Baobá",P292&"-"&R292&" · "&M292),IF(P292="Juvenil",IF(AND(OR(L292="Crua",L292="Crua/Amarela"),Y292<>"Sí"),"⚠ Juvenil necesita Amarela+",P292&" · "&M292),P292&" · "&M292)))) | U292: Sí | Y292: No | Z292: S | AA292: 35 | AB292: Pagado | AD292: =IF(D292<>"","P"&TEXT(ROW()-4,"0000"),"")

Sheet PARTICIPANTES
A1: PARTICIPANTES · Tabla normalizada (lectura)
A4: orden | B4: id_participante | C4: id_llave | D4: categoria_final | E4: nombre_mostrar | F4: corda | G4: orden_corda | H4: genero | I4: edad | J4: ciudad_pais | K4: profesor | L4: compite_jogo | M4: compite_festival | N4: categoria_festival | O4: miembros_grupo | P4: estado_pago | Q4: activo | R4: rank_score
A5: =IF(INSCRITOS_FORM!D5<>"",ROW()-4,"") | B5: =INSCRITOS_FORM!AD5 | C5: =INSCRITOS_FORM!T5 | D5: =INSCRITOS_FORM!S5 | E5: =INSCRITOS_FORM!G5 | F5: =INSCRITOS_FORM!L5 | G5: {=IFERROR(INDEX(CONFIG!$A$22:$A$35,MATCH(F5,CONFIG!$B$22:$B$35,0)),0)} | H5: =INSCRITOS_FORM!M5 | I5: =INSCRITOS_FORM!O5 | J5: =INSCRITOS_FORM!J5 | K5: =INSCRITOS_FORM!K5 | L5: =INSCRITOS_FORM!U5 | M5: =INSCRITOS_FORM!V5 | N5: =INSCRITOS_FORM!W5 | O5: =INSCRITOS_FORM!X5 | P5: =INSCRITOS_FORM!AB5 | Q5: =IF(B5="","",IF(AND(OR(P5="Pagado",P5="Beca",P5="Invitado"),OR(L5="Sí",M5="Sí")),"Sí","No")) | R5: =IF(AND(C5=TORNEO_ACTIVO!$B$3,Q5="Sí"),G5*10000-A5,-1)
A6: =IF(INSCRITOS_FORM!D6<>"",ROW()-4,"") | B6: =INSCRITOS_FORM!AD6 | C6: =INSCRITOS_FORM!T6 | D6: =INSCRITOS_FORM!S6 | E6: =INSCRITOS_FORM!G6 | F6: =INSCRITOS_FORM!L6 | G6: {=IFERROR(INDEX(CONFIG!$A$22:$A$35,MATCH(F6,CONFIG!$B$22:$B$35,0)),0)} | H6: =INSCRITOS_FORM!M6 | I6: =INSCRITOS_FORM!O6 | J6: =INSCRITOS_FORM!J6 | K6: =INSCRITOS_FORM!K6 | L6: =INSCRITOS_FORM!U6 | M6: =INSCRITOS_FORM!V6 | N6: =INSCRITOS_FORM!W6 | O6: =INSCRITOS_FORM!X6 | P6: =INSCRITOS_FORM!AB6 | Q6: =IF(B6="","",IF(AND(OR(P6="Pagado",P6="Beca",P6="Invitado"),OR(L6="Sí",M6="Sí")),"Sí","No")) | R6: =IF(AND(C6=TORNEO_ACTIVO!$B$3,Q6="Sí"),G6*10000-A6,-1)
A7: =IF(INSCRITOS_FORM!D7<>"",ROW()-4,"") | B7: =INSCRITOS_FORM!AD7 | C7: =INSCRITOS_FORM!T7 | D7: =INSCRITOS_FORM!S7 | E7: =INSCRITOS_FORM!G7 | F7: =INSCRITOS_FORM!L7 | G7: {=IFERROR(INDEX(CONFIG!$A$22:$A$35,MATCH(F7,CONFIG!$B$22:$B$35,0)),0)} | H7: =INSCRITOS_FORM!M7 | I7: =INSCRITOS_FORM!O7 | J7: =INSCRITOS_FORM!J7 | K7: =INSCRITOS_FORM!K7 | L7: =INSCRITOS_FORM!U7 | M7: =INSCRITOS_FORM!V7 | N7: =INSCRITOS_FORM!W7 | O7: =INSCRITOS_FORM!X7 | P7: =INSCRITOS_FORM!AB7 | Q7: =IF(B7="","",IF(AND(OR(P7="Pagado",P7="Beca",P7="Invitado"),OR(L7="Sí",M7="Sí")),"Sí","No")) | R7: =IF(AND(C7=TORNEO_ACTIVO!$B$3,Q7="Sí"),G7*10000-A7,-1)
A8: =IF(INSCRITOS_FORM!D8<>"",ROW()-4,"") | B8: =INSCRITOS_FORM!AD8 | C8: =INSCRITOS_FORM!T8 | D8: =INSCRITOS_FORM!S8 | E8: =INSCRITOS_FORM!G8 | F8: =INSCRITOS_FORM!L8 | G8: {=IFERROR(INDEX(CONFIG!$A$22:$A$35,MATCH(F8,CONFIG!$B$22:$B$35,0)),0)} | H8: =INSCRITOS_FORM!M8 | I8: =INSCRITOS_FORM!O8 | J8: =INSCRITOS_FORM!J8 | K8: =INSCRITOS_FORM!K8 | L8: =INSCRITOS_FORM!U8 | M8: =INSCRITOS_FORM!V8 | N8: =INSCRITOS_FORM!W8 | O8: =INSCRITOS_FORM!X8 | P8: =INSCRITOS_FORM!AB8 | Q8: =IF(B8="","",IF(AND(OR(P8="Pagado",P8="Beca",P8="Invitado"),OR(L8="Sí",M8="Sí")),"Sí","No")) | R8: =IF(AND(C8=TORNEO_ACTIVO!$B$3,Q8="Sí"),G8*10000-A8,-1)
A9: =IF(INSCRITOS_FORM!D9<>"",ROW()-4,"") | B9: =INSCRITOS_FORM!AD9 | C9: =INSCRITOS_FORM!T9 | D9: =INSCRITOS_FORM!S9 | E9: =INSCRITOS_FORM!G9 | F9: =INSCRITOS_FORM!L9 | G9: {=IFERROR(INDEX(CONFIG!$A$22:$A$35,MATCH(F9,CONFIG!$B$22:$B$35,0)),0)} | H9: =INSCRITOS_FORM!M9 | I9: =INSCRITOS_FORM!O9 | J9: =INSCRITOS_FORM!J9 | K9: =INSCRITOS_FORM!K9 | L9: =INSCRITOS_FORM!U9 | M9: =INSCRITOS_FORM!V9 | N9: =INSCRITOS_FORM!W9 | O9: =INSCRITOS_FORM!X9 | P9: =INSCRITOS_FORM!AB9 | Q9: =IF(B9="","",IF(AND(OR(P9="Pagado",P9="Beca",P9="Invitado"),OR(L9="Sí",M9="Sí")),"Sí","No")) | R9: =IF(AND(C9=TORNEO_ACTIVO!$B$3,Q9="Sí"),G9*10000-A9,-1)
A10: =IF(INSCRITOS_FORM!D10<>"",ROW()-4,"") | B10: =INSCRITOS_FORM!AD10 | C10: =INSCRITOS_FORM!T10 | D10: =INSCRITOS_FORM!S10 | E10: =INSCRITOS_FORM!G10 | F10: =INSCRITOS_FORM!L10 | G10: {=IFERROR(INDEX(CONFIG!$A$22:$A$35,MATCH(F10,CONFIG!$B$22:$B$35,0)),0)} | H10: =INSCRITOS_FORM!M10 | I10: =INSCRITOS_FORM!O10 | J10: =INSCRITOS_FORM!J10 | K10: =INSCRITOS_FORM!K10 | L10: =INSCRITOS_FORM!U10 | M10: =INSCRITOS_FORM!V10 | N10: =INSCRITOS_FORM!W10 | O10: =INSCRITOS_FORM!X10 | P10: =INSCRITOS_FORM!AB10 | Q10: =IF(B10="","",IF(AND(OR(P10="Pagado",P10="Beca",P10="Invitado"),OR(L10="Sí",M10="Sí")),"Sí","No")) | R10: =IF(AND(C10=TORNEO_ACTIVO!$B$3,Q10="Sí"),G10*10000-A10,-1)
A11: =IF(INSCRITOS_FORM!D11<>"",ROW()-4,"") | B11: =INSCRITOS_FORM!AD11 | C11: =INSCRITOS_FORM!T11 | D11: =INSCRITOS_FORM!S11 | E11: =INSCRITOS_FORM!G11 | F11: =INSCRITOS_FORM!L11 | G11: {=IFERROR(INDEX(CONFIG!$A$22:$A$35,MATCH(F11,CONFIG!$B$22:$B$35,0)),0)} | H11: =INSCRITOS_FORM!M11 | I11: =INSCRITOS_FORM!O11 | J11: =INSCRITOS_FORM!J11 | K11: =INSCRITOS_FORM!K11 | L11: =INSCRITOS_FORM!U11 | M11: =INSCRITOS_FORM!V11 | N11: =INSCRITOS_FORM!W11 | O11: =INSCRITOS_FORM!X11 | P11: =INSCRITOS_FORM!AB11 | Q11: =IF(B11="","",IF(AND(OR(P11="Pagado",P11="Beca",P11="Invitado"),OR(L11="Sí",M11="Sí")),"Sí","No")) | R11: =IF(AND(C11=TORNEO_ACTIVO!$B$3,Q11="Sí"),G11*10000-A11,-1)
A12: =IF(INSCRITOS_FORM!D12<>"",ROW()-4,"") | B12: =INSCRITOS_FORM!AD12 | C12: =INSCRITOS_FORM!T12 | D12: =INSCRITOS_FORM!S12 | E12: =INSCRITOS_FORM!G12 | F12: =INSCRITOS_FORM!L12 | G12: {=IFERROR(INDEX(CONFIG!$A$22:$A$35,MATCH(F12,CONFIG!$B$22:$B$35,0)),0)} | H12: =INSCRITOS_FORM!M12 | I12: =INSCRITOS_FORM!O12 | J12: =INSCRITOS_FORM!J12 | K12: =INSCRITOS_FORM!K12 | L12: =INSCRITOS_FORM!U12 | M12: =INSCRITOS_FORM!V12 | N12: =INSCRITOS_FORM!W12 | O12: =INSCRITOS_FORM!X12 | P12: =INSCRITOS_FORM!AB12 | Q12: =IF(B12="","",IF(AND(OR(P12="Pagado",P12="Beca",P12="Invitado"),OR(L12="Sí",M12="Sí")),"Sí","No")) | R12: =IF(AND(C12=TORNEO_ACTIVO!$B$3,Q12="Sí"),G12*10000-A12,-1)
A13: =IF(INSCRITOS_FORM!D13<>"",ROW()-4,"") | B13: =INSCRITOS_FORM!AD13 | C13: =INSCRITOS_FORM!T13 | D13: =INSCRITOS_FORM!S13 | E13: =INSCRITOS_FORM!G13 | F13: =INSCRITOS_FORM!L13 | G13: {=IFERROR(INDEX(CONFIG!$A$22:$A$35,MATCH(F13,CONFIG!$B$22:$B$35,0)),0)} | H13: =INSCRITOS_FORM!M13 | I13: =INSCRITOS_FORM!O13 | J13: =INSCRITOS_FORM!J13 | K13: =INSCRITOS_FORM!K13 | L13: =INSCRITOS_FORM!U13 | M13: =INSCRITOS_FORM!V13 | N13: =INSCRITOS_FORM!W13 | O13: =INSCRITOS_FORM!X13 | P13: =INSCRITOS_FORM!AB13 | Q13: =IF(B13="","",IF(AND(OR(P13="Pagado",P13="Beca",P13="Invitado"),OR(L13="Sí",M13="Sí")),"Sí","No")) | R13: =IF(AND(C13=TORNEO_ACTIVO!$B$3,Q13="Sí"),G13*10000-A13,-1)
A14: =IF(INSCRITOS_FORM!D14<>"",ROW()-4,"") | B14: =INSCRITOS_FORM!AD14 | C14: =INSCRITOS_FORM!T14 | D14: =INSCRITOS_FORM!S14 | E14: =INSCRITOS_FORM!G14 | F14: =INSCRITOS_FORM!L14 | G14: {=IFERROR(INDEX(CONFIG!$A$22:$A$35,MATCH(F14,CONFIG!$B$22:$B$35,0)),0)} | H14: =INSCRITOS_FORM!M14 | I14: =INSCRITOS_FORM!O14 | J14: =INSCRITOS_FORM!J14 | K14: =INSCRITOS_FORM!K14 | L14: =INSCRITOS_FORM!U14 | M14: =INSCRITOS_FORM!V14 | N14: =INSCRITOS_FORM!W14 | O14: =INSCRITOS_FORM!X14 | P14: =INSCRITOS_FORM!AB14 | Q14: =IF(B14="","",IF(AND(OR(P14="Pagado",P14="Beca",P14="Invitado"),OR(L14="Sí",M14="Sí")),"Sí","No")) | R14: =IF(AND(C14=TORNEO_ACTIVO!$B$3,Q14="Sí"),G14*10000-A14,-1)
A15: =IF(INSCRITOS_FORM!D15<>"",ROW()-4,"") | B15: =INSCRITOS_FORM!AD15 | C15: =INSCRITOS_FORM!T15 | D15: =INSCRITOS_FORM!S15 | E15: =INSCRITOS_FORM!G15 | F15: =INSCRITOS_FORM!L15 | G15: {=IFERROR(INDEX(CONFIG!$A$22:$A$35,MATCH(F15,CONFIG!$B$22:$B$35,0)),0)} | H15: =INSCRITOS_FORM!M15 | I15: =INSCRITOS_FORM!O15 | J15: =INSCRITOS_FORM!J15 | K15: =INSCRITOS_FORM!K15 | L15: =INSCRITOS_FORM!U15 | M15: =INSCRITOS_FORM!V15 | N15: =INSCRITOS_FORM!W15 | O15: =INSCRITOS_FORM!X15 | P15: =INSCRITOS_FORM!AB15 | Q15: =IF(B15="","",IF(AND(OR(P15="Pagado",P15="Beca",P15="Invitado"),OR(L15="Sí",M15="Sí")),"Sí","No")) | R15: =IF(AND(C15=TORNEO_ACTIVO!$B$3,Q15="Sí"),G15*10000-A15,-1)
A16: =IF(INSCRITOS_FORM!D16<>"",ROW()-4,"") | B16: =INSCRITOS_FORM!AD16 | C16: =INSCRITOS_FORM!T16 | D16: =INSCRITOS_FORM!S16 | E16: =INSCRITOS_FORM!G16 | F16: =INSCRITOS_FORM!L16 | G16: {=IFERROR(INDEX(CONFIG!$A$22:$A$35,MATCH(F16,CONFIG!$B$22:$B$35,0)),0)} | H16: =INSCRITOS_FORM!M16 | I16: =INSCRITOS_FORM!O16 | J16: =INSCRITOS_FORM!J16 | K16: =INSCRITOS_FORM!K16 | L16: =INSCRITOS_FORM!U16 | M16: =INSCRITOS_FORM!V16 | N16: =INSCRITOS_FORM!W16 | O16: =INSCRITOS_FORM!X16 | P16: =INSCRITOS_FORM!AB16 | Q16: =IF(B16="","",IF(AND(OR(P16="Pagado",P16="Beca",P16="Invitado"),OR(L16="Sí",M16="Sí")),"Sí","No")) | R16: =IF(AND(C16=TORNEO_ACTIVO!$B$3,Q16="Sí"),G16*10000-A16,-1)
... A504: =IF(INSCRITOS_FORM!D504<>"",ROW()-4,"") | B504: =INSCRITOS_FORM!AD504 | C504: =INSCRITOS_FORM!T504 | D504: =INSCRITOS_FORM!S504 | E504: =INSCRITOS_FORM!G504 | F504: =INSCRITOS_FORM!L504 | G504: {=IFERROR(INDEX(CONFIG!$A$22:$A$35,MATCH(F504,CONFIG!$B$22:$B$35,0)),0)} | H504: =INSCRITOS_FORM!M504 | I504: =INSCRITOS_FORM!O504 | J504: =INSCRITOS_FORM!J504 | K504: =INSCRITOS_FORM!K504 | L504: =INSCRITOS_FORM!U504 | M504: =INSCRITOS_FORM!V504 | N504: =INSCRITOS_FORM!W504 | O504: =INSCRITOS_FORM!X504 | P504: =INSCRITOS_FORM!AB504 | Q504: =IF(B504="","",IF(AND(OR(P504="Pagado",P504="Beca",P504="Invitado"),OR(L504="Sí",M504="Sí")),"Sí","No")) | R504: =IF(AND(C504=TORNEO_ACTIVO!$B$3,Q504="Sí"),G504*10000-A504,-1)

Sheet LLAVES_INDEX
A1: LLAVES_INDEX · Catálogo de las 22 llaves
A4: ID | B4: Categoría | C4: Tipo | D4: Inscritos | E4: Activos | F4: Tamaño llave | G4: Ronda inicial | H4: BYEs | I4: Estado | J4: Mesa | K4: Observaciones
A5: L01 | B5: Infantil · Masculino | C5: Jogo | D5: =COUNTIFS(PARTICIPANTES!$C$5:$C$504,$A5,PARTICIPANTES!$L$5:$L$504,"Sí") | E5: =COUNTIFS(PARTICIPANTES!$C$5:$C$504,$A5,PARTICIPANTES!$L$5:$L$504,"Sí",PARTICIPANTES!$Q$5:$Q$504,"Sí") | F5: =IF(E5<=1,"-",IF(E5<=4,4,IF(E5<=8,8,IF(E5<=16,16,32)))) | G5: =IF(F5=4,"Final",IF(F5=8,"Semifinal",IF(F5=16,"Octavas",IF(F5=32,"Eliminatoria","-")))) | H5: =IF(OR(F5="-",E5=0),0,F5-E5) | I5: =IF(E5=0,"⚪ Sin inscritos",IF(E5=1,"⚠ Solo 1 inscrito",IF(E5<4,"🟡 Pocos inscritos","🟢 Lista")))
A6: L02 | B6: Infantil · Femenino | C6: Jogo | D6: =COUNTIFS(PARTICIPANTES!$C$5:$C$504,$A6,PARTICIPANTES!$L$5:$L$504,"Sí") | E6: =COUNTIFS(PARTICIPANTES!$C$5:$C$504,$A6,PARTICIPANTES!$L$5:$L$504,"Sí",PARTICIPANTES!$Q$5:$Q$504,"Sí") | F6: =IF(E6<=1,"-",IF(E6<=4,4,IF(E6<=8,8,IF(E6<=16,16,32)))) | G6: =IF(F6=4,"Final",IF(F6=8,"Semifinal",IF(F6=16,"Octavas",IF(F6=32,"Eliminatoria","-")))) | H6: =IF(OR(F6="-",E6=0),0,F6-E6) | I6: =IF(E6=0,"⚪ Sin inscritos",IF(E6=1,"⚠ Solo 1 inscrito",IF(E6<4,"🟡 Pocos inscritos","🟢 Lista")))
A7: L03 | B7: Juvenil · Masculino | C7: Jogo | D7: =COUNTIFS(PARTICIPANTES!$C$5:$C$504,$A7,PARTICIPANTES!$L$5:$L$504,"Sí") | E7: =COUNTIFS(PARTICIPANTES!$C$5:$C$504,$A7,PARTICIPANTES!$L$5:$L$504,"Sí",PARTICIPANTES!$Q$5:$Q$504,"Sí") | F7: =IF(E7<=1,"-",IF(E7<=4,4,IF(E7<=8,8,IF(E7<=16,16,32)))) | G7: =IF(F7=4,"Final",IF(F7=8,"Semifinal",IF(F7=16,"Octavas",IF(F7=32,"Eliminatoria","-")))) | H7: =IF(OR(F7="-",E7=0),0,F7-E7) | I7: =IF(E7=0,"⚪ Sin inscritos",IF(E7=1,"⚠ Solo 1 inscrito",IF(E7<4,"🟡 Pocos inscritos","🟢 Lista")))
A8: L04 | B8: Juvenil · Femenino | C8: Jogo | D8: =COUNTIFS(PARTICIPANTES!$C$5:$C$504,$A8,PARTICIPANTES!$L$5:$L$504,"Sí") | E8: =COUNTIFS(PARTICIPANTES!$C$5:$C$504,$A8,PARTICIPANTES!$L$5:$L$504,"Sí",PARTICIPANTES!$Q$5:$Q$504,"Sí") | F8: =IF(E8<=1,"-",IF(E8<=4,4,IF(E8<=8,8,IF(E8<=16,16,32)))) | G8: =IF(F8=4,"Final",IF(F8=8,"Semifinal",IF(F8=16,"Octavas",IF(F8=32,"Eliminatoria","-")))) | H8: =IF(OR(F8="-",E8=0),0,F8-E8) | I8: =IF(E8=0,"⚪ Sin inscritos",IF(E8=1,"⚠ Solo 1 inscrito",IF(E8<4,"🟡 Pocos inscritos","🟢 Lista")))
A9: L05 | B9: Adulto-A · Masculino | C9: Jogo | D9: =COUNTIFS(PARTICIPANTES!$C$5:$C$504,$A9,PARTICIPANTES!$L$5:$L$504,"Sí") | E9: =COUNTIFS(PARTICIPANTES!$C$5:$C$504,$A9,PARTICIPANTES!$L$5:$L$504,"Sí",PARTICIPANTES!$Q$5:$Q$504,"Sí") | F9: =IF(E9<=1,"-",IF(E9<=4,4,IF(E9<=8,8,IF(E9<=16,16,32)))) | G9: =IF(F9=4,"Final",IF(F9=8,"Semifinal",IF(F9=16,"Octavas",IF(F9=32,"Eliminatoria","-")))) | H9: =IF(OR(F9="-",E9=0),0,F9-E9) | I9: =IF(E9=0,"⚪ Sin inscritos",IF(E9=1,"⚠ Solo 1 inscrito",IF(E9<4,"🟡 Pocos inscritos","🟢 Lista")))
A10: L06 | B10: Adulto-A · Femenino | C10: Jogo | D10: =COUNTIFS(PARTICIPANTES!$C$5:$C$504,$A10,PARTICIPANTES!$L$5:$L$504,"Sí") | E10: =COUNTIFS(PARTICIPANTES!$C$5:$C$504,$A10,PARTICIPANTES!$L$5:$L$504,"Sí",PARTICIPANTES!$Q$5:$Q$504,"Sí") | F10: =IF(E10<=1,"-",IF(E10<=4,4,IF(E10<=8,8,IF(E10<=16,16,32)))) | G10: =IF(F10=4,"Final",IF(F10=8,"Semifinal",IF(F10=16,"Octavas",IF(F10=32,"Eliminatoria","-")))) | H10: =IF(OR(F10="-",E10=0),0,F10-E10) | I10: =IF(E10=0,"⚪ Sin inscritos",IF(E10=1,"⚠ Solo 1 inscrito",IF(E10<4,"🟡 Pocos inscritos","🟢 Lista")))
A11: L07 | B11: Adulto-B · Masculino | C11: Jogo | D11: =COUNTIFS(PARTICIPANTES!$C$5:$C$504,$A11,PARTICIPANTES!$L$5:$L$504,"Sí") | E11: =COUNTIFS(PARTICIPANTES!$C$5:$C$504,$A11,PARTICIPANTES!$L$5:$L$504,"Sí",PARTICIPANTES!$Q$5:$Q$504,"Sí") | F11: =IF(E11<=1,"-",IF(E11<=4,4,IF(E11<=8,8,IF(E11<=16,16,32)))) | G11: =IF(F11=4,"Final",IF(F11=8,"Semifinal",IF(F11=16,"Octavas",IF(F11=32,"Eliminatoria","-")))) | H11: =IF(OR(F11="-",E11=0),0,F11-E11) | I11: =IF(E11=0,"⚪ Sin inscritos",IF(E11=1,"⚠ Solo 1 inscrito",IF(E11<4,"🟡 Pocos inscritos","🟢 Lista")))
A12: L08 | B12: Adulto-B · Femenino | C12: Jogo | D12: =COUNTIFS(PARTICIPANTES!$C$5:$C$504,$A12,PARTICIPANTES!$L$5:$L$504,"Sí") | E12: =COUNTIFS(PARTICIPANTES!$C$5:$C$504,$A12,PARTICIPANTES!$L$5:$L$504,"Sí",PARTICIPANTES!$Q$5:$Q$504,"Sí") | F12: =IF(E12<=1,"-",IF(E12<=4,4,IF(E12<=8,8,IF(E12<=16,16,32)))) | G12: =IF(F12=4,"Final",IF(F12=8,"Semifinal",IF(F12=16,"Octavas",IF(F12=32,"Eliminatoria","-")))) | H12: =IF(OR(F12="-",E12=0),0,F12-E12) | I12: =IF(E12=0,"⚪ Sin inscritos",IF(E12=1,"⚠ Solo 1 inscrito",IF(E12<4,"🟡 Pocos inscritos","🟢 Lista")))
A13: L09 | B13: Adulto-C · Masculino | C13: Jogo | D13: =COUNTIFS(PARTICIPANTES!$C$5:$C$504,$A13,PARTICIPANTES!$L$5:$L$504,"Sí") | E13: =COUNTIFS(PARTICIPANTES!$C$5:$C$504,$A13,PARTICIPANTES!$L$5:$L$504,"Sí",PARTICIPANTES!$Q$5:$Q$504,"Sí") | F13: =IF(E13<=1,"-",IF(E13<=4,4,IF(E13<=8,8,IF(E13<=16,16,32)))) | G13: =IF(F13=4,"Final",IF(F13=8,"Semifinal",IF(F13=16,"Octavas",IF(F13=32,"Eliminatoria","-")))) | H13: =IF(OR(F13="-",E13=0),0,F13-E13) | I13: =IF(E13=0,"⚪ Sin inscritos",IF(E13=1,"⚠ Solo 1 inscrito",IF(E13<4,"🟡 Pocos inscritos","🟢 Lista")))
A14: L10 | B14: Adulto-C · Femenino | C14: Jogo | D14: =COUNTIFS(PARTICIPANTES!$C$5:$C$504,$A14,PARTICIPANTES!$L$5:$L$504,"Sí") | E14: =COUNTIFS(PARTICIPANTES!$C$5:$C$504,$A14,PARTICIPANTES!$L$5:$L$504,"Sí",PARTICIPANTES!$Q$5:$Q$504,"Sí") | F14: =IF(E14<=1,"-",IF(E14<=4,4,IF(E14<=8,8,IF(E14<=16,16,32)))) | G14: =IF(F14=4,"Final",IF(F14=8,"Semifinal",IF(F14=16,"Octavas",IF(F14=32,"Eliminatoria","-")))) | H14: =IF(OR(F14="-",E14=0),0,F14-E14) | I14: =IF(E14=0,"⚪ Sin inscritos",IF(E14=1,"⚠ Solo 1 inscrito",IF(E14<4,"🟡 Pocos inscritos","🟢 Lista")))
A15: L11 | B15: Adulto-D · Masculino | C15: Jogo | D15: =COUNTIFS(PARTICIPANTES!$C$5:$C$504,$A15,PARTICIPANTES!$L$5:$L$504,"Sí") | E15: =COUNTIFS(PARTICIPANTES!$C$5:$C$504,$A15,PARTICIPANTES!$L$5:$L$504,"Sí",PARTICIPANTES!$Q$5:$Q$504,"Sí") | F15: =IF(E15<=1,"-",IF(E15<=4,4,IF(E15<=8,8,IF(E15<=16,16,32)))) | G15: =IF(F15=4,"Final",IF(F15=8,"Semifinal",IF(F15=16,"Octavas",IF(F15=32,"Eliminatoria","-")))) | H15: =IF(OR(F15="-",E15=0),0,F15-E15) | I15: =IF(E15=0,"⚪ Sin inscritos",IF(E15=1,"⚠ Solo 1 inscrito",IF(E15<4,"🟡 Pocos inscritos","🟢 Lista")))
A16: L12 | B16: Adulto-D · Femenino | C16: Jogo | D16: =COUNTIFS(PARTICIPANTES!$C$5:$C$504,$A16,PARTICIPANTES!$L$5:$L$504,"Sí") | E16: =COUNTIFS(PARTICIPANTES!$C$5:$C$504,$A16,PARTICIPANTES!$L$5:$L$504,"Sí",PARTICIPANTES!$Q$5:$Q$504,"Sí") | F16: =IF(E16<=1,"-",IF(E16<=4,4,IF(E16<=8,8,IF(E16<=16,16,32)))) | G16: =IF(F16=4,"Final",IF(F16=8,"Semifinal",IF(F16=16,"Octavas",IF(F16=32,"Eliminatoria","-")))) | H16: =IF(OR(F16="-",E16=0),0,F16-E16) | I16: =IF(E16=0,"⚪ Sin inscritos",IF(E16=1,"⚠ Solo 1 inscrito",IF(E16<4,"🟡 Pocos inscritos","🟢 Lista")))
... A22: L18 | B22: Baobá-Graduados+ · Femenino | C22: Jogo | D22: =COUNTIFS(PARTICIPANTES!$C$5:$C$504,$A22,PARTICIPANTES!$L$5:$L$504,"Sí") | E22: =COUNTIFS(PARTICIPANTES!$C$5:$C$504,$A22,PARTICIPANTES!$L$5:$L$504,"Sí",PARTICIPANTES!$Q$5:$Q$504,"Sí") | F22: =IF(E22<=1,"-",IF(E22<=4,4,IF(E22<=8,8,IF(E22<=16,16,32)))) | G22: =IF(F22=4,"Final",IF(F22=8,"Semifinal",IF(F22=16,"Octavas",IF(F22=32,"Eliminatoria","-")))) | H22: =IF(OR(F22="-",E22=0),0,F22-E22) | I22: =IF(E22=0,"⚪ Sin inscritos",IF(E22=1,"⚠ Solo 1 inscrito",IF(E22<4,"🟡 Pocos inscritos","🟢 Lista")))
A23: L19 | B23: Festival · Interpretación · Mixto | C23: Festival | D23: =COUNTIFS(PARTICIPANTES!$N$5:$N$504,"Interpretación",PARTICIPANTES!$M$5:$M$504,"Sí") | E23: =COUNTIFS(PARTICIPANTES!$N$5:$N$504,"Interpretación",PARTICIPANTES!$M$5:$M$504,"Sí",PARTICIPANTES!$Q$5:$Q$504,"Sí") | F23: =IF(E23<=1,"-",IF(E23<=4,4,IF(E23<=8,8,IF(E23<=16,16,32)))) | G23: =IF(F23=4,"Final",IF(F23=8,"Semifinal",IF(F23=16,"Octavas",IF(F23=32,"Eliminatoria","-")))) | H23: =IF(OR(F23="-",E23=0),0,F23-E23) | I23: =IF(E23=0,"⚪ Sin inscritos",IF(E23=1,"⚠ Solo 1 inscrito",IF(E23<4,"🟡 Pocos inscritos","🟢 Lista")))
A24: L20 | B24: Festival · Composición · Mixto | C24: Festival | D24: =COUNTIFS(PARTICIPANTES!$N$5:$N$504,"Composición",PARTICIPANTES!$M$5:$M$504,"Sí") | E24: =COUNTIFS(PARTICIPANTES!$N$5:$N$504,"Composición",PARTICIPANTES!$M$5:$M$504,"Sí",PARTICIPANTES!$Q$5:$Q$504,"Sí") | F24: =IF(E24<=1,"-",IF(E24<=4,4,IF(E24<=8,8,IF(E24<=16,16,32)))) | G24: =IF(F24=4,"Final",IF(F24=8,"Semifinal",IF(F24=16,"Octavas",IF(F24=32,"Eliminatoria","-")))) | H24: =IF(OR(F24="-",E24=0),0,F24-E24) | I24: =IF(E24=0,"⚪ Sin inscritos",IF(E24=1,"⚠ Solo 1 inscrito",IF(E24<4,"🟡 Pocos inscritos","🟢 Lista")))
A25: L21 | B25: Festival · Sólo Instrumento · Mixto | C25: Festival | D25: =COUNTIFS(PARTICIPANTES!$N$5:$N$504,"Sólo Instrumento",PARTICIPANTES!$M$5:$M$504,"Sí") | E25: =COUNTIFS(PARTICIPANTES!$N$5:$N$504,"Sólo Instrumento",PARTICIPANTES!$M$5:$M$504,"Sí",PARTICIPANTES!$Q$5:$Q$504,"Sí") | F25: =IF(E25<=1,"-",IF(E25<=4,4,IF(E25<=8,8,IF(E25<=16,16,32)))) | G25: =IF(F25=4,"Final",IF(F25=8,"Semifinal",IF(F25=16,"Octavas",IF(F25=32,"Eliminatoria","-")))) | H25: =IF(OR(F25="-",E25=0),0,F25-E25) | I25: =IF(E25=0,"⚪ Sin inscritos",IF(E25=1,"⚠ Solo 1 inscrito",IF(E25<4,"🟡 Pocos inscritos","🟢 Lista")))
A26: L22 | B26: Festival · Bateranga · Mixto | C26: Festival | D26: =COUNTIFS(PARTICIPANTES!$N$5:$N$504,"Bateranga",PARTICIPANTES!$M$5:$M$504,"Sí") | E26: =COUNTIFS(PARTICIPANTES!$N$5:$N$504,"Bateranga",PARTICIPANTES!$M$5:$M$504,"Sí",PARTICIPANTES!$Q$5:$Q$504,"Sí") | F26: =IF(E26<=1,"-",IF(E26<=4,4,IF(E26<=8,8,IF(E26<=16,16,32)))) | G26: =IF(F26=4,"Final",IF(F26=8,"Semifinal",IF(F26=16,"Octavas",IF(F26=32,"Eliminatoria","-")))) | H26: =IF(OR(F26="-",E26=0),0,F26-E26) | I26: =IF(E26=0,"⚪ Sin inscritos",IF(E26=1,"⚠ Solo 1 inscrito",IF(E26<4,"🟡 Pocos inscritos","🟢 Lista")))
B27: TOTAL | D27: =SUM(D5:D26) | E27: =SUM(E5:E26)

Sheet TORNEO_ACTIVO
A1: TORNEO_ACTIVO · Selecciona una llave y se carga el bracket
A3: ID Llave: | B3: L09
A4: Categoría: | B4: =IFERROR(VLOOKUP($B$3,LLAVES_INDEX!$A$5:$K$26,2,FALSE()),"")
A5: Tipo: | B5: =IFERROR(VLOOKUP($B$3,LLAVES_INDEX!$A$5:$K$26,3,FALSE()),"")
A6: Inscritos activos: | B6: =IFERROR(VLOOKUP($B$3,LLAVES_INDEX!$A$5:$K$26,5,FALSE()),"")
A7: Tamaño llave: | B7: =IFERROR(VLOOKUP($B$3,LLAVES_INDEX!$A$5:$K$26,6,FALSE()),"")
A8: Ronda inicial: | B8: =IFERROR(VLOOKUP($B$3,LLAVES_INDEX!$A$5:$K$26,7,FALSE()),"")
A9: BYEs: | B9: =IFERROR(VLOOKUP($B$3,LLAVES_INDEX!$A$5:$K$26,8,FALSE()),"")
A11: POSICIONES SEEDED (1 = mejor corda / 32 = peor o BYE)
A12: Pos. | B12: Participante | C12: Corda | D12: Orden corda | E12: Estado
A13: 1 | B13: {=IFERROR(IF(LARGE(PARTICIPANTES!$R$5:$R$504,1)>0,INDEX(PARTICIPANTES!$E$5:$E$504,MATCH(LARGE(PARTICIPANTES!$R$5:$R$504,1),PARTICIPANTES!$R$5:$R$504,0)),"BYE"),"BYE")} | C13: {=IFERROR(IF(LARGE(PARTICIPANTES!$R$5:$R$504,1)>0,INDEX(PARTICIPANTES!$F$5:$F$504,MATCH(LARGE(PARTICIPANTES!$R$5:$R$504,1),PARTICIPANTES!$R$5:$R$504,0)),""),"")} | D13: {=IFERROR(IF(LARGE(PARTICIPANTES!$R$5:$R$504,1)>0,INDEX(PARTICIPANTES!$G$5:$G$504,MATCH(LARGE(PARTICIPANTES!$R$5:$R$504,1),PARTICIPANTES!$R$5:$R$504,0)),0),0)} | E13: =IF(B13="BYE","🚫 BYE","✓ Activo")
A14: 2 | B14: {=IFERROR(IF(LARGE(PARTICIPANTES!$R$5:$R$504,2)>0,INDEX(PARTICIPANTES!$E$5:$E$504,MATCH(LARGE(PARTICIPANTES!$R$5:$R$504,2),PARTICIPANTES!$R$5:$R$504,0)),"BYE"),"BYE")} | C14: {=IFERROR(IF(LARGE(PARTICIPANTES!$R$5:$R$504,2)>0,INDEX(PARTICIPANTES!$F$5:$F$504,MATCH(LARGE(PARTICIPANTES!$R$5:$R$504,2),PARTICIPANTES!$R$5:$R$504,0)),""),"")} | D14: {=IFERROR(IF(LARGE(PARTICIPANTES!$R$5:$R$504,2)>0,INDEX(PARTICIPANTES!$G$5:$G$504,MATCH(LARGE(PARTICIPANTES!$R$5:$R$504,2),PARTICIPANTES!$R$5:$R$504,0)),0),0)} | E14: =IF(B14="BYE","🚫 BYE","✓ Activo")
A15: 3 | B15: {=IFERROR(IF(LARGE(PARTICIPANTES!$R$5:$R$504,3)>0,INDEX(PARTICIPANTES!$E$5:$E$504,MATCH(LARGE(PARTICIPANTES!$R$5:$R$504,3),PARTICIPANTES!$R$5:$R$504,0)),"BYE"),"BYE")} | C15: {=IFERROR(IF(LARGE(PARTICIPANTES!$R$5:$R$504,3)>0,INDEX(PARTICIPANTES!$F$5:$F$504,MATCH(LARGE(PARTICIPANTES!$R$5:$R$504,3),PARTICIPANTES!$R$5:$R$504,0)),""),"")} | D15: {=IFERROR(IF(LARGE(PARTICIPANTES!$R$5:$R$504,3)>0,INDEX(PARTICIPANTES!$G$5:$G$504,MATCH(LARGE(PARTICIPANTES!$R$5:$R$504,3),PARTICIPANTES!$R$5:$R$504,0)),0),0)} | E15: =IF(B15="BYE","🚫 BYE","✓ Activo")
A16: 4 | B16: {=IFERROR(IF(LARGE(PARTICIPANTES!$R$5:$R$504,4)>0,INDEX(PARTICIPANTES!$E$5:$E$504,MATCH(LARGE(PARTICIPANTES!$R$5:$R$504,4),PARTICIPANTES!$R$5:$R$504,0)),"BYE"),"BYE")} | C16: {=IFERROR(IF(LARGE(PARTICIPANTES!$R$5:$R$504,4)>0,INDEX(PARTICIPANTES!$F$5:$F$504,MATCH(LARGE(PARTICIPANTES!$R$5:$R$504,4),PARTICIPANTES!$R$5:$R$504,0)),""),"")} | D16: {=IFERROR(IF(LARGE(PARTICIPANTES!$R$5:$R$504,4)>0,INDEX(PARTICIPANTES!$G$5:$G$504,MATCH(LARGE(PARTICIPANTES!$R$5:$R$504,4),PARTICIPANTES!$R$5:$R$504,0)),0),0)} | E16: =IF(B16="BYE","🚫 BYE","✓ Activo")
A17: 5 | B17: {=IFERROR(IF(LARGE(PARTICIPANTES!$R$5:$R$504,5)>0,INDEX(PARTICIPANTES!$E$5:$E$504,MATCH(LARGE(PARTICIPANTES!$R$5:$R$504,5),PARTICIPANTES!$R$5:$R$504,0)),"BYE"),"BYE")} | C17: {=IFERROR(IF(LARGE(PARTICIPANTES!$R$5:$R$504,5)>0,INDEX(PARTICIPANTES!$F$5:$F$504,MATCH(LARGE(PARTICIPANTES!$R$5:$R$504,5),PARTICIPANTES!$R$5:$R$504,0)),""),"")} | D17: {=IFERROR(IF(LARGE(PARTICIPANTES!$R$5:$R$504,5)>0,INDEX(PARTICIPANTES!$G$5:$G$504,MATCH(LARGE(PARTICIPANTES!$R$5:$R$504,5),PARTICIPANTES!$R$5:$R$504,0)),0),0)} | E17: =IF(B17="BYE","🚫 BYE","✓ Activo")
A18: 6 | B18: {=IFERROR(IF(LARGE(PARTICIPANTES!$R$5:$R$504,6)>0,INDEX(PARTICIPANTES!$E$5:$E$504,MATCH(LARGE(PARTICIPANTES!$R$5:$R$504,6),PARTICIPANTES!$R$5:$R$504,0)),"BYE"),"BYE")} | C18: {=IFERROR(IF(LARGE(PARTICIPANTES!$R$5:$R$504,6)>0,INDEX(PARTICIPANTES!$F$5:$F$504,MATCH(LARGE(PARTICIPANTES!$R$5:$R$504,6),PARTICIPANTES!$R$5:$R$504,0)),""),"")} | D18: {=IFERROR(IF(LARGE(PARTICIPANTES!$R$5:$R$504,6)>0,INDEX(PARTICIPANTES!$G$5:$G$504,MATCH(LARGE(PARTICIPANTES!$R$5:$R$504,6),PARTICIPANTES!$R$5:$R$504,0)),0),0)} | E18: =IF(B18="BYE","🚫 BYE","✓ Activo")
A19: 7 | B19: {=IFERROR(IF(LARGE(PARTICIPANTES!$R$5:$R$504,7)>0,INDEX(PARTICIPANTES!$E$5:$E$504,MATCH(LARGE(PARTICIPANTES!$R$5:$R$504,7),PARTICIPANTES!$R$5:$R$504,0)),"BYE"),"BYE")} | C19: {=IFERROR(IF(LARGE(PARTICIPANTES!$R$5:$R$504,7)>0,INDEX(PARTICIPANTES!$F$5:$F$504,MATCH(LARGE(PARTICIPANTES!$R$5:$R$504,7),PARTICIPANTES!$R$5:$R$504,0)),""),"")} | D19: {=IFERROR(IF(LARGE(PARTICIPANTES!$R$5:$R$504,7)>0,INDEX(PARTICIPANTES!$G$5:$G$504,MATCH(LARGE(PARTICIPANTES!$R$5:$R$504,7),PARTICIPANTES!$R$5:$R$504,0)),0),0)} | E19: =IF(B19="BYE","🚫 BYE","✓ Activo")
A20: 8 | B20: {=IFERROR(IF(LARGE(PARTICIPANTES!$R$5:$R$504,8)>0,INDEX(PARTICIPANTES!$E$5:$E$504,MATCH(LARGE(PARTICIPANTES!$R$5:$R$504,8),PARTICIPANTES!$R$5:$R$504,0)),"BYE"),"BYE")} | C20: {=IFERROR(IF(LARGE(PARTICIPANTES!$R$5:$R$504,8)>0,INDEX(PARTICIPANTES!$F$5:$F$504,MATCH(LARGE(PARTICIPANTES!$R$5:$R$504,8),PARTICIPANTES!$R$5:$R$504,0)),""),"")} | D20: {=IFERROR(IF(LARGE(PARTICIPANTES!$R$5:$R$504,8)>0,INDEX(PARTICIPANTES!$G$5:$G$504,MATCH(LARGE(PARTICIPANTES!$R$5:$R$504,8),PARTICIPANTES!$R$5:$R$504,0)),0),0)} | E20: =IF(B20="BYE","🚫 BYE","✓ Activo")
A21: 9 | B21: {=IFERROR(IF(LARGE(PARTICIPANTES!$R$5:$R$504,9)>0,INDEX(PARTICIPANTES!$E$5:$E$504,MATCH(LARGE(PARTICIPANTES!$R$5:$R$504,9),PARTICIPANTES!$R$5:$R$504,0)),"BYE"),"BYE")} | C21: {=IFERROR(IF(LARGE(PARTICIPANTES!$R$5:$R$504,9)>0,INDEX(PARTICIPANTES!$F$5:$F$504,MATCH(LARGE(PARTICIPANTES!$R$5:$R$504,9),PARTICIPANTES!$R$5:$R$504,0)),""),"")} | D21: {=IFERROR(IF(LARGE(PARTICIPANTES!$R$5:$R$504,9)>0,INDEX(PARTICIPANTES!$G$5:$G$504,MATCH(LARGE(PARTICIPANTES!$R$5:$R$504,9),PARTICIPANTES!$R$5:$R$504,0)),0),0)} | E21: =IF(B21="BYE","🚫 BYE","✓ Activo")
A22: 10 | B22: {=IFERROR(IF(LARGE(PARTICIPANTES!$R$5:$R$504,10)>0,INDEX(PARTICIPANTES!$E$5:$E$504,MATCH(LARGE(PARTICIPANTES!$R$5:$R$504,10),PARTICIPANTES!$R$5:$R$504,0)),"BYE"),"BYE")} | C22: {=IFERROR(IF(LARGE(PARTICIPANTES!$R$5:$R$504,10)>0,INDEX(PARTICIPANTES!$F$5:$F$504,MATCH(LARGE(PARTICIPANTES!$R$5:$R$504,10),PARTICIPANTES!$R$5:$R$504,0)),""),"")} | D22: {=IFERROR(IF(LARGE(PARTICIPANTES!$R$5:$R$504,10)>0,INDEX(PARTICIPANTES!$G$5:$G$504,MATCH(LARGE(PARTICIPANTES!$R$5:$R$504,10),PARTICIPANTES!$R$5:$R$504,0)),0),0)} | E22: =IF(B22="BYE","🚫 BYE","✓ Activo")
A23: 11 | B23: {=IFERROR(IF(LARGE(PARTICIPANTES!$R$5:$R$504,11)>0,INDEX(PARTICIPANTES!$E$5:$E$504,MATCH(LARGE(PARTICIPANTES!$R$5:$R$504,11),PARTICIPANTES!$R$5:$R$504,0)),"BYE"),"BYE")} | C23: {=IFERROR(IF(LARGE(PARTICIPANTES!$R$5:$R$504,11)>0,INDEX(PARTICIPANTES!$F$5:$F$504,MATCH(LARGE(PARTICIPANTES!$R$5:$R$504,11),PARTICIPANTES!$R$5:$R$504,0)),""),"")} | D23: {=IFERROR(IF(LARGE(PARTICIPANTES!$R$5:$R$504,11)>0,INDEX(PARTICIPANTES!$G$5:$G$504,MATCH(LARGE(PARTICIPANTES!$R$5:$R$504,11),PARTICIPANTES!$R$5:$R$504,0)),0),0)} | E23: =IF(B23="BYE","🚫 BYE","✓ Activo")
A24: 12 | B24: {=IFERROR(IF(LARGE(PARTICIPANTES!$R$5:$R$504,12)>0,INDEX(PARTICIPANTES!$E$5:$E$504,MATCH(LARGE(PARTICIPANTES!$R$5:$R$504,12),PARTICIPANTES!$R$5:$R$504,0)),"BYE"),"BYE")} | C24: {=IFERROR(IF(LARGE(PARTICIPANTES!$R$5:$R$504,12)>0,INDEX(PARTICIPANTES!$F$5:$F$504,MATCH(LARGE(PARTICIPANTES!$R$5:$R$504,12),PARTICIPANTES!$R$5:$R$504,0)),""),"")} | D24: {=IFERROR(IF(LARGE(PARTICIPANTES!$R$5:$R$504,12)>0,INDEX(PARTICIPANTES!$G$5:$G$504,MATCH(LARGE(PARTICIPANTES!$R$5:$R$504,12),PARTICIPANTES!$R$5:$R$504,0)),0),0)} | E24: =IF(B24="BYE","🚫 BYE","✓ Activo")
A25: 13 | B25: {=IFERROR(IF(LARGE(PARTICIPANTES!$R$5:$R$504,13)>0,INDEX(PARTICIPANTES!$E$5:$E$504,MATCH(LARGE(PARTICIPANTES!$R$5:$R$504,13),PARTICIPANTES!$R$5:$R$504,0)),"BYE"),"BYE")} | C25: {=IFERROR(IF(LARGE(PARTICIPANTES!$R$5:$R$504,13)>0,INDEX(PARTICIPANTES!$F$5:$F$504,MATCH(LARGE(PARTICIPANTES!$R$5:$R$504,13),PARTICIPANTES!$R$5:$R$504,0)),""),"")} | D25: {=IFERROR(IF(LARGE(PARTICIPANTES!$R$5:$R$504,13)>0,INDEX(PARTICIPANTES!$G$5:$G$504,MATCH(LARGE(PARTICIPANTES!$R$5:$R$504,13),PARTICIPANTES!$R$5:$R$504,0)),0),0)} | E25: =IF(B25="BYE","🚫 BYE","✓ Activo")
A26: 14 | B26: {=IFERROR(IF(LARGE(PARTICIPANTES!$R$5:$R$504,14)>0,INDEX(PARTICIPANTES!$E$5:$E$504,MATCH(LARGE(PARTICIPANTES!$R$5:$R$504,14),PARTICIPANTES!$R$5:$R$504,0)),"BYE"),"BYE")} | C26: {=IFERROR(IF(LARGE(PARTICIPANTES!$R$5:$R$504,14)>0,INDEX(PARTICIPANTES!$F$5:$F$504,MATCH(LARGE(PARTICIPANTES!$R$5:$R$504,14),PARTICIPANTES!$R$5:$R$504,0)),""),"")} | D26: {=IFERROR(IF(LARGE(PARTICIPANTES!$R$5:$R$504,14)>0,INDEX(PARTICIPANTES!$G$5:$G$504,MATCH(LARGE(PARTICIPANTES!$R$5:$R$504,14),PARTICIPANTES!$R$5:$R$504,0)),0),0)} | E26: =IF(B26="BYE","🚫 BYE","✓ Activo")
A27: 15 | B27: {=IFERROR(IF(LARGE(PARTICIPANTES!$R$5:$R$504,15)>0,INDEX(PARTICIPANTES!$E$5:$E$504,MATCH(LARGE(PARTICIPANTES!$R$5:$R$504,15),PARTICIPANTES!$R$5:$R$504,0)),"BYE"),"BYE")} | C27: {=IFERROR(IF(LARGE(PARTICIPANTES!$R$5:$R$504,15)>0,INDEX(PARTICIPANTES!$F$5:$F$504,MATCH(LARGE(PARTICIPANTES!$R$5:$R$504,15),PARTICIPANTES!$R$5:$R$504,0)),""),"")} | D27: {=IFERROR(IF(LARGE(PARTICIPANTES!$R$5:$R$504,15)>0,INDEX(PARTICIPANTES!$G$5:$G$504,MATCH(LARGE(PARTICIPANTES!$R$5:$R$504,15),PARTICIPANTES!$R$5:$R$504,0)),0),0)} | E27: =IF(B27="BYE","🚫 BYE","✓ Activo")
A28: 16 | B28: {=IFERROR(IF(LARGE(PARTICIPANTES!$R$5:$R$504,16)>0,INDEX(PARTICIPANTES!$E$5:$E$504,MATCH(LARGE(PARTICIPANTES!$R$5:$R$504,16),PARTICIPANTES!$R$5:$R$504,0)),"BYE"),"BYE")} | C28: {=IFERROR(IF(LARGE(PARTICIPANTES!$R$5:$R$504,16)>0,INDEX(PARTICIPANTES!$F$5:$F$504,MATCH(LARGE(PARTICIPANTES!$R$5:$R$504,16),PARTICIPANTES!$R$5:$R$504,0)),""),"")} | D28: {=IFERROR(IF(LARGE(PARTICIPANTES!$R$5:$R$504,16)>0,INDEX(PARTICIPANTES!$G$5:$G$504,MATCH(LARGE(PARTICIPANTES!$R$5:$R$504,16),PARTICIPANTES!$R$5:$R$504,0)),0),0)} | E28: =IF(B28="BYE","🚫 BYE","✓ Activo")
A29: 17 | B29: {=IFERROR(IF(LARGE(PARTICIPANTES!$R$5:$R$504,17)>0,INDEX(PARTICIPANTES!$E$5:$E$504,MATCH(LARGE(PARTICIPANTES!$R$5:$R$504,17),PARTICIPANTES!$R$5:$R$504,0)),"BYE"),"BYE")} | C29: {=IFERROR(IF(LARGE(PARTICIPANTES!$R$5:$R$504,17)>0,INDEX(PARTICIPANTES!$F$5:$F$504,MATCH(LARGE(PARTICIPANTES!$R$5:$R$504,17),PARTICIPANTES!$R$5:$R$504,0)),""),"")} | D29: {=IFERROR(IF(LARGE(PARTICIPANTES!$R$5:$R$504,17)>0,INDEX(PARTICIPANTES!$G$5:$G$504,MATCH(LARGE(PARTICIPANTES!$R$5:$R$504,17),PARTICIPANTES!$R$5:$R$504,0)),0),0)} | E29: =IF(B29="BYE","🚫 BYE","✓ Activo")
A30: 18 | B30: {=IFERROR(IF(LARGE(PARTICIPANTES!$R$5:$R$504,18)>0,INDEX(PARTICIPANTES!$E$5:$E$504,MATCH(LARGE(PARTICIPANTES!$R$5:$R$504,18),PARTICIPANTES!$R$5:$R$504,0)),"BYE"),"BYE")} | C30: {=IFERROR(IF(LARGE(PARTICIPANTES!$R$5:$R$504,18)>0,INDEX(PARTICIPANTES!$F$5:$F$504,MATCH(LARGE(PARTICIPANTES!$R$5:$R$504,18),PARTICIPANTES!$R$5:$R$504,0)),""),"")} | D30: {=IFERROR(IF(LARGE(PARTICIPANTES!$R$5:$R$504,18)>0,INDEX(PARTICIPANTES!$G$5:$G$504,MATCH(LARGE(PARTICIPANTES!$R$5:$R$504,18),PARTICIPANTES!$R$5:$R$504,0)),0),0)} | E30: =IF(B30="BYE","🚫 BYE","✓ Activo")
A31: 19 | B31: {=IFERROR(IF(LARGE(PARTICIPANTES!$R$5:$R$504,19)>0,INDEX(PARTICIPANTES!$E$5:$E$504,MATCH(LARGE(PARTICIPANTES!$R$5:$R$504,19),PARTICIPANTES!$R$5:$R$504,0)),"BYE"),"BYE")} | C31: {=IFERROR(IF(LARGE(PARTICIPANTES!$R$5:$R$504,19)>0,INDEX(PARTICIPANTES!$F$5:$F$504,MATCH(LARGE(PARTICIPANTES!$R$5:$R$504,19),PARTICIPANTES!$R$5:$R$504,0)),""),"")} | D31: {=IFERROR(IF(LARGE(PARTICIPANTES!$R$5:$R$504,19)>0,INDEX(PARTICIPANTES!$G$5:$G$504,MATCH(LARGE(PARTICIPANTES!$R$5:$R$504,19),PARTICIPANTES!$R$5:$R$504,0)),0),0)} | E31: =IF(B31="BYE","🚫 BYE","✓ Activo")
A32: 20 | B32: {=IFERROR(IF(LARGE(PARTICIPANTES!$R$5:$R$504,20)>0,INDEX(PARTICIPANTES!$E$5:$E$504,MATCH(LARGE(PARTICIPANTES!$R$5:$R$504,20),PARTICIPANTES!$R$5:$R$504,0)),"BYE"),"BYE")} | C32: {=IFERROR(IF(LARGE(PARTICIPANTES!$R$5:$R$504,20)>0,INDEX(PARTICIPANTES!$F$5:$F$504,MATCH(LARGE(PARTICIPANTES!$R$5:$R$504,20),PARTICIPANTES!$R$5:$R$504,0)),""),"")} | D32: {=IFERROR(IF(LARGE(PARTICIPANTES!$R$5:$R$504,20)>0,INDEX(PARTICIPANTES!$G$5:$G$504,MATCH(LARGE(PARTICIPANTES!$R$5:$R$504,20),PARTICIPANTES!$R$5:$R$504,0)),0),0)} | E32: =IF(B32="BYE","🚫 BYE","✓ Activo")
A33: 21 | B33: {=IFERROR(IF(LARGE(PARTICIPANTES!$R$5:$R$504,21)>0,INDEX(PARTICIPANTES!$E$5:$E$504,MATCH(LARGE(PARTICIPANTES!$R$5:$R$504,21),PARTICIPANTES!$R$5:$R$504,0)),"BYE"),"BYE")} | C33: {=IFERROR(IF(LARGE(PARTICIPANTES!$R$5:$R$504,21)>0,INDEX(PARTICIPANTES!$F$5:$F$504,MATCH(LARGE(PARTICIPANTES!$R$5:$R$504,21),PARTICIPANTES!$R$5:$R$504,0)),""),"")} | D33: {=IFERROR(IF(LARGE(PARTICIPANTES!$R$5:$R$504,21)>0,INDEX(PARTICIPANTES!$G$5:$G$504,MATCH(LARGE(PARTICIPANTES!$R$5:$R$504,21),PARTICIPANTES!$R$5:$R$504,0)),0),0)} | E33: =IF(B33="BYE","🚫 BYE","✓ Activo")
A34: 22 | B34: {=IFERROR(IF(LARGE(PARTICIPANTES!$R$5:$R$504,22)>0,INDEX(PARTICIPANTES!$E$5:$E$504,MATCH(LARGE(PARTICIPANTES!$R$5:$R$504,22),PARTICIPANTES!$R$5:$R$504,0)),"BYE"),"BYE")} | C34: {=IFERROR(IF(LARGE(PARTICIPANTES!$R$5:$R$504,22)>0,INDEX(PARTICIPANTES!$F$5:$F$504,MATCH(LARGE(PARTICIPANTES!$R$5:$R$504,22),PARTICIPANTES!$R$5:$R$504,0)),""),"")} | D34: {=IFERROR(IF(LARGE(PARTICIPANTES!$R$5:$R$504,22)>0,INDEX(PARTICIPANTES!$G$5:$G$504,MATCH(LARGE(PARTICIPANTES!$R$5:$R$504,22),PARTICIPANTES!$R$5:$R$504,0)),0),0)} | E34: =IF(B34="BYE","🚫 BYE","✓ Activo")
A35: 23 | B35: {=IFERROR(IF(LARGE(PARTICIPANTES!$R$5:$R$504,23)>0,INDEX(PARTICIPANTES!$E$5:$E$504,MATCH(LARGE(PARTICIPANTES!$R$5:$R$504,23),PARTICIPANTES!$R$5:$R$504,0)),"BYE"),"BYE")} | C35: {=IFERROR(IF(LARGE(PARTICIPANTES!$R$5:$R$504,23)>0,INDEX(PARTICIPANTES!$F$5:$F$504,MATCH(LARGE(PARTICIPANTES!$R$5:$R$504,23),PARTICIPANTES!$R$5:$R$504,0)),""),"")} | D35: {=IFERROR(IF(LARGE(PARTICIPANTES!$R$5:$R$504,23)>0,INDEX(PARTICIPANTES!$G$5:$G$504,MATCH(LARGE(PARTICIPANTES!$R$5:$R$504,23),PARTICIPANTES!$R$5:$R$504,0)),0),0)} | E35: =IF(B35="BYE","🚫 BYE","✓ Activo")
A36: 24 | B36: {=IFERROR(IF(LARGE(PARTICIPANTES!$R$5:$R$504,24)>0,INDEX(PARTICIPANTES!$E$5:$E$504,MATCH(LARGE(PARTICIPANTES!$R$5:$R$504,24),PARTICIPANTES!$R$5:$R$504,0)),"BYE"),"BYE")} | C36: {=IFERROR(IF(LARGE(PARTICIPANTES!$R$5:$R$504,24)>0,INDEX(PARTICIPANTES!$F$5:$F$504,MATCH(LARGE(PARTICIPANTES!$R$5:$R$504,24),PARTICIPANTES!$R$5:$R$504,0)),""),"")} | D36: {=IFERROR(IF(LARGE(PARTICIPANTES!$R$5:$R$504,24)>0,INDEX(PARTICIPANTES!$G$5:$G$504,MATCH(LARGE(PARTICIPANTES!$R$5:$R$504,24),PARTICIPANTES!$R$5:$R$504,0)),0),0)} | E36: =IF(B36="BYE","🚫 BYE","✓ Activo")
A37: 25 | B37: {=IFERROR(IF(LARGE(PARTICIPANTES!$R$5:$R$504,25)>0,INDEX(PARTICIPANTES!$E$5:$E$504,MATCH(LARGE(PARTICIPANTES!$R$5:$R$504,25),PARTICIPANTES!$R$5:$R$504,0)),"BYE"),"BYE")} | C37: {=IFERROR(IF(LARGE(PARTICIPANTES!$R$5:$R$504,25)>0,INDEX(PARTICIPANTES!$F$5:$F$504,MATCH(LARGE(PARTICIPANTES!$R$5:$R$504,25),PARTICIPANTES!$R$5:$R$504,0)),""),"")} | D37: {=IFERROR(IF(LARGE(PARTICIPANTES!$R$5:$R$504,25)>0,INDEX(PARTICIPANTES!$G$5:$G$504,MATCH(LARGE(PARTICIPANTES!$R$5:$R$504,25),PARTICIPANTES!$R$5:$R$504,0)),0),0)} | E37: =IF(B37="BYE","🚫 BYE","✓ Activo")
A38: 26 | B38: {=IFERROR(IF(LARGE(PARTICIPANTES!$R$5:$R$504,26)>0,INDEX(PARTICIPANTES!$E$5:$E$504,MATCH(LARGE(PARTICIPANTES!$R$5:$R$504,26),PARTICIPANTES!$R$5:$R$504,0)),"BYE"),"BYE")} | C38: {=IFERROR(IF(LARGE(PARTICIPANTES!$R$5:$R$504,26)>0,INDEX(PARTICIPANTES!$F$5:$F$504,MATCH(LARGE(PARTICIPANTES!$R$5:$R$504,26),PARTICIPANTES!$R$5:$R$504,0)),""),"")} | D38: {=IFERROR(IF(LARGE(PARTICIPANTES!$R$5:$R$504,26)>0,INDEX(PARTICIPANTES!$G$5:$G$504,MATCH(LARGE(PARTICIPANTES!$R$5:$R$504,26),PARTICIPANTES!$R$5:$R$504,0)),0),0)} | E38: =IF(B38="BYE","🚫 BYE","✓ Activo")
A39: 27 | B39: {=IFERROR(IF(LARGE(PARTICIPANTES!$R$5:$R$504,27)>0,INDEX(PARTICIPANTES!$E$5:$E$504,MATCH(LARGE(PARTICIPANTES!$R$5:$R$504,27),PARTICIPANTES!$R$5:$R$504,0)),"BYE"),"BYE")} | C39: {=IFERROR(IF(LARGE(PARTICIPANTES!$R$5:$R$504,27)>0,INDEX(PARTICIPANTES!$F$5:$F$504,MATCH(LARGE(PARTICIPANTES!$R$5:$R$504,27),PARTICIPANTES!$R$5:$R$504,0)),""),"")} | D39: {=IFERROR(IF(LARGE(PARTICIPANTES!$R$5:$R$504,27)>0,INDEX(PARTICIPANTES!$G$5:$G$504,MATCH(LARGE(PARTICIPANTES!$R$5:$R$504,27),PARTICIPANTES!$R$5:$R$504,0)),0),0)} | E39: =IF(B39="BYE","🚫 BYE","✓ Activo")
A40: 28 | B40: {=IFERROR(IF(LARGE(PARTICIPANTES!$R$5:$R$504,28)>0,INDEX(PARTICIPANTES!$E$5:$E$504,MATCH(LARGE(PARTICIPANTES!$R$5:$R$504,28),PARTICIPANTES!$R$5:$R$504,0)),"BYE"),"BYE")} | C40: {=IFERROR(IF(LARGE(PARTICIPANTES!$R$5:$R$504,28)>0,INDEX(PARTICIPANTES!$F$5:$F$504,MATCH(LARGE(PARTICIPANTES!$R$5:$R$504,28),PARTICIPANTES!$R$5:$R$504,0)),""),"")} | D40: {=IFERROR(IF(LARGE(PARTICIPANTES!$R$5:$R$504,28)>0,INDEX(PARTICIPANTES!$G$5:$G$504,MATCH(LARGE(PARTICIPANTES!$R$5:$R$504,28),PARTICIPANTES!$R$5:$R$504,0)),0),0)} | E40: =IF(B40="BYE","🚫 BYE","✓ Activo")
A41: 29 | B41: {=IFERROR(IF(LARGE(PARTICIPANTES!$R$5:$R$504,29)>0,INDEX(PARTICIPANTES!$E$5:$E$504,MATCH(LARGE(PARTICIPANTES!$R$5:$R$504,29),PARTICIPANTES!$R$5:$R$504,0)),"BYE"),"BYE")} | C41: {=IFERROR(IF(LARGE(PARTICIPANTES!$R$5:$R$504,29)>0,INDEX(PARTICIPANTES!$F$5:$F$504,MATCH(LARGE(PARTICIPANTES!$R$5:$R$504,29),PARTICIPANTES!$R$5:$R$504,0)),""),"")} | D41: {=IFERROR(IF(LARGE(PARTICIPANTES!$R$5:$R$504,29)>0,INDEX(PARTICIPANTES!$G$5:$G$504,MATCH(LARGE(PARTICIPANTES!$R$5:$R$504,29),PARTICIPANTES!$R$5:$R$504,0)),0),0)} | E41: =IF(B41="BYE","🚫 BYE","✓ Activo")
A42: 30 | B42: {=IFERROR(IF(LARGE(PARTICIPANTES!$R$5:$R$504,30)>0,INDEX(PARTICIPANTES!$E$5:$E$504,MATCH(LARGE(PARTICIPANTES!$R$5:$R$504,30),PARTICIPANTES!$R$5:$R$504,0)),"BYE"),"BYE")} | C42: {=IFERROR(IF(LARGE(PARTICIPANTES!$R$5:$R$504,30)>0,INDEX(PARTICIPANTES!$F$5:$F$504,MATCH(LARGE(PARTICIPANTES!$R$5:$R$504,30),PARTICIPANTES!$R$5:$R$504,0)),""),"")} | D42: {=IFERROR(IF(LARGE(PARTICIPANTES!$R$5:$R$504,30)>0,INDEX(PARTICIPANTES!$G$5:$G$504,MATCH(LARGE(PARTICIPANTES!$R$5:$R$504,30),PARTICIPANTES!$R$5:$R$504,0)),0),0)} | E42: =IF(B42="BYE","🚫 BYE","✓ Activo")
A43: 31 | B43: {=IFERROR(IF(LARGE(PARTICIPANTES!$R$5:$R$504,31)>0,INDEX(PARTICIPANTES!$E$5:$E$504,MATCH(LARGE(PARTICIPANTES!$R$5:$R$504,31),PARTICIPANTES!$R$5:$R$504,0)),"BYE"),"BYE")} | C43: {=IFERROR(IF(LARGE(PARTICIPANTES!$R$5:$R$504,31)>0,INDEX(PARTICIPANTES!$F$5:$F$504,MATCH(LARGE(PARTICIPANTES!$R$5:$R$504,31),PARTICIPANTES!$R$5:$R$504,0)),""),"")} | D43: {=IFERROR(IF(LARGE(PARTICIPANTES!$R$5:$R$504,31)>0,INDEX(PARTICIPANTES!$G$5:$G$504,MATCH(LARGE(PARTICIPANTES!$R$5:$R$504,31),PARTICIPANTES!$R$5:$R$504,0)),0),0)} | E43: =IF(B43="BYE","🚫 BYE","✓ Activo")
A44: 32 | B44: {=IFERROR(IF(LARGE(PARTICIPANTES!$R$5:$R$504,32)>0,INDEX(PARTICIPANTES!$E$5:$E$504,MATCH(LARGE(PARTICIPANTES!$R$5:$R$504,32),PARTICIPANTES!$R$5:$R$504,0)),"BYE"),"BYE")} | C44: {=IFERROR(IF(LARGE(PARTICIPANTES!$R$5:$R$504,32)>0,INDEX(PARTICIPANTES!$F$5:$F$504,MATCH(LARGE(PARTICIPANTES!$R$5:$R$504,32),PARTICIPANTES!$R$5:$R$504,0)),""),"")} | D44: {=IFERROR(IF(LARGE(PARTICIPANTES!$R$5:$R$504,32)>0,INDEX(PARTICIPANTES!$G$5:$G$504,MATCH(LARGE(PARTICIPANTES!$R$5:$R$504,32),PARTICIPANTES!$R$5:$R$504,0)),0),0)} | E44: =IF(B44="BYE","🚫 BYE","✓ Activo")

Sheet JUEZ_1
A1: JUEZ 1 · EVENTO COMPLETO · Rellena NOTA y puntos a quitar por jugador en cada jogo
A3: ═══ CATEGORÍA A · Masculino · Marrón (Profesores) · Toques: Benguela, São Bento da Abadá, Siriuna ═══
A4: Jogo | B4: Fase | C4: Toque | D4: Jugador A | E4: Quita A | F4: Jugador B | G4: Quita B | H4: NOTA (0-5) | I4: Final A | J4: Final B
A5: AM-32-P01-BEN | B5: Fase 32 | C5: Benguela | D5: A_A_M_32_P1 | F5: B_A_M_32_P1 | I5: =IF($H5="","",MAX(0,$H5-N($E5))) | J5: =IF($H5="","",MAX(0,$H5-N($G5)))
A6: AM-32-P01-SBA | B6: Fase 32 | C6: São Bento da Abadá | D6: A_A_M_32_P1 | F6: B_A_M_32_P1 | I6: =IF($H6="","",MAX(0,$H6-N($E6))) | J6: =IF($H6="","",MAX(0,$H6-N($G6)))
A7: AM-32-P01-SIR | B7: Fase 32 | C7: Siriuna | D7: A_A_M_32_P1 | F7: B_A_M_32_P1 | I7: =IF($H7="","",MAX(0,$H7-N($E7))) | J7: =IF($H7="","",MAX(0,$H7-N($G7)))
A8: AM-32-P02-BEN | B8: Fase 32 | C8: Benguela | D8: A_A_M_32_P2 | F8: B_A_M_32_P2 | I8: =IF($H8="","",MAX(0,$H8-N($E8))) | J8: =IF($H8="","",MAX(0,$H8-N($G8)))
A9: AM-32-P02-SBA | B9: Fase 32 | C9: São Bento da Abadá | D9: A_A_M_32_P2 | F9: B_A_M_32_P2 | I9: =IF($H9="","",MAX(0,$H9-N($E9))) | J9: =IF($H9="","",MAX(0,$H9-N($G9)))
A10: AM-32-P02-SIR | B10: Fase 32 | C10: Siriuna | D10: A_A_M_32_P2 | F10: B_A_M_32_P2 | I10: =IF($H10="","",MAX(0,$H10-N($E10))) | J10: =IF($H10="","",MAX(0,$H10-N($G10)))
A11: AM-32-P03-BEN | B11: Fase 32 | C11: Benguela | D11: A_A_M_32_P3 | F11: B_A_M_32_P3 | I11: =IF($H11="","",MAX(0,$H11-N($E11))) | J11: =IF($H11="","",MAX(0,$H11-N($G11)))
A12: AM-32-P03-SBA | B12: Fase 32 | C12: São Bento da Abadá | D12: A_A_M_32_P3 | F12: B_A_M_32_P3 | I12: =IF($H12="","",MAX(0,$H12-N($E12))) | J12: =IF($H12="","",MAX(0,$H12-N($G12)))
A13: AM-32-P03-SIR | B13: Fase 32 | C13: Siriuna | D13: A_A_M_32_P3 | F13: B_A_M_32_P3 | I13: =IF($H13="","",MAX(0,$H13-N($E13))) | J13: =IF($H13="","",MAX(0,$H13-N($G13)))
A14: AM-32-P04-BEN | B14: Fase 32 | C14: Benguela | D14: A_A_M_32_P4 | F14: B_A_M_32_P4 | I14: =IF($H14="","",MAX(0,$H14-N($E14))) | J14: =IF($H14="","",MAX(0,$H14-N($G14)))
A15: AM-32-P04-SBA | B15: Fase 32 | C15: São Bento da Abadá | D15: A_A_M_32_P4 | F15: B_A_M_32_P4 | I15: =IF($H15="","",MAX(0,$H15-N($E15))) | J15: =IF($H15="","",MAX(0,$H15-N($G15)))
A16: AM-32-P04-SIR | B16: Fase 32 | C16: Siriuna | D16: A_A_M_32_P4 | F16: B_A_M_32_P4 | I16: =IF($H16="","",MAX(0,$H16-N($E16))) | J16: =IF($H16="","",MAX(0,$H16-N($G16)))
... A52: AM-32-P16-SIR | B52: Fase 32 | C52: Siriuna | D52: A_A_M_32_P16 | F52: B_A_M_32_P16 | I52: =IF($H52="","",MAX(0,$H52-N($E52))) | J52: =IF($H52="","",MAX(0,$H52-N($G52)))
A53: AM-OCT-P01-BEN | B53: Octavas | C53: Benguela | D53: =IFERROR(CLASIF_A_M!$F$5,"") | F53: =IFERROR(CLASIF_A_M!$F$20,"") | I53: =IF($H53="","",MAX(0,$H53-N($E53))) | J53: =IF($H53="","",MAX(0,$H53-N($G53)))
A54: AM-OCT-P01-SBA | B54: Octavas | C54: São Bento da Abadá | D54: =IFERROR(CLASIF_A_M!$F$5,"") | F54: =IFERROR(CLASIF_A_M!$F$20,"") | I54: =IF($H54="","",MAX(0,$H54-N($E54))) | J54: =IF($H54="","",MAX(0,$H54-N($G54)))
A55: AM-OCT-P01-SIR | B55: Octavas | C55: Siriuna | D55: =IFERROR(CLASIF_A_M!$F$5,"") | F55: =IFERROR(CLASIF_A_M!$F$20,"") | I55: =IF($H55="","",MAX(0,$H55-N($E55))) | J55: =IF($H55="","",MAX(0,$H55-N($G55)))
A56: AM-OCT-P02-BEN | B56: Octavas | C56: Benguela | D56: =IFERROR(CLASIF_A_M!$F$6,"") | F56: =IFERROR(CLASIF_A_M!$F$19,"") | I56: =IF($H56="","",MAX(0,$H56-N($E56))) | J56: =IF($H56="","",MAX(0,$H56-N($G56)))
A57: AM-OCT-P02-SBA | B57: Octavas | C57: São Bento da Abadá | D57: =IFERROR(CLASIF_A_M!$F$6,"") | F57: =IFERROR(CLASIF_A_M!$F$19,"") | I57: =IF($H57="","",MAX(0,$H57-N($E57))) | J57: =IF($H57="","",MAX(0,$H57-N($G57)))
A58: AM-OCT-P02-SIR | B58: Octavas | C58: Siriuna | D58: =IFERROR(CLASIF_A_M!$F$6,"") | F58: =IFERROR(CLASIF_A_M!$F$19,"") | I58: =IF($H58="","",MAX(0,$H58-N($E58))) | J58: =IF($H58="","",MAX(0,$H58-N($G58)))
A59: AM-OCT-P03-BEN | B59: Octavas | C59: Benguela | D59: =IFERROR(CLASIF_A_M!$F$7,"") | F59: =IFERROR(CLASIF_A_M!$F$18,"") | I59: =IF($H59="","",MAX(0,$H59-N($E59))) | J59: =IF($H59="","",MAX(0,$H59-N($G59)))
A60: AM-OCT-P03-SBA | B60: Octavas | C60: São Bento da Abadá | D60: =IFERROR(CLASIF_A_M!$F$7,"") | F60: =IFERROR(CLASIF_A_M!$F$18,"") | I60: =IF($H60="","",MAX(0,$H60-N($E60))) | J60: =IF($H60="","",MAX(0,$H60-N($G60)))
A61: AM-OCT-P03-SIR | B61: Octavas | C61: Siriuna | D61: =IFERROR(CLASIF_A_M!$F$7,"") | F61: =IFERROR(CLASIF_A_M!$F$18,"") | I61: =IF($H61="","",MAX(0,$H61-N($E61))) | J61: =IF($H61="","",MAX(0,$H61-N($G61)))
A62: AM-OCT-P04-BEN | B62: Octavas | C62: Benguela | D62: =IFERROR(CLASIF_A_M!$F$8,"") | F62: =IFERROR(CLASIF_A_M!$F$17,"") | I62: =IF($H62="","",MAX(0,$H62-N($E62))) | J62: =IF($H62="","",MAX(0,$H62-N($G62)))
A63: AM-OCT-P04-SBA | B63: Octavas | C63: São Bento da Abadá | D63: =IFERROR(CLASIF_A_M!$F$8,"") | F63: =IFERROR(CLASIF_A_M!$F$17,"") | I63: =IF($H63="","",MAX(0,$H63-N($E63))) | J63: =IF($H63="","",MAX(0,$H63-N($G63)))
A64: AM-OCT-P04-SIR | B64: Octavas | C64: Siriuna | D64: =IFERROR(CLASIF_A_M!$F$8,"") | F64: =IFERROR(CLASIF_A_M!$F$17,"") | I64: =IF($H64="","",MAX(0,$H64-N($E64))) | J64: =IF($H64="","",MAX(0,$H64-N($G64)))
A65: AM-OCT-P05-BEN | B65: Octavas | C65: Benguela | D65: =IFERROR(CLASIF_A_M!$F$9,"") | F65: =IFERROR(CLASIF_A_M!$F$16,"") | I65: =IF($H65="","",MAX(0,$H65-N($E65))) | J65: =IF($H65="","",MAX(0,$H65-N($G65)))
A66: AM-OCT-P05-SBA | B66: Octavas | C66: São Bento da Abadá | D66: =IFERROR(CLASIF_A_M!$F$9,"") | F66: =IFERROR(CLASIF_A_M!$F$16,"") | I66: =IF($H66="","",MAX(0,$H66-N($E66))) | J66: =IF($H66="","",MAX(0,$H66-N($G66)))
A67: AM-OCT-P05-SIR | B67: Octavas | C67: Siriuna | D67: =IFERROR(CLASIF_A_M!$F$9,"") | F67: =IFERROR(CLASIF_A_M!$F$16,"") | I67: =IF($H67="","",MAX(0,$H67-N($E67))) | J67: =IF($H67="","",MAX(0,$H67-N($G67)))
A68: AM-OCT-P06-BEN | B68: Octavas | C68: Benguela | D68: =IFERROR(CLASIF_A_M!$F$10,"") | F68: =IFERROR(CLASIF_A_M!$F$15,"") | I68: =IF($H68="","",MAX(0,$H68-N($E68))) | J68: =IF($H68="","",MAX(0,$H68-N($G68)))
A69: AM-OCT-P06-SBA | B69: Octavas | C69: São Bento da Abadá | D69: =IFERROR(CLASIF_A_M!$F$10,"") | F69: =IFERROR(CLASIF_A_M!$F$15,"") | I69: =IF($H69="","",MAX(0,$H69-N($E69))) | J69: =IF($H69="","",MAX(0,$H69-N($G69)))
A70: AM-OCT-P06-SIR | B70: Octavas | C70: Siriuna | D70: =IFERROR(CLASIF_A_M!$F$10,"") | F70: =IFERROR(CLASIF_A_M!$F$15,"") | I70: =IF($H70="","",MAX(0,$H70-N($E70))) | J70: =IF($H70="","",MAX(0,$H70-N($G70)))
A71: AM-OCT-P07-BEN | B71: Octavas | C71: Benguela | D71: =IFERROR(CLASIF_A_M!$F$11,"") | F71: =IFERROR(CLASIF_A_M!$F$14,"") | I71: =IF($H71="","",MAX(0,$H71-N($E71))) | J71: =IF($H71="","",MAX(0,$H71-N($G71)))
A72: AM-OCT-P07-SBA | B72: Octavas | C72: São Bento da Abadá | D72: =IFERROR(CLASIF_A_M!$F$11,"") | F72: =IFERROR(CLASIF_A_M!$F$14,"") | I72: =IF($H72="","",MAX(0,$H72-N($E72))) | J72: =IF($H72="","",MAX(0,$H72-N($G72)))
A73: AM-OCT-P07-SIR | B73: Octavas | C73: Siriuna | D73: =IFERROR(CLASIF_A_M!$F$11,"") | F73: =IFERROR(CLASIF_A_M!$F$14,"") | I73: =IF($H73="","",MAX(0,$H73-N($E73))) | J73: =IF($H73="","",MAX(0,$H73-N($G73)))
A74: AM-OCT-P08-BEN | B74: Octavas | C74: Benguela | D74: =IFERROR(CLASIF_A_M!$F$12,"") | F74: =IFERROR(CLASIF_A_M!$F$13,"") | I74: =IF($H74="","",MAX(0,$H74-N($E74))) | J74: =IF($H74="","",MAX(0,$H74-N($G74)))
A75: AM-OCT-P08-SBA | B75: Octavas | C75: São Bento da Abadá | D75: =IFERROR(CLASIF_A_M!$F$12,"") | F75: =IFERROR(CLASIF_A_M!$F$13,"") | I75: =IF($H75="","",MAX(0,$H75-N($E75))) | J75: =IF($H75="","",MAX(0,$H75-N($G75)))
A76: AM-OCT-P08-SIR | B76: Octavas | C76: Siriuna | D76: =IFERROR(CLASIF_A_M!$F$12,"") | F76: =IFERROR(CLASIF_A_M!$F$13,"") | I76: =IF($H76="","",MAX(0,$H76-N($E76))) | J76: =IF($H76="","",MAX(0,$H76-N($G76)))
A77: AM-SEM-P01-BEN | B77: Semifinal | C77: Benguela | D77: =IFERROR(CLASIF_A_M!$O$5,"") | F77: =IFERROR(CLASIF_A_M!$O$12,"") | I77: =IF($H77="","",MAX(0,$H77-N($E77))) | J77: =IF($H77="","",MAX(0,$H77-N($G77)))
A78: AM-SEM-P01-SBA | B78: Semifinal | C78: São Bento da Abadá | D78: =IFERROR(CLASIF_A_M!$O$5,"") | F78: =IFERROR(CLASIF_A_M!$O$12,"") | I78: =IF($H78="","",MAX(0,$H78-N($E78))) | J78: =IF($H78="","",MAX(0,$H78-N($G78)))
A79: AM-SEM-P01-SIR | B79: Semifinal | C79: Siriuna | D79: =IFERROR(CLASIF_A_M!$O$5,"") | F79: =IFERROR(CLASIF_A_M!$O$12,"") | I79: =IF($H79="","",MAX(0,$H79-N($E79))) | J79: =IF($H79="","",MAX(0,$H79-N($G79)))
A80: AM-SEM-P02-BEN | B80: Semifinal | C80: Benguela | D80: =IFERROR(CLASIF_A_M!$O$6,"") | F80: =IFERROR(CLASIF_A_M!$O$11,"") | I80: =IF($H80="","",MAX(0,$H80-N($E80))) | J80: =IF($H80="","",MAX(0,$H80-N($G80)))
A81: AM-SEM-P02-SBA | B81: Semifinal | C81: São Bento da Abadá | D81: =IFERROR(CLASIF_A_M!$O$6,"") | F81: =IFERROR(CLASIF_A_M!$O$11,"") | I81: =IF($H81="","",MAX(0,$H81-N($E81))) | J81: =IF($H81="","",MAX(0,$H81-N($G81)))
A82: AM-SEM-P02-SIR | B82: Semifinal | C82: Siriuna | D82: =IFERROR(CLASIF_A_M!$O$6,"") | F82: =IFERROR(CLASIF_A_M!$O$11,"") | I82: =IF($H82="","",MAX(0,$H82-N($E82))) | J82: =IF($H82="","",MAX(0,$H82-N($G82)))
A83: AM-SEM-P03-BEN | B83: Semifinal | C83: Benguela | D83: =IFERROR(CLASIF_A_M!$O$7,"") | F83: =IFERROR(CLASIF_A_M!$O$10,"") | I83: =IF($H83="","",MAX(0,$H83-N($E83))) | J83: =IF($H83="","",MAX(0,$H83-N($G83)))
A84: AM-SEM-P03-SBA | B84: Semifinal | C84: São Bento da Abadá | D84: =IFERROR(CLASIF_A_M!$O$7,"") | F84: =IFERROR(CLASIF_A_M!$O$10,"") | I84: =IF($H84="","",MAX(0,$H84-N($E84))) | J84: =IF($H84="","",MAX(0,$H84-N($G84)))
A85: AM-SEM-P03-SIR | B85: Semifinal | C85: Siriuna | D85: =IFERROR(CLASIF_A_M!$O$7,"") | F85: =IFERROR(CLASIF_A_M!$O$10,"") | I85: =IF($H85="","",MAX(0,$H85-N($E85))) | J85: =IF($H85="","",MAX(0,$H85-N($G85)))
A86: AM-SEM-P04-BEN | B86: Semifinal | C86: Benguela | D86: =IFERROR(CLASIF_A_M!$O$8,"") | F86: =IFERROR(CLASIF_A_M!$O$9,"") | I86: =IF($H86="","",MAX(0,$H86-N($E86))) | J86: =IF($H86="","",MAX(0,$H86-N($G86)))
A87: AM-SEM-P04-SBA | B87: Semifinal | C87: São Bento da Abadá | D87: =IFERROR(CLASIF_A_M!$O$8,"") | F87: =IFERROR(CLASIF_A_M!$O$9,"") | I87: =IF($H87="","",MAX(0,$H87-N($E87))) | J87: =IF($H87="","",MAX(0,$H87-N($G87)))
A88: AM-SEM-P04-SIR | B88: Semifinal | C88: Siriuna | D88: =IFERROR(CLASIF_A_M!$O$8,"") | F88: =IFERROR(CLASIF_A_M!$O$9,"") | I88: =IF($H88="","",MAX(0,$H88-N($E88))) | J88: =IF($H88="","",MAX(0,$H88-N($G88)))
A89: AM-FIN-P01-BEN | B89: Final | C89: Benguela | D89: =IFERROR(CLASIF_A_M!$X$5,"") | F89: =IFERROR(CLASIF_A_M!$X$8,"") | I89: =IF($H89="","",MAX(0,$H89-N($E89))) | J89: =IF($H89="","",MAX(0,$H89-N($G89)))
A90: AM-FIN-P01-SBA | B90: Final | C90: São Bento da Abadá | D90: =IFERROR(CLASIF_A_M!$X$5,"") | F90: =IFERROR(CLASIF_A_M!$X$8,"") | I90: =IF($H90="","",MAX(0,$H90-N($E90))) | J90: =IF($H90="","",MAX(0,$H90-N($G90)))
A91: AM-FIN-P01-SIR | B91: Final | C91: Siriuna | D91: =IFERROR(CLASIF_A_M!$X$5,"") | F91: =IFERROR(CLASIF_A_M!$X$8,"") | I91: =IF($H91="","",MAX(0,$H91-N($E91))) | J91: =IF($H91="","",MAX(0,$H91-N($G91)))
A92: AM-FIN-P02-BEN | B92: Final | C92: Benguela | D92: =IFERROR(CLASIF_A_M!$X$6,"") | F92: =IFERROR(CLASIF_A_M!$X$7,"") | I92: =IF($H92="","",MAX(0,$H92-N($E92))) | J92: =IF($H92="","",MAX(0,$H92-N($G92)))
A93: AM-FIN-P02-SBA | B93: Final | C93: São Bento da Abadá | D93: =IFERROR(CLASIF_A_M!$X$6,"") | F93: =IFERROR(CLASIF_A_M!$X$7,"") | I93: =IF($H93="","",MAX(0,$H93-N($E93))) | J93: =IF($H93="","",MAX(0,$H93-N($G93)))
A94: AM-FIN-P02-SIR | B94: Final | C94: Siriuna | D94: =IFERROR(CLASIF_A_M!$X$6,"") | F94: =IFERROR(CLASIF_A_M!$X$7,"") | I94: =IF($H94="","",MAX(0,$H94-N($E94))) | J94: =IF($H94="","",MAX(0,$H94-N($G94)))
I95: =IF($H95="","",MAX(0,$H95-N($E95))) | J95: =IF($H95="","",MAX(0,$H95-N($G95)))
A96: ═══ CATEGORÍA A · Femenino · Marrón (Profesores) · Toques: Benguela, São Bento da Abadá, Siriuna ═══
A97: Jogo | B97: Fase | C97: Toque | D97: Jugador A | E97: Quita A | F97: Jugador B | G97: Quita B | H97: NOTA (0-5) | I97: =IF($H97="","",MAX(0,$H97-N($E97))) | J97: =IF($H97="","",MAX(0,$H97-N($G97)))
A98: AF-32-P01-BEN | B98: Fase 32 | C98: Benguela | D98: A_A_F_32_P1 | F98: B_A_F_32_P1 | I98: =IF($H98="","",MAX(0,$H98-N($E98))) | J98: =IF($H98="","",MAX(0,$H98-N($G98)))
A99: AF-32-P01-SBA | B99: Fase 32 | C99: São Bento da Abadá | D99: A_A_F_32_P1 | F99: B_A_F_32_P1 | I99: =IF($H99="","",MAX(0,$H99-N($E99))) | J99: =IF($H99="","",MAX(0,$H99-N($G99)))
A100: AF-32-P01-SIR | B100: Fase 32 | C100: Siriuna | D100: A_A_F_32_P1 | F100: B_A_F_32_P1 | I100: =IF($H100="","",MAX(0,$H100-N($E100))) | J100: =IF($H100="","",MAX(0,$H100-N($G100)))
A101: AF-32-P02-BEN | B101: Fase 32 | C101: Benguela | D101: A_A_F_32_P2 | F101: B_A_F_32_P2 | I101: =IF($H101="","",MAX(0,$H101-N($E101))) | J101: =IF($H101="","",MAX(0,$H101-N($G101)))
A102: AF-32-P02-SBA | B102: Fase 32 | C102: São Bento da Abadá | D102: A_A_F_32_P2 | F102: B_A_F_32_P2 | I102: =IF($H102="","",MAX(0,$H102-N($E102))) | J102: =IF($H102="","",MAX(0,$H102-N($G102)))
A103: AF-32-P02-SIR | B103: Fase 32 | C103: Siriuna | D103: A_A_F_32_P2 | F103: B_A_F_32_P2 | I103: =IF($H103="","",MAX(0,$H103-N($E103))) | J103: =IF($H103="","",MAX(0,$H103-N($G103)))
A104: AF-32-P03-BEN | B104: Fase 32 | C104: Benguela | D104: A_A_F_32_P3 | F104: B_A_F_32_P3 | I104: =IF($H104="","",MAX(0,$H104-N($E104))) | J104: =IF($H104="","",MAX(0,$H104-N($G104)))
A105: AF-32-P03-SBA | B105: Fase 32 | C105: São Bento da Abadá | D105: A_A_F_32_P3 | F105: B_A_F_32_P3 | I105: =IF($H105="","",MAX(0,$H105-N($E105))) | J105: =IF($H105="","",MAX(0,$H105-N($G105)))
A106: AF-32-P03-SIR | B106: Fase 32 | C106: Siriuna | D106: A_A_F_32_P3 | F106: B_A_F_32_P3 | I106: =IF($H106="","",MAX(0,$H106-N($E106))) | J106: =IF($H106="","",MAX(0,$H106-N($G106)))
A107: AF-32-P04-BEN | B107: Fase 32 | C107: Benguela | D107: A_A_F_32_P4 | F107: B_A_F_32_P4 | I107: =IF($H107="","",MAX(0,$H107-N($E107))) | J107: =IF($H107="","",MAX(0,$H107-N($G107)))
A108: AF-32-P04-SBA | B108: Fase 32 | C108: São Bento da Abadá | D108: A_A_F_32_P4 | F108: B_A_F_32_P4 | I108: =IF($H108="","",MAX(0,$H108-N($E108))) | J108: =IF($H108="","",MAX(0,$H108-N($G108)))
A109: AF-32-P04-SIR | B109: Fase 32 | C109: Siriuna | D109: A_A_F_32_P4 | F109: B_A_F_32_P4 | I109: =IF($H109="","",MAX(0,$H109-N($E109))) | J109: =IF($H109="","",MAX(0,$H109-N($G109)))
... A145: AF-32-P16-SIR | B145: Fase 32 | C145: Siriuna | D145: A_A_F_32_P16 | F145: B_A_F_32_P16 | I145: =IF($H145="","",MAX(0,$H145-N($E145))) | J145: =IF($H145="","",MAX(0,$H145-N($G145)))
A146: AF-OCT-P01-BEN | B146: Octavas | C146: Benguela | D146: =IFERROR(CLASIF_A_F!$F$5,"") | F146: =IFERROR(CLASIF_A_F!$F$20,"") | I146: =IF($H146="","",MAX(0,$H146-N($E146))) | J146: =IF($H146="","",MAX(0,$H146-N($G146)))
A147: AF-OCT-P01-SBA | B147: Octavas | C147: São Bento da Abadá | D147: =IFERROR(CLASIF_A_F!$F$5,"") | F147: =IFERROR(CLASIF_A_F!$F$20,"") | I147: =IF($H147="","",MAX(0,$H147-N($E147))) | J147: =IF($H147="","",MAX(0,$H147-N($G147)))
A148: AF-OCT-P01-SIR | B148: Octavas | C148: Siriuna | D148: =IFERROR(CLASIF_A_F!$F$5,"") | F148: =IFERROR(CLASIF_A_F!$F$20,"") | I148: =IF($H148="","",MAX(0,$H148-N($E148))) | J148: =IF($H148="","",MAX(0,$H148-N($G148)))
A149: AF-OCT-P02-BEN | B149: Octavas | C149: Benguela | D149: =IFERROR(CLASIF_A_F!$F$6,"") | F149: =IFERROR(CLASIF_A_F!$F$19,"") | I149: =IF($H149="","",MAX(0,$H149-N($E149))) | J149: =IF($H149="","",MAX(0,$H149-N($G149)))
A150: AF-OCT-P02-SBA | B150: Octavas | C150: São Bento da Abadá | D150: =IFERROR(CLASIF_A_F!$F$6,"") | F150: =IFERROR(CLASIF_A_F!$F$19,"") | I150: =IF($H150="","",MAX(0,$H150-N($E150))) | J150: =IF($H150="","",MAX(0,$H150-N($G150)))
A151: AF-OCT-P02-SIR | B151: Octavas | C151: Siriuna | D151: =IFERROR(CLASIF_A_F!$F$6,"") | F151: =IFERROR(CLASIF_A_F!$F$19,"") | I151: =IF($H151="","",MAX(0,$H151-N($E151))) | J151: =IF($H151="","",MAX(0,$H151-N($G151)))
A152: AF-OCT-P03-BEN | B152: Octavas | C152: Benguela | D152: =IFERROR(CLASIF_A_F!$F$7,"") | F152: =IFERROR(CLASIF_A_F!$F$18,"") | I152: =IF($H152="","",MAX(0,$H152-N($E152))) | J152: =IF($H152="","",MAX(0,$H152-N($G152)))
A153: AF-OCT-P03-SBA | B153: Octavas | C153: São Bento da Abadá | D153: =IFERROR(CLASIF_A_F!$F$7,"") | F153: =IFERROR(CLASIF_A_F!$F$18,"") | I153: =IF($H153="","",MAX(0,$H153-N($E153))) | J153: =IF($H153="","",MAX(0,$H153-N($G153)))
A154: AF-OCT-P03-SIR | B154: Octavas | C154: Siriuna | D154: =IFERROR(CLASIF_A_F!$F$7,"") | F154: =IFERROR(CLASIF_A_F!$F$18,"") | I154: =IF($H154="","",MAX(0,$H154-N($E154))) | J154: =IF($H154="","",MAX(0,$H154-N($G154)))
A155: AF-OCT-P04-BEN | B155: Octavas | C155: Benguela | D155: =IFERROR(CLASIF_A_F!$F$8,"") | F155: =IFERROR(CLASIF_A_F!$F$17,"") | I155: =IF($H155="","",MAX(0,$H155-N($E155))) | J155: =IF($H155="","",MAX(0,$H155-N($G155)))
A156: AF-OCT-P04-SBA | B156: Octavas | C156: São Bento da Abadá | D156: =IFERROR(CLASIF_A_F!$F$8,"") | F156: =IFERROR(CLASIF_A_F!$F$17,"") | I156: =IF($H156="","",MAX(0,$H156-N($E156))) | J156: =IF($H156="","",MAX(0,$H156-N($G156)))
A157: AF-OCT-P04-SIR | B157: Octavas | C157: Siriuna | D157: =IFERROR(CLASIF_A_F!$F$8,"") | F157: =IFERROR(CLASIF_A_F!$F$17,"") | I157: =IF($H157="","",MAX(0,$H157-N($E157))) | J157: =IF($H157="","",MAX(0,$H157-N($G157)))
A158: AF-OCT-P05-BEN | B158: Octavas | C158: Benguela | D158: =IFERROR(CLASIF_A_F!$F$9,"") | F158: =IFERROR(CLASIF_A_F!$F$16,"") | I158: =IF($H158="","",MAX(0,$H158-N($E158))) | J158: =IF($H158="","",MAX(0,$H158-N($G158)))
A159: AF-OCT-P05-SBA | B159: Octavas | C159: São Bento da Abadá | D159: =IFERROR(CLASIF_A_F!$F$9,"") | F159: =IFERROR(CLASIF_A_F!$F$16,"") | I159: =IF($H159="","",MAX(0,$H159-N($E159))) | J159: =IF($H159="","",MAX(0,$H159-N($G159)))
A160: AF-OCT-P05-SIR | B160: Octavas | C160: Siriuna | D160: =IFERROR(CLASIF_A_F!$F$9,"") | F160: =IFERROR(CLASIF_A_F!$F$16,"") | I160: =IF($H160="","",MAX(0,$H160-N($E160))) | J160: =IF($H160="","",MAX(0,$H160-N($G160)))
A161: AF-OCT-P06-BEN | B161: Octavas | C161: Benguela | D161: =IFERROR(CLASIF_A_F!$F$10,"") | F161: =IFERROR(CLASIF_A_F!$F$15,"") | I161: =IF($H161="","",MAX(0,$H161-N($E161))) | J161: =IF($H161="","",MAX(0,$H161-N($G161)))
A162: AF-OCT-P06-SBA | B162: Octavas | C162: São Bento da Abadá | D162: =IFERROR(CLASIF_A_F!$F$10,"") | F162: =IFERROR(CLASIF_A_F!$F$15,"") | I162: =IF($H162="","",MAX(0,$H162-N($E162))) | J162: =IF($H162="","",MAX(0,$H162-N($G162)))
A163: AF-OCT-P06-SIR | B163: Octavas | C163: Siriuna | D163: =IFERROR(CLASIF_A_F!$F$10,"") | F163: =IFERROR(CLASIF_A_F!$F$15,"") | I163: =IF($H163="","",MAX(0,$H163-N($E163))) | J163: =IF($H163="","",MAX(0,$H163-N($G163)))
A164: AF-OCT-P07-BEN | B164: Octavas | C164: Benguela | D164: =IFERROR(CLASIF_A_F!$F$11,"") | F164: =IFERROR(CLASIF_A_F!$F$14,"") | I164: =IF($H164="","",MAX(0,$H164-N($E164))) | J164: =IF($H164="","",MAX(0,$H164-N($G164)))
A165: AF-OCT-P07-SBA | B165: Octavas | C165: São Bento da Abadá | D165: =IFERROR(CLASIF_A_F!$F$11,"") | F165: =IFERROR(CLASIF_A_F!$F$14,"") | I165: =IF($H165="","",MAX(0,$H165-N($E165))) | J165: =IF($H165="","",MAX(0,$H165-N($G165)))
A166: AF-OCT-P07-SIR | B166: Octavas | C166: Siriuna | D166: =IFERROR(CLASIF_A_F!$F$11,"") | F166: =IFERROR(CLASIF_A_F!$F$14,"") | I166: =IF($H166="","",MAX(0,$H166-N($E166))) | J166: =IF($H166="","",MAX(0,$H166-N($G166)))
A167: AF-OCT-P08-BEN | B167: Octavas | C167: Benguela | D167: =IFERROR(CLASIF_A_F!$F$12,"") | F167: =IFERROR(CLASIF_A_F!$F$13,"") | I167: =IF($H167="","",MAX(0,$H167-N($E167))) | J167: =IF($H167="","",MAX(0,$H167-N($G167)))
A168: AF-OCT-P08-SBA | B168: Octavas | C168: São Bento da Abadá | D168: =IFERROR(CLASIF_A_F!$F$12,"") | F168: =IFERROR(CLASIF_A_F!$F$13,"") | I168: =IF($H168="","",MAX(0,$H168-N($E168))) | J168: =IF($H168="","",MAX(0,$H168-N($G168)))
A169: AF-OCT-P08-SIR | B169: Octavas | C169: Siriuna | D169: =IFERROR(CLASIF_A_F!$F$12,"") | F169: =IFERROR(CLASIF_A_F!$F$13,"") | I169: =IF($H169="","",MAX(0,$H169-N($E169))) | J169: =IF($H169="","",MAX(0,$H169-N($G169)))
A170: AF-SEM-P01-BEN | B170: Semifinal | C170: Benguela | D170: =IFERROR(CLASIF_A_F!$O$5,"") | F170: =IFERROR(CLASIF_A_F!$O$12,"") | I170: =IF($H170="","",MAX(0,$H170-N($E170))) | J170: =IF($H170="","",MAX(0,$H170-N($G170)))
A171: AF-SEM-P01-SBA | B171: Semifinal | C171: São Bento da Abadá | D171: =IFERROR(CLASIF_A_F!$O$5,"") | F171: =IFERROR(CLASIF_A_F!$O$12,"") | I171: =IF($H171="","",MAX(0,$H171-N($E171))) | J171: =IF($H171="","",MAX(0,$H171-N($G171)))
...

Sheet JUEZ_2
A1: JUEZ 2 · EVENTO COMPLETO · Rellena NOTA y puntos a quitar por jugador en cada jogo
A3: ═══ CATEGORÍA A · Masculino · Marrón (Profesores) · Toques: Benguela, São Bento da Abadá, Siriuna ═══
A4: Jogo | B4: Fase | C4: Toque | D4: Jugador A | E4: Quita A | F4: Jugador B | G4: Quita B | H4: NOTA (0-5) | I4: Final A | J4: Final B
A5: AM-32-P01-BEN | B5: Fase 32 | C5: Benguela | D5: A_A_M_32_P1 | F5: B_A_M_32_P1 | I5: =IF($H5="","",MAX(0,$H5-N($E5))) | J5: =IF($H5="","",MAX(0,$H5-N($G5)))
A6: AM-32-P01-SBA | B6: Fase 32 | C6: São Bento da Abadá | D6: A_A_M_32_P1 | F6: B_A_M_32_P1 | I6: =IF($H6="","",MAX(0,$H6-N($E6))) | J6: =IF($H6="","",MAX(0,$H6-N($G6)))
A7: AM-32-P01-SIR | B7: Fase 32 | C7: Siriuna | D7: A_A_M_32_P1 | F7: B_A_M_32_P1 | I7: =IF($H7="","",MAX(0,$H7-N($E7))) | J7: =IF($H7="","",MAX(0,$H7-N($G7)))
A8: AM-32-P02-BEN | B8: Fase 32 | C8: Benguela | D8: A_A_M_32_P2 | F8: B_A_M_32_P2 | I8: =IF($H8="","",MAX(0,$H8-N($E8))) | J8: =IF($H8="","",MAX(0,$H8-N($G8)))
A9: AM-32-P02-SBA | B9: Fase 32 | C9: São Bento da Abadá | D9: A_A_M_32_P2 | F9: B_A_M_32_P2 | I9: =IF($H9="","",MAX(0,$H9-N($E9))) | J9: =IF($H9="","",MAX(0,$H9-N($G9)))
A10: AM-32-P02-SIR | B10: Fase 32 | C10: Siriuna | D10: A_A_M_32_P2 | F10: B_A_M_32_P2 | I10: =IF($H10="","",MAX(0,$H10-N($E10))) | J10: =IF($H10="","",MAX(0,$H10-N($G10)))
A11: AM-32-P03-BEN | B11: Fase 32 | C11: Benguela | D11: A_A_M_32_P3 | F11: B_A_M_32_P3 | I11: =IF($H11="","",MAX(0,$H11-N($E11))) | J11: =IF($H11="","",MAX(0,$H11-N($G11)))
A12: AM-32-P03-SBA | B12: Fase 32 | C12: São Bento da Abadá | D12: A_A_M_32_P3 | F12: B_A_M_32_P3 | I12: =IF($H12="","",MAX(0,$H12-N($E12))) | J12: =IF($H12="","",MAX(0,$H12-N($G12)))
A13: AM-32-P03-SIR | B13: Fase 32 | C13: Siriuna | D13: A_A_M_32_P3 | F13: B_A_M_32_P3 | I13: =IF($H13="","",MAX(0,$H13-N($E13))) | J13: =IF($H13="","",MAX(0,$H13-N($G13)))
A14: AM-32-P04-BEN | B14: Fase 32 | C14: Benguela | D14: A_A_M_32_P4 | F14: B_A_M_32_P4 | I14: =IF($H14="","",MAX(0,$H14-N($E14))) | J14: =IF($H14="","",MAX(0,$H14-N($G14)))
A15: AM-32-P04-SBA | B15: Fase 32 | C15: São Bento da Abadá | D15: A_A_M_32_P4 | F15: B_A_M_32_P4 | I15: =IF($H15="","",MAX(0,$H15-N($E15))) | J15: =IF($H15="","",MAX(0,$H15-N($G15)))
A16: AM-32-P04-SIR | B16: Fase 32 | C16: Siriuna | D16: A_A_M_32_P4 | F16: B_A_M_32_P4 | I16: =IF($H16="","",MAX(0,$H16-N($E16))) | J16: =IF($H16="","",MAX(0,$H16-N($G16)))
... A52: AM-32-P16-SIR | B52: Fase 32 | C52: Siriuna | D52: A_A_M_32_P16 | F52: B_A_M_32_P16 | I52: =IF($H52="","",MAX(0,$H52-N($E52))) | J52: =IF($H52="","",MAX(0,$H52-N($G52)))
A53: AM-OCT-P01-BEN | B53: Octavas | C53: Benguela | D53: =IFERROR(CLASIF_A_M!$F$5,"") | F53: =IFERROR(CLASIF_A_M!$F$20,"") | I53: =IF($H53="","",MAX(0,$H53-N($E53))) | J53: =IF($H53="","",MAX(0,$H53-N($G53)))
A54: AM-OCT-P01-SBA | B54: Octavas | C54: São Bento da Abadá | D54: =IFERROR(CLASIF_A_M!$F$5,"") | F54: =IFERROR(CLASIF_A_M!$F$20,"") | I54: =IF($H54="","",MAX(0,$H54-N($E54))) | J54: =IF($H54="","",MAX(0,$H54-N($G54)))
A55: AM-OCT-P01-SIR | B55: Octavas | C55: Siriuna | D55: =IFERROR(CLASIF_A_M!$F$5,"") | F55: =IFERROR(CLASIF_A_M!$F$20,"") | I55: =IF($H55="","",MAX(0,$H55-N($E55))) | J55: =IF($H55="","",MAX(0,$H55-N($G55)))
A56: AM-OCT-P02-BEN | B56: Octavas | C56: Benguela | D56: =IFERROR(CLASIF_A_M!$F$6,"") | F56: =IFERROR(CLASIF_A_M!$F$19,"") | I56: =IF($H56="","",MAX(0,$H56-N($E56))) | J56: =IF($H56="","",MAX(0,$H56-N($G56)))
A57: AM-OCT-P02-SBA | B57: Octavas | C57: São Bento da Abadá | D57: =IFERROR(CLASIF_A_M!$F$6,"") | F57: =IFERROR(CLASIF_A_M!$F$19,"") | I57: =IF($H57="","",MAX(0,$H57-N($E57))) | J57: =IF($H57="","",MAX(0,$H57-N($G57)))
A58: AM-OCT-P02-SIR | B58: Octavas | C58: Siriuna | D58: =IFERROR(CLASIF_A_M!$F$6,"") | F58: =IFERROR(CLASIF_A_M!$F$19,"") | I58: =IF($H58="","",MAX(0,$H58-N($E58))) | J58: =IF($H58="","",MAX(0,$H58-N($G58)))
A59: AM-OCT-P03-BEN | B59: Octavas | C59: Benguela | D59: =IFERROR(CLASIF_A_M!$F$7,"") | F59: =IFERROR(CLASIF_A_M!$F$18,"") | I59: =IF($H59="","",MAX(0,$H59-N($E59))) | J59: =IF($H59="","",MAX(0,$H59-N($G59)))
A60: AM-OCT-P03-SBA | B60: Octavas | C60: São Bento da Abadá | D60: =IFERROR(CLASIF_A_M!$F$7,"") | F60: =IFERROR(CLASIF_A_M!$F$18,"") | I60: =IF($H60="","",MAX(0,$H60-N($E60))) | J60: =IF($H60="","",MAX(0,$H60-N($G60)))
A61: AM-OCT-P03-SIR | B61: Octavas | C61: Siriuna | D61: =IFERROR(CLASIF_A_M!$F$7,"") | F61: =IFERROR(CLASIF_A_M!$F$18,"") | I61: =IF($H61="","",MAX(0,$H61-N($E61))) | J61: =IF($H61="","",MAX(0,$H61-N($G61)))
A62: AM-OCT-P04-BEN | B62: Octavas | C62: Benguela | D62: =IFERROR(CLASIF_A_M!$F$8,"") | F62: =IFERROR(CLASIF_A_M!$F$17,"") | I62: =IF($H62="","",MAX(0,$H62-N($E62))) | J62: =IF($H62="","",MAX(0,$H62-N($G62)))
A63: AM-OCT-P04-SBA | B63: Octavas | C63: São Bento da Abadá | D63: =IFERROR(CLASIF_A_M!$F$8,"") | F63: =IFERROR(CLASIF_A_M!$F$17,"") | I63: =IF($H63="","",MAX(0,$H63-N($E63))) | J63: =IF($H63="","",MAX(0,$H63-N($G63)))
A64: AM-OCT-P04-SIR | B64: Octavas | C64: Siriuna | D64: =IFERROR(CLASIF_A_M!$F$8,"") | F64: =IFERROR(CLASIF_A_M!$F$17,"") | I64: =IF($H64="","",MAX(0,$H64-N($E64))) | J64: =IF($H64="","",MAX(0,$H64-N($G64)))
A65: AM-OCT-P05-BEN | B65: Octavas | C65: Benguela | D65: =IFERROR(CLASIF_A_M!$F$9,"") | F65: =IFERROR(CLASIF_A_M!$F$16,"") | I65: =IF($H65="","",MAX(0,$H65-N($E65))) | J65: =IF($H65="","",MAX(0,$H65-N($G65)))
A66: AM-OCT-P05-SBA | B66: Octavas | C66: São Bento da Abadá | D66: =IFERROR(CLASIF_A_M!$F$9,"") | F66: =IFERROR(CLASIF_A_M!$F$16,"") | I66: =IF($H66="","",MAX(0,$H66-N($E66))) | J66: =IF($H66="","",MAX(0,$H66-N($G66)))
A67: AM-OCT-P05-SIR | B67: Octavas | C67: Siriuna | D67: =IFERROR(CLASIF_A_M!$F$9,"") | F67: =IFERROR(CLASIF_A_M!$F$16,"") | I67: =IF($H67="","",MAX(0,$H67-N($E67))) | J67: =IF($H67="","",MAX(0,$H67-N($G67)))
A68: AM-OCT-P06-BEN | B68: Octavas | C68: Benguela | D68: =IFERROR(CLASIF_A_M!$F$10,"") | F68: =IFERROR(CLASIF_A_M!$F$15,"") | I68: =IF($H68="","",MAX(0,$H68-N($E68))) | J68: =IF($H68="","",MAX(0,$H68-N($G68)))
A69: AM-OCT-P06-SBA | B69: Octavas | C69: São Bento da Abadá | D69: =IFERROR(CLASIF_A_M!$F$10,"") | F69: =IFERROR(CLASIF_A_M!$F$15,"") | I69: =IF($H69="","",MAX(0,$H69-N($E69))) | J69: =IF($H69="","",MAX(0,$H69-N($G69)))
A70: AM-OCT-P06-SIR | B70: Octavas | C70: Siriuna | D70: =IFERROR(CLASIF_A_M!$F$10,"") | F70: =IFERROR(CLASIF_A_M!$F$15,"") | I70: =IF($H70="","",MAX(0,$H70-N($E70))) | J70: =IF($H70="","",MAX(0,$H70-N($G70)))
A71: AM-OCT-P07-BEN | B71: Octavas | C71: Benguela | D71: =IFERROR(CLASIF_A_M!$F$11,"") | F71: =IFERROR(CLASIF_A_M!$F$14,"") | I71: =IF($H71="","",MAX(0,$H71-N($E71))) | J71: =IF($H71="","",MAX(0,$H71-N($G71)))
A72: AM-OCT-P07-SBA | B72: Octavas | C72: São Bento da Abadá | D72: =IFERROR(CLASIF_A_M!$F$11,"") | F72: =IFERROR(CLASIF_A_M!$F$14,"") | I72: =IF($H72="","",MAX(0,$H72-N($E72))) | J72: =IF($H72="","",MAX(0,$H72-N($G72)))
A73: AM-OCT-P07-SIR | B73: Octavas | C73: Siriuna | D73: =IFERROR(CLASIF_A_M!$F$11,"") | F73: =IFERROR(CLASIF_A_M!$F$14,"") | I73: =IF($H73="","",MAX(0,$H73-N($E73))) | J73: =IF($H73="","",MAX(0,$H73-N($G73)))
A74: AM-OCT-P08-BEN | B74: Octavas | C74: Benguela | D74: =IFERROR(CLASIF_A_M!$F$12,"") | F74: =IFERROR(CLASIF_A_M!$F$13,"") | I74: =IF($H74="","",MAX(0,$H74-N($E74))) | J74: =IF($H74="","",MAX(0,$H74-N($G74)))
A75: AM-OCT-P08-SBA | B75: Octavas | C75: São Bento da Abadá | D75: =IFERROR(CLASIF_A_M!$F$12,"") | F75: =IFERROR(CLASIF_A_M!$F$13,"") | I75: =IF($H75="","",MAX(0,$H75-N($E75))) | J75: =IF($H75="","",MAX(0,$H75-N($G75)))
A76: AM-OCT-P08-SIR | B76: Octavas | C76: Siriuna | D76: =IFERROR(CLASIF_A_M!$F$12,"") | F76: =IFERROR(CLASIF_A_M!$F$13,"") | I76: =IF($H76="","",MAX(0,$H76-N($E76))) | J76: =IF($H76="","",MAX(0,$H76-N($G76)))
A77: AM-SEM-P01-BEN | B77: Semifinal | C77: Benguela | D77: =IFERROR(CLASIF_A_M!$O$5,"") | F77: =IFERROR(CLASIF_A_M!$O$12,"") | I77: =IF($H77="","",MAX(0,$H77-N($E77))) | J77: =IF($H77="","",MAX(0,$H77-N($G77)))
A78: AM-SEM-P01-SBA | B78: Semifinal | C78: São Bento da Abadá | D78: =IFERROR(CLASIF_A_M!$O$5,"") | F78: =IFERROR(CLASIF_A_M!$O$12,"") | I78: =IF($H78="","",MAX(0,$H78-N($E78))) | J78: =IF($H78="","",MAX(0,$H78-N($G78)))
A79: AM-SEM-P01-SIR | B79: Semifinal | C79: Siriuna | D79: =IFERROR(CLASIF_A_M!$O$5,"") | F79: =IFERROR(CLASIF_A_M!$O$12,"") | I79: =IF($H79="","",MAX(0,$H79-N($E79))) | J79: =IF($H79="","",MAX(0,$H79-N($G79)))
A80: AM-SEM-P02-BEN | B80: Semifinal | C80: Benguela | D80: =IFERROR(CLASIF_A_M!$O$6,"") | F80: =IFERROR(CLASIF_A_M!$O$11,"") | I80: =IF($H80="","",MAX(0,$H80-N($E80))) | J80: =IF($H80="","",MAX(0,$H80-N($G80)))
A81: AM-SEM-P02-SBA | B81: Semifinal | C81: São Bento da Abadá | D81: =IFERROR(CLASIF_A_M!$O$6,"") | F81: =IFERROR(CLASIF_A_M!$O$11,"") | I81: =IF($H81="","",MAX(0,$H81-N($E81))) | J81: =IF($H81="","",MAX(0,$H81-N($G81)))
A82: AM-SEM-P02-SIR | B82: Semifinal | C82: Siriuna | D82: =IFERROR(CLASIF_A_M!$O$6,"") | F82: =IFERROR(CLASIF_A_M!$O$11,"") | I82: =IF($H82="","",MAX(0,$H82-N($E82))) | J82: =IF($H82="","",MAX(0,$H82-N($G82)))
A83: AM-SEM-P03-BEN | B83: Semifinal | C83: Benguela | D83: =IFERROR(CLASIF_A_M!$O$7,"") | F83: =IFERROR(CLASIF_A_M!$O$10,"") | I83: =IF($H83="","",MAX(0,$H83-N($E83))) | J83: =IF($H83="","",MAX(0,$H83-N($G83)))
A84: AM-SEM-P03-SBA | B84: Semifinal | C84: São Bento da Abadá | D84: =IFERROR(CLASIF_A_M!$O$7,"") | F84: =IFERROR(CLASIF_A_M!$O$10,"") | I84: =IF($H84="","",MAX(0,$H84-N($E84))) | J84: =IF($H84="","",MAX(0,$H84-N($G84)))
A85: AM-SEM-P03-SIR | B85: Semifinal | C85: Siriuna | D85: =IFERROR(CLASIF_A_M!$O$7,"") | F85: =IFERROR(CLASIF_A_M!$O$10,"") | I85: =IF($H85="","",MAX(0,$H85-N($E85))) | J85: =IF($H85="","",MAX(0,$H85-N($G85)))
A86: AM-SEM-P04-BEN | B86: Semifinal | C86: Benguela | D86: =IFERROR(CLASIF_A_M!$O$8,"") | F86: =IFERROR(CLASIF_A_M!$O$9,"") | I86: =IF($H86="","",MAX(0,$H86-N($E86))) | J86: =IF($H86="","",MAX(0,$H86-N($G86)))
A87: AM-SEM-P04-SBA | B87: Semifinal | C87: São Bento da Abadá | D87: =IFERROR(CLASIF_A_M!$O$8,"") | F87: =IFERROR(CLASIF_A_M!$O$9,"") | I87: =IF($H87="","",MAX(0,$H87-N($E87))) | J87: =IF($H87="","",MAX(0,$H87-N($G87)))
A88: AM-SEM-P04-SIR | B88: Semifinal | C88: Siriuna | D88: =IFERROR(CLASIF_A_M!$O$8,"") | F88: =IFERROR(CLASIF_A_M!$O$9,"") | I88: =IF($H88="","",MAX(0,$H88-N($E88))) | J88: =IF($H88="","",MAX(0,$H88-N($G88)))
A89: AM-FIN-P01-BEN | B89: Final | C89: Benguela | D89: =IFERROR(CLASIF_A_M!$X$5,"") | F89: =IFERROR(CLASIF_A_M!$X$8,"") | I89: =IF($H89="","",MAX(0,$H89-N($E89))) | J89: =IF($H89="","",MAX(0,$H89-N($G89)))
A90: AM-FIN-P01-SBA | B90: Final | C90: São Bento da Abadá | D90: =IFERROR(CLASIF_A_M!$X$5,"") | F90: =IFERROR(CLASIF_A_M!$X$8,"") | I90: =IF($H90="","",MAX(0,$H90-N($E90))) | J90: =IF($H90="","",MAX(0,$H90-N($G90)))
A91: AM-FIN-P01-SIR | B91: Final | C91: Siriuna | D91: =IFERROR(CLASIF_A_M!$X$5,"") | F91: =IFERROR(CLASIF_A_M!$X$8,"") | I91: =IF($H91="","",MAX(0,$H91-N($E91))) | J91: =IF($H91="","",MAX(0,$H91-N($G91)))
A92: AM-FIN-P02-BEN | B92: Final | C92: Benguela | D92: =IFERROR(CLASIF_A_M!$X$6,"") | F92: =IFERROR(CLASIF_A_M!$X$7,"") | I92: =IF($H92="","",MAX(0,$H92-N($E92))) | J92: =IF($H92="","",MAX(0,$H92-N($G92)))
A93: AM-FIN-P02-SBA | B93: Final | C93: São Bento da Abadá | D93: =IFERROR(CLASIF_A_M!$X$6,"") | F93: =IFERROR(CLASIF_A_M!$X$7,"") | I93: =IF($H93="","",MAX(0,$H93-N($E93))) | J93: =IF($H93="","",MAX(0,$H93-N($G93)))
A94: AM-FIN-P02-SIR | B94: Final | C94: Siriuna | D94: =IFERROR(CLASIF_A_M!$X$6,"") | F94: =IFERROR(CLASIF_A_M!$X$7,"") | I94: =IF($H94="","",MAX(0,$H94-N($E94))) | J94: =IF($H94="","",MAX(0,$H94-N($G94)))
I95: =IF($H95="","",MAX(0,$H95-N($E95))) | J95: =IF($H95="","",MAX(0,$H95-N($G95)))
A96: ═══ CATEGORÍA A · Femenino · Marrón (Profesores) · Toques: Benguela, São Bento da Abadá, Siriuna ═══
A97: Jogo | B97: Fase | C97: Toque | D97: Jugador A | E97: Quita A | F97: Jugador B | G97: Quita B | H97: NOTA (0-5) | I97: =IF($H97="","",MAX(0,$H97-N($E97))) | J97: =IF($H97="","",MAX(0,$H97-N($G97)))
A98: AF-32-P01-BEN | B98: Fase 32 | C98: Benguela | D98: A_A_F_32_P1 | F98: B_A_F_32_P1 | I98: =IF($H98="","",MAX(0,$H98-N($E98))) | J98: =IF($H98="","",MAX(0,$H98-N($G98)))
A99: AF-32-P01-SBA | B99: Fase 32 | C99: São Bento da Abadá | D99: A_A_F_32_P1 | F99: B_A_F_32_P1 | I99: =IF($H99="","",MAX(0,$H99-N($E99))) | J99: =IF($H99="","",MAX(0,$H99-N($G99)))
A100: AF-32-P01-SIR | B100: Fase 32 | C100: Siriuna | D100: A_A_F_32_P1 | F100: B_A_F_32_P1 | I100: =IF($H100="","",MAX(0,$H100-N($E100))) | J100: =IF($H100="","",MAX(0,$H100-N($G100)))
A101: AF-32-P02-BEN | B101: Fase 32 | C101: Benguela | D101: A_A_F_32_P2 | F101: B_A_F_32_P2 | I101: =IF($H101="","",MAX(0,$H101-N($E101))) | J101: =IF($H101="","",MAX(0,$H101-N($G101)))
A102: AF-32-P02-SBA | B102: Fase 32 | C102: São Bento da Abadá | D102: A_A_F_32_P2 | F102: B_A_F_32_P2 | I102: =IF($H102="","",MAX(0,$H102-N($E102))) | J102: =IF($H102="","",MAX(0,$H102-N($G102)))
A103: AF-32-P02-SIR | B103: Fase 32 | C103: Siriuna | D103: A_A_F_32_P2 | F103: B_A_F_32_P2 | I103: =IF($H103="","",MAX(0,$H103-N($E103))) | J103: =IF($H103="","",MAX(0,$H103-N($G103)))
A104: AF-32-P03-BEN | B104: Fase 32 | C104: Benguela | D104: A_A_F_32_P3 | F104: B_A_F_32_P3 | I104: =IF($H104="","",MAX(0,$H104-N($E104))) | J104: =IF($H104="","",MAX(0,$H104-N($G104)))
A105: AF-32-P03-SBA | B105: Fase 32 | C105: São Bento da Abadá | D105: A_A_F_32_P3 | F105: B_A_F_32_P3 | I105: =IF($H105="","",MAX(0,$H105-N($E105))) | J105: =IF($H105="","",MAX(0,$H105-N($G105)))
A106: AF-32-P03-SIR | B106: Fase 32 | C106: Siriuna | D106: A_A_F_32_P3 | F106: B_A_F_32_P3 | I106: =IF($H106="","",MAX(0,$H106-N($E106))) | J106: =IF($H106="","",MAX(0,$H106-N($G106)))
A107: AF-32-P04-BEN | B107: Fase 32 | C107: Benguela | D107: A_A_F_32_P4 | F107: B_A_F_32_P4 | I107: =IF($H107="","",MAX(0,$H107-N($E107))) | J107: =IF($H107="","",MAX(0,$H107-N($G107)))
A108: AF-32-P04-SBA | B108: Fase 32 | C108: São Bento da Abadá | D108: A_A_F_32_P4 | F108: B_A_F_32_P4 | I108: =IF($H108="","",MAX(0,$H108-N($E108))) | J108: =IF($H108="","",MAX(0,$H108-N($G108)))
A109: AF-32-P04-SIR | B109: Fase 32 | C109: Siriuna | D109: A_A_F_32_P4 | F109: B_A_F_32_P4 | I109: =IF($H109="","",MAX(0,$H109-N($E109))) | J109: =IF($H109="","",MAX(0,$H109-N($G109)))
... A145: AF-32-P16-SIR | B145: Fase 32 | C145: Siriuna | D145: A_A_F_32_P16 | F145: B_A_F_32_P16 | I145: =IF($H145="","",MAX(0,$H145-N($E145))) | J145: =IF($H145="","",MAX(0,$H145-N($G145)))
A146: AF-OCT-P01-BEN | B146: Octavas | C146: Benguela | D146: =IFERROR(CLASIF_A_F!$F$5,"") | F146: =IFERROR(CLASIF_A_F!$F$20,"") | I146: =IF($H146="","",MAX(0,$H146-N($E146))) | J146: =IF($H146="","",MAX(0,$H146-N($G146)))
A147: AF-OCT-P01-SBA | B147: Octavas | C147: São Bento da Abadá | D147: =IFERROR(CLASIF_A_F!$F$5,"") | F147: =IFERROR(CLASIF_A_F!$F$20,"") | I147: =IF($H147="","",MAX(0,$H147-N($E147))) | J147: =IF($H147="","",MAX(0,$H147-N($G147)))
A148: AF-OCT-P01-SIR | B148: Octavas | C148: Siriuna | D148: =IFERROR(CLASIF_A_F!$F$5,"") | F148: =IFERROR(CLASIF_A_F!$F$20,"") | I148: =IF($H148="","",MAX(0,$H148-N($E148))) | J148: =IF($H148="","",MAX(0,$H148-N($G148)))
A149: AF-OCT-P02-BEN | B149: Octavas | C149: Benguela | D149: =IFERROR(CLASIF_A_F!$F$6,"") | F149: =IFERROR(CLASIF_A_F!$F$19,"") | I149: =IF($H149="","",MAX(0,$H149-N($E149))) | J149: =IF($H149="","",MAX(0,$H149-N($G149)))
A150: AF-OCT-P02-SBA | B150: Octavas | C150: São Bento da Abadá | D150: =IFERROR(CLASIF_A_F!$F$6,"") | F150: =IFERROR(CLASIF_A_F!$F$19,"") | I150: =IF($H150="","",MAX(0,$H150-N($E150))) | J150: =IF($H150="","",MAX(0,$H150-N($G150)))
A151: AF-OCT-P02-SIR | B151: Octavas | C151: Siriuna | D151: =IFERROR(CLASIF_A_F!$F$6,"") | F151: =IFERROR(CLASIF_A_F!$F$19,"") | I151: =IF($H151="","",MAX(0,$H151-N($E151))) | J151: =IF($H151="","",MAX(0,$H151-N($G151)))
A152: AF-OCT-P03-BEN | B152: Octavas | C152: Benguela | D152: =IFERROR(CLASIF_A_F!$F$7,"") | F152: =IFERROR(CLASIF_A_F!$F$18,"") | I152: =IF($H152="","",MAX(0,$H152-N($E152))) | J152: =IF($H152="","",MAX(0,$H152-N($G152)))
A153: AF-OCT-P03-SBA | B153: Octavas | C153: São Bento da Abadá | D153: =IFERROR(CLASIF_A_F!$F$7,"") | F153: =IFERROR(CLASIF_A_F!$F$18,"") | I153: =IF($H153="","",MAX(0,$H153-N($E153))) | J153: =IF($H153="","",MAX(0,$H153-N($G153)))
A154: AF-OCT-P03-SIR | B154: Octavas | C154: Siriuna | D154: =IFERROR(CLASIF_A_F!$F$7,"") | F154: =IFERROR(CLASIF_A_F!$F$18,"") | I154: =IF($H154="","",MAX(0,$H154-N($E154))) | J154: =IF($H154="","",MAX(0,$H154-N($G154)))
A155: AF-OCT-P04-BEN | B155: Octavas | C155: Benguela | D155: =IFERROR(CLASIF_A_F!$F$8,"") | F155: =IFERROR(CLASIF_A_F!$F$17,"") | I155: =IF($H155="","",MAX(0,$H155-N($E155))) | J155: =IF($H155="","",MAX(0,$H155-N($G155)))
A156: AF-OCT-P04-SBA | B156: Octavas | C156: São Bento da Abadá | D156: =IFERROR(CLASIF_A_F!$F$8,"") | F156: =IFERROR(CLASIF_A_F!$F$17,"") | I156: =IF($H156="","",MAX(0,$H156-N($E156))) | J156: =IF($H156="","",MAX(0,$H156-N($G156)))
A157: AF-OCT-P04-SIR | B157: Octavas | C157: Siriuna | D157: =IFERROR(CLASIF_A_F!$F$8,"") | F157: =IFERROR(CLASIF_A_F!$F$17,"") | I157: =IF($H157="","",MAX(0,$H157-N($E157))) | J157: =IF($H157="","",MAX(0,$H157-N($G157)))
A158: AF-OCT-P05-BEN | B158: Octavas | C158: Benguela | D158: =IFERROR(CLASIF_A_F!$F$9,"") | F158: =IFERROR(CLASIF_A_F!$F$16,"") | I158: =IF($H158="","",MAX(0,$H158-N($E158))) | J158: =IF($H158="","",MAX(0,$H158-N($G158)))
A159: AF-OCT-P05-SBA | B159: Octavas | C159: São Bento da Abadá | D159: =IFERROR(CLASIF_A_F!$F$9,"") | F159: =IFERROR(CLASIF_A_F!$F$16,"") | I159: =IF($H159="","",MAX(0,$H159-N($E159))) | J159: =IF($H159="","",MAX(0,$H159-N($G159)))
A160: AF-OCT-P05-SIR | B160: Octavas | C160: Siriuna | D160: =IFERROR(CLASIF_A_F!$F$9,"") | F160: =IFERROR(CLASIF_A_F!$F$16,"") | I160: =IF($H160="","",MAX(0,$H160-N($E160))) | J160: =IF($H160="","",MAX(0,$H160-N($G160)))
A161: AF-OCT-P06-BEN | B161: Octavas | C161: Benguela | D161: =IFERROR(CLASIF_A_F!$F$10,"") | F161: =IFERROR(CLASIF_A_F!$F$15,"") | I161: =IF($H161="","",MAX(0,$H161-N($E161))) | J161: =IF($H161="","",MAX(0,$H161-N($G161)))
A162: AF-OCT-P06-SBA | B162: Octavas | C162: São Bento da Abadá | D162: =IFERROR(CLASIF_A_F!$F$10,"") | F162: =IFERROR(CLASIF_A_F!$F$15,"") | I162: =IF($H162="","",MAX(0,$H162-N($E162))) | J162: =IF($H162="","",MAX(0,$H162-N($G162)))
A163: AF-OCT-P06-SIR | B163: Octavas | C163: Siriuna | D163: =IFERROR(CLASIF_A_F!$F$10,"") | F163: =IFERROR(CLASIF_A_F!$F$15,"") | I163: =IF($H163="","",MAX(0,$H163-N($E163))) | J163: =IF($H163="","",MAX(0,$H163-N($G163)))
A164: AF-OCT-P07-BEN | B164: Octavas | C164: Benguela | D164: =IFERROR(CLASIF_A_F!$F$11,"") | F164: =IFERROR(CLASIF_A_F!$F$14,"") | I164: =IF($H164="","",MAX(0,$H164-N($E164))) | J164: =IF($H164="","",MAX(0,$H164-N($G164)))
A165: AF-OCT-P07-SBA | B165: Octavas | C165: São Bento da Abadá | D165: =IFERROR(CLASIF_A_F!$F$11,"") | F165: =IFERROR(CLASIF_A_F!$F$14,"") | I165: =IF($H165="","",MAX(0,$H165-N($E165))) | J165: =IF($H165="","",MAX(0,$H165-N($G165)))
A166: AF-OCT-P07-SIR | B166: Octavas | C166: Siriuna | D166: =IFERROR(CLASIF_A_F!$F$11,"") | F166: =IFERROR(CLASIF_A_F!$F$14,"") | I166: =IF($H166="","",MAX(0,$H166-N($E166))) | J166: =IF($H166="","",MAX(0,$H166-N($G166)))
A167: AF-OCT-P08-BEN | B167: Octavas | C167: Benguela | D167: =IFERROR(CLASIF_A_F!$F$12,"") | F167: =IFERROR(CLASIF_A_F!$F$13,"") | I167: =IF($H167="","",MAX(0,$H167-N($E167))) | J167: =IF($H167="","",MAX(0,$H167-N($G167)))
A168: AF-OCT-P08-SBA | B168: Octavas | C168: São Bento da Abadá | D168: =IFERROR(CLASIF_A_F!$F$12,"") | F168: =IFERROR(CLASIF_A_F!$F$13,"") | I168: =IF($H168="","",MAX(0,$H168-N($E168))) | J168: =IF($H168="","",MAX(0,$H168-N($G168)))
A169: AF-OCT-P08-SIR | B169: Octavas | C169: Siriuna | D169: =IFERROR(CLASIF_A_F!$F$12,"") | F169: =IFERROR(CLASIF_A_F!$F$13,"") | I169: =IF($H169="","",MAX(0,$H169-N($E169))) | J169: =IF($H169="","",MAX(0,$H169-N($G169)))
A170: AF-SEM-P01-BEN | B170: Semifinal | C170: Benguela | D170: =IFERROR(CLASIF_A_F!$O$5,"") | F170: =IFERROR(CLASIF_A_F!$O$12,"") | I170: =IF($H170="","",MAX(0,$H170-N($E170))) | J170: =IF($H170="","",MAX(0,$H170-N($G170)))
A171: AF-SEM-P01-SBA | B171: Semifinal | C171: São Bento da Abadá | D171: =IFERROR(CLASIF_A_F!$O$5,"") | F171: =IFERROR(CLASIF_A_F!$O$12,"") | I171: =IF($H171="","",MAX(0,$H171-N($E171))) | J171: =IF($H171="","",MAX(0,$H171-N($G171)))
...

Sheet JUEZ_3
A1: JUEZ 3 · EVENTO COMPLETO · Rellena NOTA y puntos a quitar por jugador en cada jogo
A3: ═══ CATEGORÍA A · Masculino · Marrón (Profesores) · Toques: Benguela, São Bento da Abadá, Siriuna ═══
A4: Jogo | B4: Fase | C4: Toque | D4: Jugador A | E4: Quita A | F4: Jugador B | G4: Quita B | H4: NOTA (0-5) | I4: Final A | J4: Final B
A5: AM-32-P01-BEN | B5: Fase 32 | C5: Benguela | D5: A_A_M_32_P1 | F5: B_A_M_32_P1 | I5: =IF($H5="","",MAX(0,$H5-N($E5))) | J5: =IF($H5="","",MAX(0,$H5-N($G5)))
A6: AM-32-P01-SBA | B6: Fase 32 | C6: São Bento da Abadá | D6: A_A_M_32_P1 | F6: B_A_M_32_P1 | I6: =IF($H6="","",MAX(0,$H6-N($E6))) | J6: =IF($H6="","",MAX(0,$H6-N($G6)))
A7: AM-32-P01-SIR | B7: Fase 32 | C7: Siriuna | D7: A_A_M_32_P1 | F7: B_A_M_32_P1 | I7: =IF($H7="","",MAX(0,$H7-N($E7))) | J7: =IF($H7="","",MAX(0,$H7-N($G7)))
A8: AM-32-P02-BEN | B8: Fase 32 | C8: Benguela | D8: A_A_M_32_P2 | F8: B_A_M_32_P2 | I8: =IF($H8="","",MAX(0,$H8-N($E8))) | J8: =IF($H8="","",MAX(0,$H8-N($G8)))
A9: AM-32-P02-SBA | B9: Fase 32 | C9: São Bento da Abadá | D9: A_A_M_32_P2 | F9: B_A_M_32_P2 | I9: =IF($H9="","",MAX(0,$H9-N($E9))) | J9: =IF($H9="","",MAX(0,$H9-N($G9)))
A10: AM-32-P02-SIR | B10: Fase 32 | C10: Siriuna | D10: A_A_M_32_P2 | F10: B_A_M_32_P2 | I10: =IF($H10="","",MAX(0,$H10-N($E10))) | J10: =IF($H10="","",MAX(0,$H10-N($G10)))
A11: AM-32-P03-BEN | B11: Fase 32 | C11: Benguela | D11: A_A_M_32_P3 | F11: B_A_M_32_P3 | I11: =IF($H11="","",MAX(0,$H11-N($E11))) | J11: =IF($H11="","",MAX(0,$H11-N($G11)))
A12: AM-32-P03-SBA | B12: Fase 32 | C12: São Bento da Abadá | D12: A_A_M_32_P3 | F12: B_A_M_32_P3 | I12: =IF($H12="","",MAX(0,$H12-N($E12))) | J12: =IF($H12="","",MAX(0,$H12-N($G12)))
A13: AM-32-P03-SIR | B13: Fase 32 | C13: Siriuna | D13: A_A_M_32_P3 | F13: B_A_M_32_P3 | I13: =IF($H13="","",MAX(0,$H13-N($E13))) | J13: =IF($H13="","",MAX(0,$H13-N($G13)))
A14: AM-32-P04-BEN | B14: Fase 32 | C14: Benguela | D14: A_A_M_32_P4 | F14: B_A_M_32_P4 | I14: =IF($H14="","",MAX(0,$H14-N($E14))) | J14: =IF($H14="","",MAX(0,$H14-N($G14)))
A15: AM-32-P04-SBA | B15: Fase 32 | C15: São Bento da Abadá | D15: A_A_M_32_P4 | F15: B_A_M_32_P4 | I15: =IF($H15="","",MAX(0,$H15-N($E15))) | J15: =IF($H15="","",MAX(0,$H15-N($G15)))
A16: AM-32-P04-SIR | B16: Fase 32 | C16: Siriuna | D16: A_A_M_32_P4 | F16: B_A_M_32_P4 | I16: =IF($H16="","",MAX(0,$H16-N($E16))) | J16: =IF($H16="","",MAX(0,$H16-N($G16)))
... A52: AM-32-P16-SIR | B52: Fase 32 | C52: Siriuna | D52: A_A_M_32_P16 | F52: B_A_M_32_P16 | I52: =IF($H52="","",MAX(0,$H52-N($E52))) | J52: =IF($H52="","",MAX(0,$H52-N($G52)))
A53: AM-OCT-P01-BEN | B53: Octavas | C53: Benguela | D53: =IFERROR(CLASIF_A_M!$F$5,"") | F53: =IFERROR(CLASIF_A_M!$F$20,"") | I53: =IF($H53="","",MAX(0,$H53-N($E53))) | J53: =IF($H53="","",MAX(0,$H53-N($G53)))
A54: AM-OCT-P01-SBA | B54: Octavas | C54: São Bento da Abadá | D54: =IFERROR(CLASIF_A_M!$F$5,"") | F54: =IFERROR(CLASIF_A_M!$F$20,"") | I54: =IF($H54="","",MAX(0,$H54-N($E54))) | J54: =IF($H54="","",MAX(0,$H54-N($G54)))
A55: AM-OCT-P01-SIR | B55: Octavas | C55: Siriuna | D55: =IFERROR(CLASIF_A_M!$F$5,"") | F55: =IFERROR(CLASIF_A_M!$F$20,"") | I55: =IF($H55="","",MAX(0,$H55-N($E55))) | J55: =IF($H55="","",MAX(0,$H55-N($G55)))
A56: AM-OCT-P02-BEN | B56: Octavas | C56: Benguela | D56: =IFERROR(CLASIF_A_M!$F$6,"") | F56: =IFERROR(CLASIF_A_M!$F$19,"") | I56: =IF($H56="","",MAX(0,$H56-N($E56))) | J56: =IF($H56="","",MAX(0,$H56-N($G56)))
A57: AM-OCT-P02-SBA | B57: Octavas | C57: São Bento da Abadá | D57: =IFERROR(CLASIF_A_M!$F$6,"") | F57: =IFERROR(CLASIF_A_M!$F$19,"") | I57: =IF($H57="","",MAX(0,$H57-N($E57))) | J57: =IF($H57="","",MAX(0,$H57-N($G57)))
A58: AM-OCT-P02-SIR | B58: Octavas | C58: Siriuna | D58: =IFERROR(CLASIF_A_M!$F$6,"") | F58: =IFERROR(CLASIF_A_M!$F$19,"") | I58: =IF($H58="","",MAX(0,$H58-N($E58))) | J58: =IF($H58="","",MAX(0,$H58-N($G58)))
A59: AM-OCT-P03-BEN | B59: Octavas | C59: Benguela | D59: =IFERROR(CLASIF_A_M!$F$7,"") | F59: =IFERROR(CLASIF_A_M!$F$18,"") | I59: =IF($H59="","",MAX(0,$H59-N($E59))) | J59: =IF($H59="","",MAX(0,$H59-N($G59)))
A60: AM-OCT-P03-SBA | B60: Octavas | C60: São Bento da Abadá | D60: =IFERROR(CLASIF_A_M!$F$7,"") | F60: =IFERROR(CLASIF_A_M!$F$18,"") | I60: =IF($H60="","",MAX(0,$H60-N($E60))) | J60: =IF($H60="","",MAX(0,$H60-N($G60)))
A61: AM-OCT-P03-SIR | B61: Octavas | C61: Siriuna | D61: =IFERROR(CLASIF_A_M!$F$7,"") | F61: =IFERROR(CLASIF_A_M!$F$18,"") | I61: =IF($H61="","",MAX(0,$H61-N($E61))) | J61: =IF($H61="","",MAX(0,$H61-N($G61)))
A62: AM-OCT-P04-BEN | B62: Octavas | C62: Benguela | D62: =IFERROR(CLASIF_A_M!$F$8,"") | F62: =IFERROR(CLASIF_A_M!$F$17,"") | I62: =IF($H62="","",MAX(0,$H62-N($E62))) | J62: =IF($H62="","",MAX(0,$H62-N($G62)))
A63: AM-OCT-P04-SBA | B63: Octavas | C63: São Bento da Abadá | D63: =IFERROR(CLASIF_A_M!$F$8,"") | F63: =IFERROR(CLASIF_A_M!$F$17,"") | I63: =IF($H63="","",MAX(0,$H63-N($E63))) | J63: =IF($H63="","",MAX(0,$H63-N($G63)))
A64: AM-OCT-P04-SIR | B64: Octavas | C64: Siriuna | D64: =IFERROR(CLASIF_A_M!$F$8,"") | F64: =IFERROR(CLASIF_A_M!$F$17,"") | I64: =IF($H64="","",MAX(0,$H64-N($E64))) | J64: =IF($H64="","",MAX(0,$H64-N($G64)))
A65: AM-OCT-P05-BEN | B65: Octavas | C65: Benguela | D65: =IFERROR(CLASIF_A_M!$F$9,"") | F65: =IFERROR(CLASIF_A_M!$F$16,"") | I65: =IF($H65="","",MAX(0,$H65-N($E65))) | J65: =IF($H65="","",MAX(0,$H65-N($G65)))
A66: AM-OCT-P05-SBA | B66: Octavas | C66: São Bento da Abadá | D66: =IFERROR(CLASIF_A_M!$F$9,"") | F66: =IFERROR(CLASIF_A_M!$F$16,"") | I66: =IF($H66="","",MAX(0,$H66-N($E66))) | J66: =IF($H66="","",MAX(0,$H66-N($G66)))
A67: AM-OCT-P05-SIR | B67: Octavas | C67: Siriuna | D67: =IFERROR(CLASIF_A_M!$F$9,"") | F67: =IFERROR(CLASIF_A_M!$F$16,"") | I67: =IF($H67="","",MAX(0,$H67-N($E67))) | J67: =IF($H67="","",MAX(0,$H67-N($G67)))
A68: AM-OCT-P06-BEN | B68: Octavas | C68: Benguela | D68: =IFERROR(CLASIF_A_M!$F$10,"") | F68: =IFERROR(CLASIF_A_M!$F$15,"") | I68: =IF($H68="","",MAX(0,$H68-N($E68))) | J68: =IF($H68="","",MAX(0,$H68-N($G68)))
A69: AM-OCT-P06-SBA | B69: Octavas | C69: São Bento da Abadá | D69: =IFERROR(CLASIF_A_M!$F$10,"") | F69: =IFERROR(CLASIF_A_M!$F$15,"") | I69: =IF($H69="","",MAX(0,$H69-N($E69))) | J69: =IF($H69="","",MAX(0,$H69-N($G69)))
A70: AM-OCT-P06-SIR | B70: Octavas | C70: Siriuna | D70: =IFERROR(CLASIF_A_M!$F$10,"") | F70: =IFERROR(CLASIF_A_M!$F$15,"") | I70: =IF($H70="","",MAX(0,$H70-N($E70))) | J70: =IF($H70="","",MAX(0,$H70-N($G70)))
A71: AM-OCT-P07-BEN | B71: Octavas | C71: Benguela | D71: =IFERROR(CLASIF_A_M!$F$11,"") | F71: =IFERROR(CLASIF_A_M!$F$14,"") | I71: =IF($H71="","",MAX(0,$H71-N($E71))) | J71: =IF($H71="","",MAX(0,$H71-N($G71)))
A72: AM-OCT-P07-SBA | B72: Octavas | C72: São Bento da Abadá | D72: =IFERROR(CLASIF_A_M!$F$11,"") | F72: =IFERROR(CLASIF_A_M!$F$14,"") | I72: =IF($H72="","",MAX(0,$H72-N($E72))) | J72: =IF($H72="","",MAX(0,$H72-N($G72)))
A73: AM-OCT-P07-SIR | B73: Octavas | C73: Siriuna | D73: =IFERROR(CLASIF_A_M!$F$11,"") | F73: =IFERROR(CLASIF_A_M!$F$14,"") | I73: =IF($H73="","",MAX(0,$H73-N($E73))) | J73: =IF($H73="","",MAX(0,$H73-N($G73)))
A74: AM-OCT-P08-BEN | B74: Octavas | C74: Benguela | D74: =IFERROR(CLASIF_A_M!$F$12,"") | F74: =IFERROR(CLASIF_A_M!$F$13,"") | I74: =IF($H74="","",MAX(0,$H74-N($E74))) | J74: =IF($H74="","",MAX(0,$H74-N($G74)))
A75: AM-OCT-P08-SBA | B75: Octavas | C75: São Bento da Abadá | D75: =IFERROR(CLASIF_A_M!$F$12,"") | F75: =IFERROR(CLASIF_A_M!$F$13,"") | I75: =IF($H75="","",MAX(0,$H75-N($E75))) | J75: =IF($H75="","",MAX(0,$H75-N($G75)))
A76: AM-OCT-P08-SIR | B76: Octavas | C76: Siriuna | D76: =IFERROR(CLASIF_A_M!$F$12,"") | F76: =IFERROR(CLASIF_A_M!$F$13,"") | I76: =IF($H76="","",MAX(0,$H76-N($E76))) | J76: =IF($H76="","",MAX(0,$H76-N($G76)))
A77: AM-SEM-P01-BEN | B77: Semifinal | C77: Benguela | D77: =IFERROR(CLASIF_A_M!$O$5,"") | F77: =IFERROR(CLASIF_A_M!$O$12,"") | I77: =IF($H77="","",MAX(0,$H77-N($E77))) | J77: =IF($H77="","",MAX(0,$H77-N($G77)))
A78: AM-SEM-P01-SBA | B78: Semifinal | C78: São Bento da Abadá | D78: =IFERROR(CLASIF_A_M!$O$5,"") | F78: =IFERROR(CLASIF_A_M!$O$12,"") | I78: =IF($H78="","",MAX(0,$H78-N($E78))) | J78: =IF($H78="","",MAX(0,$H78-N($G78)))
A79: AM-SEM-P01-SIR | B79: Semifinal | C79: Siriuna | D79: =IFERROR(CLASIF_A_M!$O$5,"") | F79: =IFERROR(CLASIF_A_M!$O$12,"") | I79: =IF($H79="","",MAX(0,$H79-N($E79))) | J79: =IF($H79="","",MAX(0,$H79-N($G79)))
A80: AM-SEM-P02-BEN | B80: Semifinal | C80: Benguela | D80: =IFERROR(CLASIF_A_M!$O$6,"") | F80: =IFERROR(CLASIF_A_M!$O$11,"") | I80: =IF($H80="","",MAX(0,$H80-N($E80))) | J80: =IF($H80="","",MAX(0,$H80-N($G80)))
A81: AM-SEM-P02-SBA | B81: Semifinal | C81: São Bento da Abadá | D81: =IFERROR(CLASIF_A_M!$O$6,"") | F81: =IFERROR(CLASIF_A_M!$O$11,"") | I81: =IF($H81="","",MAX(0,$H81-N($E81))) | J81: =IF($H81="","",MAX(0,$H81-N($G81)))
A82: AM-SEM-P02-SIR | B82: Semifinal | C82: Siriuna | D82: =IFERROR(CLASIF_A_M!$O$6,"") | F82: =IFERROR(CLASIF_A_M!$O$11,"") | I82: =IF($H82="","",MAX(0,$H82-N($E82))) | J82: =IF($H82="","",MAX(0,$H82-N($G82)))
A83: AM-SEM-P03-BEN | B83: Semifinal | C83: Benguela | D83: =IFERROR(CLASIF_A_M!$O$7,"") | F83: =IFERROR(CLASIF_A_M!$O$10,"") | I83: =IF($H83="","",MAX(0,$H83-N($E83))) | J83: =IF($H83="","",MAX(0,$H83-N($G83)))
A84: AM-SEM-P03-SBA | B84: Semifinal | C84: São Bento da Abadá | D84: =IFERROR(CLASIF_A_M!$O$7,"") | F84: =IFERROR(CLASIF_A_M!$O$10,"") | I84: =IF($H84="","",MAX(0,$H84-N($E84))) | J84: =IF($H84="","",MAX(0,$H84-N($G84)))
A85: AM-SEM-P03-SIR | B85: Semifinal | C85: Siriuna | D85: =IFERROR(CLASIF_A_M!$O$7,"") | F85: =IFERROR(CLASIF_A_M!$O$10,"") | I85: =IF($H85="","",MAX(0,$H85-N($E85))) | J85: =IF($H85="","",MAX(0,$H85-N($G85)))
A86: AM-SEM-P04-BEN | B86: Semifinal | C86: Benguela | D86: =IFERROR(CLASIF_A_M!$O$8,"") | F86: =IFERROR(CLASIF_A_M!$O$9,"") | I86: =IF($H86="","",MAX(0,$H86-N($E86))) | J86: =IF($H86="","",MAX(0,$H86-N($G86)))
A87: AM-SEM-P04-SBA | B87: Semifinal | C87: São Bento da Abadá | D87: =IFERROR(CLASIF_A_M!$O$8,"") | F87: =IFERROR(CLASIF_A_M!$O$9,"") | I87: =IF($H87="","",MAX(0,$H87-N($E87))) | J87: =IF($H87="","",MAX(0,$H87-N($G87)))
A88: AM-SEM-P04-SIR | B88: Semifinal | C88: Siriuna | D88: =IFERROR(CLASIF_A_M!$O$8,"") | F88: =IFERROR(CLASIF_A_M!$O$9,"") | I88: =IF($H88="","",MAX(0,$H88-N($E88))) | J88: =IF($H88="","",MAX(0,$H88-N($G88)))
A89: AM-FIN-P01-BEN | B89: Final | C89: Benguela | D89: =IFERROR(CLASIF_A_M!$X$5,"") | F89: =IFERROR(CLASIF_A_M!$X$8,"") | I89: =IF($H89="","",MAX(0,$H89-N($E89))) | J89: =IF($H89="","",MAX(0,$H89-N($G89)))
A90: AM-FIN-P01-SBA | B90: Final | C90: São Bento da Abadá | D90: =IFERROR(CLASIF_A_M!$X$5,"") | F90: =IFERROR(CLASIF_A_M!$X$8,"") | I90: =IF($H90="","",MAX(0,$H90-N($E90))) | J90: =IF($H90="","",MAX(0,$H90-N($G90)))
A91: AM-FIN-P01-SIR | B91: Final | C91: Siriuna | D91: =IFERROR(CLASIF_A_M!$X$5,"") | F91: =IFERROR(CLASIF_A_M!$X$8,"") | I91: =IF($H91="","",MAX(0,$H91-N($E91))) | J91: =IF($H91="","",MAX(0,$H91-N($G91)))
A92: AM-FIN-P02-BEN | B92: Final | C92: Benguela | D92: =IFERROR(CLASIF_A_M!$X$6,"") | F92: =IFERROR(CLASIF_A_M!$X$7,"") | I92: =IF($H92="","",MAX(0,$H92-N($E92))) | J92: =IF($H92="","",MAX(0,$H92-N($G92)))
A93: AM-FIN-P02-SBA | B93: Final | C93: São Bento da Abadá | D93: =IFERROR(CLASIF_A_M!$X$6,"") | F93: =IFERROR(CLASIF_A_M!$X$7,"") | I93: =IF($H93="","",MAX(0,$H93-N($E93))) | J93: =IF($H93="","",MAX(0,$H93-N($G93)))
A94: AM-FIN-P02-SIR | B94: Final | C94: Siriuna | D94: =IFERROR(CLASIF_A_M!$X$6,"") | F94: =IFERROR(CLASIF_A_M!$X$7,"") | I94: =IF($H94="","",MAX(0,$H94-N($E94))) | J94: =IF($H94="","",MAX(0,$H94-N($G94)))
I95: =IF($H95="","",MAX(0,$H95-N($E95))) | J95: =IF($H95="","",MAX(0,$H95-N($G95)))
A96: ═══ CATEGORÍA A · Femenino · Marrón (Profesores) · Toques: Benguela, São Bento da Abadá, Siriuna ═══
A97: Jogo | B97: Fase | C97: Toque | D97: Jugador A | E97: Quita A | F97: Jugador B | G97: Quita B | H97: NOTA (0-5) | I97: =IF($H97="","",MAX(0,$H97-N($E97))) | J97: =IF($H97="","",MAX(0,$H97-N($G97)))
A98: AF-32-P01-BEN | B98: Fase 32 | C98: Benguela | D98: A_A_F_32_P1 | F98: B_A_F_32_P1 | I98: =IF($H98="","",MAX(0,$H98-N($E98))) | J98: =IF($H98="","",MAX(0,$H98-N($G98)))
A99: AF-32-P01-SBA | B99: Fase 32 | C99: São Bento da Abadá | D99: A_A_F_32_P1 | F99: B_A_F_32_P1 | I99: =IF($H99="","",MAX(0,$H99-N($E99))) | J99: =IF($H99="","",MAX(0,$H99-N($G99)))
A100: AF-32-P01-SIR | B100: Fase 32 | C100: Siriuna | D100: A_A_F_32_P1 | F100: B_A_F_32_P1 | I100: =IF($H100="","",MAX(0,$H100-N($E100))) | J100: =IF($H100="","",MAX(0,$H100-N($G100)))
A101: AF-32-P02-BEN | B101: Fase 32 | C101: Benguela | D101: A_A_F_32_P2 | F101: B_A_F_32_P2 | I101: =IF($H101="","",MAX(0,$H101-N($E101))) | J101: =IF($H101="","",MAX(0,$H101-N($G101)))
A102: AF-32-P02-SBA | B102: Fase 32 | C102: São Bento da Abadá | D102: A_A_F_32_P2 | F102: B_A_F_32_P2 | I102: =IF($H102="","",MAX(0,$H102-N($E102))) | J102: =IF($H102="","",MAX(0,$H102-N($G102)))
A103: AF-32-P02-SIR | B103: Fase 32 | C103: Siriuna | D103: A_A_F_32_P2 | F103: B_A_F_32_P2 | I103: =IF($H103="","",MAX(0,$H103-N($E103))) | J103: =IF($H103="","",MAX(0,$H103-N($G103)))
A104: AF-32-P03-BEN | B104: Fase 32 | C104: Benguela | D104: A_A_F_32_P3 | F104: B_A_F_32_P3 | I104: =IF($H104="","",MAX(0,$H104-N($E104))) | J104: =IF($H104="","",MAX(0,$H104-N($G104)))
A105: AF-32-P03-SBA | B105: Fase 32 | C105: São Bento da Abadá | D105: A_A_F_32_P3 | F105: B_A_F_32_P3 | I105: =IF($H105="","",MAX(0,$H105-N($E105))) | J105: =IF($H105="","",MAX(0,$H105-N($G105)))
A106: AF-32-P03-SIR | B106: Fase 32 | C106: Siriuna | D106: A_A_F_32_P3 | F106: B_A_F_32_P3 | I106: =IF($H106="","",MAX(0,$H106-N($E106))) | J106: =IF($H106="","",MAX(0,$H106-N($G106)))
A107: AF-32-P04-BEN | B107: Fase 32 | C107: Benguela | D107: A_A_F_32_P4 | F107: B_A_F_32_P4 | I107: =IF($H107="","",MAX(0,$H107-N($E107))) | J107: =IF($H107="","",MAX(0,$H107-N($G107)))
A108: AF-32-P04-SBA | B108: Fase 32 | C108: São Bento da Abadá | D108: A_A_F_32_P4 | F108: B_A_F_32_P4 | I108: =IF($H108="","",MAX(0,$H108-N($E108))) | J108: =IF($H108="","",MAX(0,$H108-N($G108)))
A109: AF-32-P04-SIR | B109: Fase 32 | C109: Siriuna | D109: A_A_F_32_P4 | F109: B_A_F_32_P4 | I109: =IF($H109="","",MAX(0,$H109-N($E109))) | J109: =IF($H109="","",MAX(0,$H109-N($G109)))
... A145: AF-32-P16-SIR | B145: Fase 32 | C145: Siriuna | D145: A_A_F_32_P16 | F145: B_A_F_32_P16 | I145: =IF($H145="","",MAX(0,$H145-N($E145))) | J145: =IF($H145="","",MAX(0,$H145-N($G145)))
A146: AF-OCT-P01-BEN | B146: Octavas | C146: Benguela | D146: =IFERROR(CLASIF_A_F!$F$5,"") | F146: =IFERROR(CLASIF_A_F!$F$20,"") | I146: =IF($H146="","",MAX(0,$H146-N($E146))) | J146: =IF($H146="","",MAX(0,$H146-N($G146)))
A147: AF-OCT-P01-SBA | B147: Octavas | C147: São Bento da Abadá | D147: =IFERROR(CLASIF_A_F!$F$5,"") | F147: =IFERROR(CLASIF_A_F!$F$20,"") | I147: =IF($H147="","",MAX(0,$H147-N($E147))) | J147: =IF($H147="","",MAX(0,$H147-N($G147)))
A148: AF-OCT-P01-SIR | B148: Octavas | C148: Siriuna | D148: =IFERROR(CLASIF_A_F!$F$5,"") | F148: =IFERROR(CLASIF_A_F!$F$20,"") | I148: =IF($H148="","",MAX(0,$H148-N($E148))) | J148: =IF($H148="","",MAX(0,$H148-N($G148)))
A149: AF-OCT-P02-BEN | B149: Octavas | C149: Benguela | D149: =IFERROR(CLASIF_A_F!$F$6,"") | F149: =IFERROR(CLASIF_A_F!$F$19,"") | I149: =IF($H149="","",MAX(0,$H149-N($E149))) | J149: =IF($H149="","",MAX(0,$H149-N($G149)))
A150: AF-OCT-P02-SBA | B150: Octavas | C150: São Bento da Abadá | D150: =IFERROR(CLASIF_A_F!$F$6,"") | F150: =IFERROR(CLASIF_A_F!$F$19,"") | I150: =IF($H150="","",MAX(0,$H150-N($E150))) | J150: =IF($H150="","",MAX(0,$H150-N($G150)))
A151: AF-OCT-P02-SIR | B151: Octavas | C151: Siriuna | D151: =IFERROR(CLASIF_A_F!$F$6,"") | F151: =IFERROR(CLASIF_A_F!$F$19,"") | I151: =IF($H151="","",MAX(0,$H151-N($E151))) | J151: =IF($H151="","",MAX(0,$H151-N($G151)))
A152: AF-OCT-P03-BEN | B152: Octavas | C152: Benguela | D152: =IFERROR(CLASIF_A_F!$F$7,"") | F152: =IFERROR(CLASIF_A_F!$F$18,"") | I152: =IF($H152="","",MAX(0,$H152-N($E152))) | J152: =IF($H152="","",MAX(0,$H152-N($G152)))
A153: AF-OCT-P03-SBA | B153: Octavas | C153: São Bento da Abadá | D153: =IFERROR(CLASIF_A_F!$F$7,"") | F153: =IFERROR(CLASIF_A_F!$F$18,"") | I153: =IF($H153="","",MAX(0,$H153-N($E153))) | J153: =IF($H153="","",MAX(0,$H153-N($G153)))
A154: AF-OCT-P03-SIR | B154: Octavas | C154: Siriuna | D154: =IFERROR(CLASIF_A_F!$F$7,"") | F154: =IFERROR(CLASIF_A_F!$F$18,"") | I154: =IF($H154="","",MAX(0,$H154-N($E154))) | J154: =IF($H154="","",MAX(0,$H154-N($G154)))
A155: AF-OCT-P04-BEN | B155: Octavas | C155: Benguela | D155: =IFERROR(CLASIF_A_F!$F$8,"") | F155: =IFERROR(CLASIF_A_F!$F$17,"") | I155: =IF($H155="","",MAX(0,$H155-N($E155))) | J155: =IF($H155="","",MAX(0,$H155-N($G155)))
A156: AF-OCT-P04-SBA | B156: Octavas | C156: São Bento da Abadá | D156: =IFERROR(CLASIF_A_F!$F$8,"") | F156: =IFERROR(CLASIF_A_F!$F$17,"") | I156: =IF($H156="","",MAX(0,$H156-N($E156))) | J156: =IF($H156="","",MAX(0,$H156-N($G156)))
A157: AF-OCT-P04-SIR | B157: Octavas | C157: Siriuna | D157: =IFERROR(CLASIF_A_F!$F$8,"") | F157: =IFERROR(CLASIF_A_F!$F$17,"") | I157: =IF($H157="","",MAX(0,$H157-N($E157))) | J157: =IF($H157="","",MAX(0,$H157-N($G157)))
A158: AF-OCT-P05-BEN | B158: Octavas | C158: Benguela | D158: =IFERROR(CLASIF_A_F!$F$9,"") | F158: =IFERROR(CLASIF_A_F!$F$16,"") | I158: =IF($H158="","",MAX(0,$H158-N($E158))) | J158: =IF($H158="","",MAX(0,$H158-N($G158)))
A159: AF-OCT-P05-SBA | B159: Octavas | C159: São Bento da Abadá | D159: =IFERROR(CLASIF_A_F!$F$9,"") | F159: =IFERROR(CLASIF_A_F!$F$16,"") | I159: =IF($H159="","",MAX(0,$H159-N($E159))) | J159: =IF($H159="","",MAX(0,$H159-N($G159)))
A160: AF-OCT-P05-SIR | B160: Octavas | C160: Siriuna | D160: =IFERROR(CLASIF_A_F!$F$9,"") | F160: =IFERROR(CLASIF_A_F!$F$16,"") | I160: =IF($H160="","",MAX(0,$H160-N($E160))) | J160: =IF($H160="","",MAX(0,$H160-N($G160)))
A161: AF-OCT-P06-BEN | B161: Octavas | C161: Benguela | D161: =IFERROR(CLASIF_A_F!$F$10,"") | F161: =IFERROR(CLASIF_A_F!$F$15,"") | I161: =IF($H161="","",MAX(0,$H161-N($E161))) | J161: =IF($H161="","",MAX(0,$H161-N($G161)))
A162: AF-OCT-P06-SBA | B162: Octavas | C162: São Bento da Abadá | D162: =IFERROR(CLASIF_A_F!$F$10,"") | F162: =IFERROR(CLASIF_A_F!$F$15,"") | I162: =IF($H162="","",MAX(0,$H162-N($E162))) | J162: =IF($H162="","",MAX(0,$H162-N($G162)))
A163: AF-OCT-P06-SIR | B163: Octavas | C163: Siriuna | D163: =IFERROR(CLASIF_A_F!$F$10,"") | F163: =IFERROR(CLASIF_A_F!$F$15,"") | I163: =IF($H163="","",MAX(0,$H163-N($E163))) | J163: =IF($H163="","",MAX(0,$H163-N($G163)))
A164: AF-OCT-P07-BEN | B164: Octavas | C164: Benguela | D164: =IFERROR(CLASIF_A_F!$F$11,"") | F164: =IFERROR(CLASIF_A_F!$F$14,"") | I164: =IF($H164="","",MAX(0,$H164-N($E164))) | J164: =IF($H164="","",MAX(0,$H164-N($G164)))
A165: AF-OCT-P07-SBA | B165: Octavas | C165: São Bento da Abadá | D165: =IFERROR(CLASIF_A_F!$F$11,"") | F165: =IFERROR(CLASIF_A_F!$F$14,"") | I165: =IF($H165="","",MAX(0,$H165-N($E165))) | J165: =IF($H165="","",MAX(0,$H165-N($G165)))
A166: AF-OCT-P07-SIR | B166: Octavas | C166: Siriuna | D166: =IFERROR(CLASIF_A_F!$F$11,"") | F166: =IFERROR(CLASIF_A_F!$F$14,"") | I166: =IF($H166="","",MAX(0,$H166-N($E166))) | J166: =IF($H166="","",MAX(0,$H166-N($G166)))
A167: AF-OCT-P08-BEN | B167: Octavas | C167: Benguela | D167: =IFERROR(CLASIF_A_F!$F$12,"") | F167: =IFERROR(CLASIF_A_F!$F$13,"") | I167: =IF($H167="","",MAX(0,$H167-N($E167))) | J167: =IF($H167="","",MAX(0,$H167-N($G167)))
A168: AF-OCT-P08-SBA | B168: Octavas | C168: São Bento da Abadá | D168: =IFERROR(CLASIF_A_F!$F$12,"") | F168: =IFERROR(CLASIF_A_F!$F$13,"") | I168: =IF($H168="","",MAX(0,$H168-N($E168))) | J168: =IF($H168="","",MAX(0,$H168-N($G168)))
A169: AF-OCT-P08-SIR | B169: Octavas | C169: Siriuna | D169: =IFERROR(CLASIF_A_F!$F$12,"") | F169: =IFERROR(CLASIF_A_F!$F$13,"") | I169: =IF($H169="","",MAX(0,$H169-N($E169))) | J169: =IF($H169="","",MAX(0,$H169-N($G169)))
A170: AF-SEM-P01-BEN | B170: Semifinal | C170: Benguela | D170: =IFERROR(CLASIF_A_F!$O$5,"") | F170: =IFERROR(CLASIF_A_F!$O$12,"") | I170: =IF($H170="","",MAX(0,$H170-N($E170))) | J170: =IF($H170="","",MAX(0,$H170-N($G170)))
A171: AF-SEM-P01-SBA | B171: Semifinal | C171: São Bento da Abadá | D171: =IFERROR(CLASIF_A_F!$O$5,"") | F171: =IFERROR(CLASIF_A_F!$O$12,"") | I171: =IF($H171="","",MAX(0,$H171-N($E171))) | J171: =IF($H171="","",MAX(0,$H171-N($G171)))
...

Sheet CLASIF_A_M
A1: CLASIFICACIÓN · Cat A Masculino · suma de toques × 3 jueces
J3: FASE OCTAVAS · pasan 8 a Semifinal | S3: FASE SEMIFINAL · pasan 4 a la Final | AB3: FASE FINAL · sale el CAMPEÓN
A4: Competidor | B4: Puntos | C4: clave | E4: Puesto | F4: Competidor | G4: Puntos | H4: Estado | J4: Competidor | K4: Puntos | L4: clave | N4: Puesto | O4: Competidor | P4: Puntos | Q4: Estado | S4: Competidor | T4: Puntos | U4: clave | W4: Puesto | X4: Competidor | Y4: Puntos | Z4: Estado | AB4: Competidor | AC4: Puntos | AD4: clave | AF4: Puesto | AG4: Competidor | AH4: Puntos | AI4: Resultado
A5: =JUEZ_1!D5 | B5: =(SUM(JUEZ_1!I5:I7)+SUM(JUEZ_2!I5:I7)+SUM(JUEZ_3!I5:I7)) | C5: =IF(OR($A5="",$A5="BYE",LEFT($A5,2)="A_",LEFT($A5,2)="B_"),-1000-ROW()*0.0000001,N(B5)-ROW()*0.0000001) | E5: =ROW()-4 | F5: =IFERROR(INDEX($A$5:$A$36,MATCH(LARGE($C$5:$C$36,$E5),$C$5:$C$36,0)),"") | G5: =IFERROR(INDEX($B$5:$B$36,MATCH(LARGE($C$5:$C$36,$E5),$C$5:$C$36,0)),"") | H5: =IF(OR($F5="",$F5="BYE",LEFT($F5,2)="A_",LEFT($F5,2)="B_"),"",IF($E5<=16,IF(AND($G5=INDEX($G$5:$G$36,17),$G5=INDEX($G$5:$G$36,16)),"Empate (mesa)","CLASIFICA"),IF($G5=INDEX($G$5:$G$36,16),"Empate (mesa)","—"))) | J5: =JUEZ_1!D53 | K5: =(SUM(JUEZ_1!I53:I55)+SUM(JUEZ_2!I53:I55)+SUM(JUEZ_3!I53:I55)) | L5: =IF(OR($J5="",$J5="BYE",LEFT($J5,2)="A_",LEFT($J5,2)="B_"),-1000-ROW()*0.0000001,N(K5)-ROW()*0.0000001) | N5: =ROW()-4 | O5: =IFERROR(INDEX($J$5:$J$20,MATCH(LARGE($L$5:$L$20,$N5),$L$5:$L$20,0)),"") | P5: =IFERROR(INDEX($K$5:$K$20,MATCH(LARGE($L$5:$L$20,$N5),$L$5:$L$20,0)),"") | Q5: =IF(OR($O5="",$O5="BYE",LEFT($O5,2)="A_",LEFT($O5,2)="B_"),"",IF($N5<=8,IF(AND($P5=INDEX($P$5:$P$20,9),$P5=INDEX($P$5:$P$20,8)),"Empate (mesa)","CLASIFICA"),IF($P5=INDEX($P$5:$P$20,8),"Empate (mesa)","—"))) | S5: =JUEZ_1!D77 | T5: =(SUM(JUEZ_1!I77:I79)+SUM(JUEZ_2!I77:I79)+SUM(JUEZ_3!I77:I79)) | U5: =IF(OR($S5="",$S5="BYE",LEFT($S5,2)="A_",LEFT($S5,2)="B_"),-1000-ROW()*0.0000001,N(T5)-ROW()*0.0000001) | W5: =ROW()-4 | X5: =IFERROR(INDEX($S$5:$S$12,MATCH(LARGE($U$5:$U$12,$W5),$U$5:$U$12,0)),"") | Y5: =IFERROR(INDEX($T$5:$T$12,MATCH(LARGE($U$5:$U$12,$W5),$U$5:$U$12,0)),"") | Z5: =IF(OR($X5="",$X5="BYE",LEFT($X5,2)="A_",LEFT($X5,2)="B_"),"",IF($W5<=4,IF(AND($Y5=INDEX($Y$5:$Y$12,5),$Y5=INDEX($Y$5:$Y$12,4)),"Empate (mesa)","CLASIFICA"),IF($Y5=INDEX($Y$5:$Y$12,4),"Empate (mesa)","—"))) | AB5: =JUEZ_1!D89 | AC5: =(SUM(JUEZ_1!I89:I91)+SUM(JUEZ_2!I89:I91)+SUM(JUEZ_3!I89:I91)) | AD5: =IF(OR($AB5="",$AB5="BYE",LEFT($AB5,2)="A_",LEFT($AB5,2)="B_"),-1000-ROW()*0.0000001,N(AC5)-ROW()*0.0000001) | AF5: =ROW()-4 | AG5: =IFERROR(INDEX($AB$5:$AB$8,MATCH(LARGE($AD$5:$AD$8,$AF5),$AD$5:$AD$8,0)),"") | AH5: =IFERROR(INDEX($AC$5:$AC$8,MATCH(LARGE($AD$5:$AD$8,$AF5),$AD$5:$AD$8,0)),"") | AI5: =IF(OR($AG5="",$AG5="BYE",LEFT($AG5,2)="A_",LEFT($AG5,2)="B_"),"",IF($AF5=1,IF($AH5=INDEX($AH$5:$AH$8,2),"Empate 1º (mesa)","🏆 CAMPEÓN"),IF($AF5=2,"2º Subcampeón",IF($AF5=3,"3er puesto","4º puesto"))))
A6: =JUEZ_1!F5 | B6: =(SUM(JUEZ_1!J5:J7)+SUM(JUEZ_2!J5:J7)+SUM(JUEZ_3!J5:J7)) | C6: =IF(OR($A6="",$A6="BYE",LEFT($A6,2)="A_",LEFT($A6,2)="B_"),-1000-ROW()*0.0000001,N(B6)-ROW()*0.0000001) | E6: =ROW()-4 | F6: =IFERROR(INDEX($A$5:$A$36,MATCH(LARGE($C$5:$C$36,$E6),$C$5:$C$36,0)),"") | G6: =IFERROR(INDEX($B$5:$B$36,MATCH(LARGE($C$5:$C$36,$E6),$C$5:$C$36,0)),"") | H6: =IF(OR($F6="",$F6="BYE",LEFT($F6,2)="A_",LEFT($F6,2)="B_"),"",IF($E6<=16,IF(AND($G6=INDEX($G$5:$G$36,17),$G6=INDEX($G$5:$G$36,16)),"Empate (mesa)","CLASIFICA"),IF($G6=INDEX($G$5:$G$36,16),"Empate (mesa)","—"))) | J6: =JUEZ_1!F53 | K6: =(SUM(JUEZ_1!J53:J55)+SUM(JUEZ_2!J53:J55)+SUM(JUEZ_3!J53:J55)) | L6: =IF(OR($J6="",$J6="BYE",LEFT($J6,2)="A_",LEFT($J6,2)="B_"),-1000-ROW()*0.0000001,N(K6)-ROW()*0.0000001) | N6: =ROW()-4 | O6: =IFERROR(INDEX($J$5:$J$20,MATCH(LARGE($L$5:$L$20,$N6),$L$5:$L$20,0)),"") | P6: =IFERROR(INDEX($K$5:$K$20,MATCH(LARGE($L$5:$L$20,$N6),$L$5:$L$20,0)),"") | Q6: =IF(OR($O6="",$O6="BYE",LEFT($O6,2)="A_",LEFT($O6,2)="B_"),"",IF($N6<=8,IF(AND($P6=INDEX($P$5:$P$20,9),$P6=INDEX($P$5:$P$20,8)),"Empate (mesa)","CLASIFICA"),IF($P6=INDEX($P$5:$P$20,8),"Empate (mesa)","—"))) | S6: =JUEZ_1!F77 | T6: =(SUM(JUEZ_1!J77:J79)+SUM(JUEZ_2!J77:J79)+SUM(JUEZ_3!J77:J79)) | U6: =IF(OR($S6="",$S6="BYE",LEFT($S6,2)="A_",LEFT($S6,2)="B_"),-1000-ROW()*0.0000001,N(T6)-ROW()*0.0000001) | W6: =ROW()-4 | X6: =IFERROR(INDEX($S$5:$S$12,MATCH(LARGE($U$5:$U$12,$W6),$U$5:$U$12,0)),"") | Y6: =IFERROR(INDEX($T$5:$T$12,MATCH(LARGE($U$5:$U$12,$W6),$U$5:$U$12,0)),"") | Z6: =IF(OR($X6="",$X6="BYE",LEFT($X6,2)="A_",LEFT($X6,2)="B_"),"",IF($W6<=4,IF(AND($Y6=INDEX($Y$5:$Y$12,5),$Y6=INDEX($Y$5:$Y$12,4)),"Empate (mesa)","CLASIFICA"),IF($Y6=INDEX($Y$5:$Y$12,4),"Empate (mesa)","—"))) | AB6: =JUEZ_1!F89 | AC6: =(SUM(JUEZ_1!J89:J91)+SUM(JUEZ_2!J89:J91)+SUM(JUEZ_3!J89:J91)) | AD6: =IF(OR($AB6="",$AB6="BYE",LEFT($AB6,2)="A_",LEFT($AB6,2)="B_"),-1000-ROW()*0.0000001,N(AC6)-ROW()*0.0000001) | AF6: =ROW()-4 | AG6: =IFERROR(INDEX($AB$5:$AB$8,MATCH(LARGE($AD$5:$AD$8,$AF6),$AD$5:$AD$8,0)),"") | AH6: =IFERROR(INDEX($AC$5:$AC$8,MATCH(LARGE($AD$5:$AD$8,$AF6),$AD$5:$AD$8,0)),"") | AI6: =IF(OR($AG6="",$AG6="BYE",LEFT($AG6,2)="A_",LEFT($AG6,2)="B_"),"",IF($AF6=1,IF($AH6=INDEX($AH$5:$AH$8,2),"Empate 1º (mesa)","🏆 CAMPEÓN"),IF($AF6=2,"2º Subcampeón",IF($AF6=3,"3er puesto","4º puesto"))))
A7: =JUEZ_1!D8 | B7: =(SUM(JUEZ_1!I8:I10)+SUM(JUEZ_2!I8:I10)+SUM(JUEZ_3!I8:I10)) | C7: =IF(OR($A7="",$A7="BYE",LEFT($A7,2)="A_",LEFT($A7,2)="B_"),-1000-ROW()*0.0000001,N(B7)-ROW()*0.0000001) | E7: =ROW()-4 | F7: =IFERROR(INDEX($A$5:$A$36,MATCH(LARGE($C$5:$C$36,$E7),$C$5:$C$36,0)),"") | G7: =IFERROR(INDEX($B$5:$B$36,MATCH(LARGE($C$5:$C$36,$E7),$C$5:$C$36,0)),"") | H7: =IF(OR($F7="",$F7="BYE",LEFT($F7,2)="A_",LEFT($F7,2)="B_"),"",IF($E7<=16,IF(AND($G7=INDEX($G$5:$G$36,17),$G7=INDEX($G$5:$G$36,16)),"Empate (mesa)","CLASIFICA"),IF($G7=INDEX($G$5:$G$36,16),"Empate (mesa)","—"))) | J7: =JUEZ_1!D56 | K7: =(SUM(JUEZ_1!I56:I58)+SUM(JUEZ_2!I56:I58)+SUM(JUEZ_3!I56:I58)) | L7: =IF(OR($J7="",$J7="BYE",LEFT($J7,2)="A_",LEFT($J7,2)="B_"),-1000-ROW()*0.0000001,N(K7)-ROW()*0.0000001) | N7: =ROW()-4 | O7: =IFERROR(INDEX($J$5:$J$20,MATCH(LARGE($L$5:$L$20,$N7),$L$5:$L$20,0)),"") | P7: =IFERROR(INDEX($K$5:$K$20,MATCH(LARGE($L$5:$L$20,$N7),$L$5:$L$20,0)),"") | Q7: =IF(OR($O7="",$O7="BYE",LEFT($O7,2)="A_",LEFT($O7,2)="B_"),"",IF($N7<=8,IF(AND($P7=INDEX($P$5:$P$20,9),$P7=INDEX($P$5:$P$20,8)),"Empate (mesa)","CLASIFICA"),IF($P7=INDEX($P$5:$P$20,8),"Empate (mesa)","—"))) | S7: =JUEZ_1!D80 | T7: =(SUM(JUEZ_1!I80:I82)+SUM(JUEZ_2!I80:I82)+SUM(JUEZ_3!I80:I82)) | U7: =IF(OR($S7="",$S7="BYE",LEFT($S7,2)="A_",LEFT($S7,2)="B_"),-1000-ROW()*0.0000001,N(T7)-ROW()*0.0000001) | W7: =ROW()-4 | X7: =IFERROR(INDEX($S$5:$S$12,MATCH(LARGE($U$5:$U$12,$W7),$U$5:$U$12,0)),"") | Y7: =IFERROR(INDEX($T$5:$T$12,MATCH(LARGE($U$5:$U$12,$W7),$U$5:$U$12,0)),"") | Z7: =IF(OR($X7="",$X7="BYE",LEFT($X7,2)="A_",LEFT($X7,2)="B_"),"",IF($W7<=4,IF(AND($Y7=INDEX($Y$5:$Y$12,5),$Y7=INDEX($Y$5:$Y$12,4)),"Empate (mesa)","CLASIFICA"),IF($Y7=INDEX($Y$5:$Y$12,4),"Empate (mesa)","—"))) | AB7: =JUEZ_1!D92 | AC7: =(SUM(JUEZ_1!I92:I94)+SUM(JUEZ_2!I92:I94)+SUM(JUEZ_3!I92:I94)) | AD7: =IF(OR($AB7="",$AB7="BYE",LEFT($AB7,2)="A_",LEFT($AB7,2)="B_"),-1000-ROW()*0.0000001,N(AC7)-ROW()*0.0000001) | AF7: =ROW()-4 | AG7: =IFERROR(INDEX($AB$5:$AB$8,MATCH(LARGE($AD$5:$AD$8,$AF7),$AD$5:$AD$8,0)),"") | AH7: =IFERROR(INDEX($AC$5:$AC$8,MATCH(LARGE($AD$5:$AD$8,$AF7),$AD$5:$AD$8,0)),"") | AI7: =IF(OR($AG7="",$AG7="BYE",LEFT($AG7,2)="A_",LEFT($AG7,2)="B_"),"",IF($AF7=1,IF($AH7=INDEX($AH$5:$AH$8,2),"Empate 1º (mesa)","🏆 CAMPEÓN"),IF($AF7=2,"2º Subcampeón",IF($AF7=3,"3er puesto","4º puesto"))))
A8: =JUEZ_1!F8 | B8: =(SUM(JUEZ_1!J8:J10)+SUM(JUEZ_2!J8:J10)+SUM(JUEZ_3!J8:J10)) | C8: =IF(OR($A8="",$A8="BYE",LEFT($A8,2)="A_",LEFT($A8,2)="B_"),-1000-ROW()*0.0000001,N(B8)-ROW()*0.0000001) | E8: =ROW()-4 | F8: =IFERROR(INDEX($A$5:$A$36,MATCH(LARGE($C$5:$C$36,$E8),$C$5:$C$36,0)),"") | G8: =IFERROR(INDEX($B$5:$B$36,MATCH(LARGE($C$5:$C$36,$E8),$C$5:$C$36,0)),"") | H8: =IF(OR($F8="",$F8="BYE",LEFT($F8,2)="A_",LEFT($F8,2)="B_"),"",IF($E8<=16,IF(AND($G8=INDEX($G$5:$G$36,17),$G8=INDEX($G$5:$G$36,16)),"Empate (mesa)","CLASIFICA"),IF($G8=INDEX($G$5:$G$36,16),"Empate (mesa)","—"))) | J8: =JUEZ_1!F56 | K8: =(SUM(JUEZ_1!J56:J58)+SUM(JUEZ_2!J56:J58)+SUM(JUEZ_3!J56:J58)) | L8: =IF(OR($J8="",$J8="BYE",LEFT($J8,2)="A_",LEFT($J8,2)="B_"),-1000-ROW()*0.0000001,N(K8)-ROW()*0.0000001) | N8: =ROW()-4 | O8: =IFERROR(INDEX($J$5:$J$20,MATCH(LARGE($L$5:$L$20,$N8),$L$5:$L$20,0)),"") | P8: =IFERROR(INDEX($K$5:$K$20,MATCH(LARGE($L$5:$L$20,$N8),$L$5:$L$20,0)),"") | Q8: =IF(OR($O8="",$O8="BYE",LEFT($O8,2)="A_",LEFT($O8,2)="B_"),"",IF($N8<=8,IF(AND($P8=INDEX($P$5:$P$20,9),$P8=INDEX($P$5:$P$20,8)),"Empate (mesa)","CLASIFICA"),IF($P8=INDEX($P$5:$P$20,8),"Empate (mesa)","—"))) | S8: =JUEZ_1!F80 | T8: =(SUM(JUEZ_1!J80:J82)+SUM(JUEZ_2!J80:J82)+SUM(JUEZ_3!J80:J82)) | U8: =IF(OR($S8="",$S8="BYE",LEFT($S8,2)="A_",LEFT($S8,2)="B_"),-1000-ROW()*0.0000001,N(T8)-ROW()*0.0000001) | W8: =ROW()-4 | X8: =IFERROR(INDEX($S$5:$S$12,MATCH(LARGE($U$5:$U$12,$W8),$U$5:$U$12,0)),"") | Y8: =IFERROR(INDEX($T$5:$T$12,MATCH(LARGE($U$5:$U$12,$W8),$U$5:$U$12,0)),"") | Z8: =IF(OR($X8="",$X8="BYE",LEFT($X8,2)="A_",LEFT($X8,2)="B_"),"",IF($W8<=4,IF(AND($Y8=INDEX($Y$5:$Y$12,5),$Y8=INDEX($Y$5:$Y$12,4)),"Empate (mesa)","CLASIFICA"),IF($Y8=INDEX($Y$5:$Y$12,4),"Empate (mesa)","—"))) | AB8: =JUEZ_1!F92 | AC8: =(SUM(JUEZ_1!J92:J94)+SUM(JUEZ_2!J92:J94)+SUM(JUEZ_3!J92:J94)) | AD8: =IF(OR($AB8="",$AB8="BYE",LEFT($AB8,2)="A_",LEFT($AB8,2)="B_"),-1000-ROW()*0.0000001,N(AC8)-ROW()*0.0000001) | AF8: =ROW()-4 | AG8: =IFERROR(INDEX($AB$5:$AB$8,MATCH(LARGE($AD$5:$AD$8,$AF8),$AD$5:$AD$8,0)),"") | AH8: =IFERROR(INDEX($AC$5:$AC$8,MATCH(LARGE($AD$5:$AD$8,$AF8),$AD$5:$AD$8,0)),"") | AI8: =IF(OR($AG8="",$AG8="BYE",LEFT($AG8,2)="A_",LEFT($AG8,2)="B_"),"",IF($AF8=1,IF($AH8=INDEX($AH$5:$AH$8,2),"Empate 1º (mesa)","🏆 CAMPEÓN"),IF($AF8=2,"2º Subcampeón",IF($AF8=3,"3er puesto","4º puesto"))))
A9: =JUEZ_1!D11 | B9: =(SUM(JUEZ_1!I11:I13)+SUM(JUEZ_2!I11:I13)+SUM(JUEZ_3!I11:I13)) | C9: =IF(OR($A9="",$A9="BYE",LEFT($A9,2)="A_",LEFT($A9,2)="B_"),-1000-ROW()*0.0000001,N(B9)-ROW()*0.0000001) | E9: =ROW()-4 | F9: =IFERROR(INDEX($A$5:$A$36,MATCH(LARGE($C$5:$C$36,$E9),$C$5:$C$36,0)),"") | G9: =IFERROR(INDEX($B$5:$B$36,MATCH(LARGE($C$5:$C$36,$E9),$C$5:$C$36,0)),"") | H9: =IF(OR($F9="",$F9="BYE",LEFT($F9,2)="A_",LEFT($F9,2)="B_"),"",IF($E9<=16,IF(AND($G9=INDEX($G$5:$G$36,17),$G9=INDEX($G$5:$G$36,16)),"Empate (mesa)","CLASIFICA"),IF($G9=INDEX($G$5:$G$36,16),"Empate (mesa)","—"))) | J9: =JUEZ_1!D59 | K9: =(SUM(JUEZ_1!I59:I61)+SUM(JUEZ_2!I59:I61)+SUM(JUEZ_3!I59:I61)) | L9: =IF(OR($J9="",$J9="BYE",LEFT($J9,2)="A_",LEFT($J9,2)="B_"),-1000-ROW()*0.0000001,N(K9)-ROW()*0.0000001) | N9: =ROW()-4 | O9: =IFERROR(INDEX($J$5:$J$20,MATCH(LARGE($L$5:$L$20,$N9),$L$5:$L$20,0)),"") | P9: =IFERROR(INDEX($K$5:$K$20,MATCH(LARGE($L$5:$L$20,$N9),$L$5:$L$20,0)),"") | Q9: =IF(OR($O9="",$O9="BYE",LEFT($O9,2)="A_",LEFT($O9,2)="B_"),"",IF($N9<=8,IF(AND($P9=INDEX($P$5:$P$20,9),$P9=INDEX($P$5:$P$20,8)),"Empate (mesa)","CLASIFICA"),IF($P9=INDEX($P$5:$P$20,8),"Empate (mesa)","—"))) | S9: =JUEZ_1!D83 | T9: =(SUM(JUEZ_1!I83:I85)+SUM(JUEZ_2!I83:I85)+SUM(JUEZ_3!I83:I85)) | U9: =IF(OR($S9="",$S9="BYE",LEFT($S9,2)="A_",LEFT($S9,2)="B_"),-1000-ROW()*0.0000001,N(T9)-ROW()*0.0000001) | W9: =ROW()-4 | X9: =IFERROR(INDEX($S$5:$S$12,MATCH(LARGE($U$5:$U$12,$W9),$U$5:$U$12,0)),"") | Y9: =IFERROR(INDEX($T$5:$T$12,MATCH(LARGE($U$5:$U$12,$W9),$U$5:$U$12,0)),"") | Z9: =IF(OR($X9="",$X9="BYE",LEFT($X9,2)="A_",LEFT($X9,2)="B_"),"",IF($W9<=4,IF(AND($Y9=INDEX($Y$5:$Y$12,5),$Y9=INDEX($Y$5:$Y$12,4)),"Empate (mesa)","CLASIFICA"),IF($Y9=INDEX($Y$5:$Y$12,4),"Empate (mesa)","—")))
A10: =JUEZ_1!F11 | B10: =(SUM(JUEZ_1!J11:J13)+SUM(JUEZ_2!J11:J13)+SUM(JUEZ_3!J11:J13)) | C10: =IF(OR($A10="",$A10="BYE",LEFT($A10,2)="A_",LEFT($A10,2)="B_"),-1000-ROW()*0.0000001,N(B10)-ROW()*0.0000001) | E10: =ROW()-4 | F10: =IFERROR(INDEX($A$5:$A$36,MATCH(LARGE($C$5:$C$36,$E10),$C$5:$C$36,0)),"") | G10: =IFERROR(INDEX($B$5:$B$36,MATCH(LARGE($C$5:$C$36,$E10),$C$5:$C$36,0)),"") | H10: =IF(OR($F10="",$F10="BYE",LEFT($F10,2)="A_",LEFT($F10,2)="B_"),"",IF($E10<=16,IF(AND($G10=INDEX($G$5:$G$36,17),$G10=INDEX($G$5:$G$36,16)),"Empate (mesa)","CLASIFICA"),IF($G10=INDEX($G$5:$G$36,16),"Empate (mesa)","—"))) | J10: =JUEZ_1!F59 | K10: =(SUM(JUEZ_1!J59:J61)+SUM(JUEZ_2!J59:J61)+SUM(JUEZ_3!J59:J61)) | L10: =IF(OR($J10="",$J10="BYE",LEFT($J10,2)="A_",LEFT($J10,2)="B_"),-1000-ROW()*0.0000001,N(K10)-ROW()*0.0000001) | N10: =ROW()-4 | O10: =IFERROR(INDEX($J$5:$J$20,MATCH(LARGE($L$5:$L$20,$N10),$L$5:$L$20,0)),"") | P10: =IFERROR(INDEX($K$5:$K$20,MATCH(LARGE($L$5:$L$20,$N10),$L$5:$L$20,0)),"") | Q10: =IF(OR($O10="",$O10="BYE",LEFT($O10,2)="A_",LEFT($O10,2)="B_"),"",IF($N10<=8,IF(AND($P10=INDEX($P$5:$P$20,9),$P10=INDEX($P$5:$P$20,8)),"Empate (mesa)","CLASIFICA"),IF($P10=INDEX($P$5:$P$20,8),"Empate (mesa)","—"))) | S10: =JUEZ_1!F83 | T10: =(SUM(JUEZ_1!J83:J85)+SUM(JUEZ_2!J83:J85)+SUM(JUEZ_3!J83:J85)) | U10: =IF(OR($S10="",$S10="BYE",LEFT($S10,2)="A_",LEFT($S10,2)="B_"),-1000-ROW()*0.0000001,N(T10)-ROW()*0.0000001) | W10: =ROW()-4 | X10: =IFERROR(INDEX($S$5:$S$12,MATCH(LARGE($U$5:$U$12,$W10),$U$5:$U$12,0)),"") | Y10: =IFERROR(INDEX($T$5:$T$12,MATCH(LARGE($U$5:$U$12,$W10),$U$5:$U$12,0)),"") | Z10: =IF(OR($X10="",$X10="BYE",LEFT($X10,2)="A_",LEFT($X10,2)="B_"),"",IF($W10<=4,IF(AND($Y10=INDEX($Y$5:$Y$12,5),$Y10=INDEX($Y$5:$Y$12,4)),"Empate (mesa)","CLASIFICA"),IF($Y10=INDEX($Y$5:$Y$12,4),"Empate (mesa)","—"))) | AB10: 🥇 PREMIO MEJOR JUEGO POR TOQUE (Final)
A11: =JUEZ_1!D14 | B11: =(SUM(JUEZ_1!I14:I16)+SUM(JUEZ_2!I14:I16)+SUM(JUEZ_3!I14:I16)) | C11: =IF(OR($A11="",$A11="BYE",LEFT($A11,2)="A_",LEFT($A11,2)="B_"),-1000-ROW()*0.0000001,N(B11)-ROW()*0.0000001) | E11: =ROW()-4 | F11: =IFERROR(INDEX($A$5:$A$36,MATCH(LARGE($C$5:$C$36,$E11),$C$5:$C$36,0)),"") | G11: =IFERROR(INDEX($B$5:$B$36,MATCH(LARGE($C$5:$C$36,$E11),$C$5:$C$36,0)),"") | H11: =IF(OR($F11="",$F11="BYE",LEFT($F11,2)="A_",LEFT($F11,2)="B_"),"",IF($E11<=16,IF(AND($G11=INDEX($G$5:$G$36,17),$G11=INDEX($G$5:$G$36,16)),"Empate (mesa)","CLASIFICA"),IF($G11=INDEX($G$5:$G$36,16),"Empate (mesa)","—"))) | J11: =JUEZ_1!D62 | K11: =(SUM(JUEZ_1!I62:I64)+SUM(JUEZ_2!I62:I64)+SUM(JUEZ_3!I62:I64)) | L11: =IF(OR($J11="",$J11="BYE",LEFT($J11,2)="A_",LEFT($J11,2)="B_"),-1000-ROW()*0.0000001,N(K11)-ROW()*0.0000001) | N11: =ROW()-4 | O11: =IFERROR(INDEX($J$5:$J$20,MATCH(LARGE($L$5:$L$20,$N11),$L$5:$L$20,0)),"") | P11: =IFERROR(INDEX($K$5:$K$20,MATCH(LARGE($L$5:$L$20,$N11),$L$5:$L$20,0)),"") | Q11: =IF(OR($O11="",$O11="BYE",LEFT($O11,2)="A_",LEFT($O11,2)="B_"),"",IF($N11<=8,IF(AND($P11=INDEX($P$5:$P$20,9),$P11=INDEX($P$5:$P$20,8)),"Empate (mesa)","CLASIFICA"),IF($P11=INDEX($P$5:$P$20,8),"Empate (mesa)","—"))) | S11: =JUEZ_1!D86 | T11: =(SUM(JUEZ_1!I86:I88)+SUM(JUEZ_2!I86:I88)+SUM(JUEZ_3!I86:I88)) | U11: =IF(OR($S11="",$S11="BYE",LEFT($S11,2)="A_",LEFT($S11,2)="B_"),-1000-ROW()*0.0000001,N(T11)-ROW()*0.0000001) | W11: =ROW()-4 | X11: =IFERROR(INDEX($S$5:$S$12,MATCH(LARGE($U$5:$U$12,$W11),$U$5:$U$12,0)),"") | Y11: =IFERROR(INDEX($T$5:$T$12,MATCH(LARGE($U$5:$U$12,$W11),$U$5:$U$12,0)),"") | Z11: =IF(OR($X11="",$X11="BYE",LEFT($X11,2)="A_",LEFT($X11,2)="B_"),"",IF($W11<=4,IF(AND($Y11=INDEX($Y$5:$Y$12,5),$Y11=INDEX($Y$5:$Y$12,4)),"Empate (mesa)","CLASIFICA"),IF($Y11=INDEX($Y$5:$Y$12,4),"Empate (mesa)","—"))) | AB11: Toque | AC11: Jogo | AD11: Jugador A | AE11: Jugador B | AF11: Nota jogo | AG11: Premio
A12: =JUEZ_1!F14 | B12: =(SUM(JUEZ_1!J14:J16)+SUM(JUEZ_2!J14:J16)+SUM(JUEZ_3!J14:J16)) | C12: =IF(OR($A12="",$A12="BYE",LEFT($A12,2)="A_",LEFT($A12,2)="B_"),-1000-ROW()*0.0000001,N(B12)-ROW()*0.0000001) | E12: =ROW()-4 | F12: =IFERROR(INDEX($A$5:$A$36,MATCH(LARGE($C$5:$C$36,$E12),$C$5:$C$36,0)),"") | G12: =IFERROR(INDEX($B$5:$B$36,MATCH(LARGE($C$5:$C$36,$E12),$C$5:$C$36,0)),"") | H12: =IF(OR($F12="",$F12="BYE",LEFT($F12,2)="A_",LEFT($F12,2)="B_"),"",IF($E12<=16,IF(AND($G12=INDEX($G$5:$G$36,17),$G12=INDEX($G$5:$G$36,16)),"Empate (mesa)","CLASIFICA"),IF($G12=INDEX($G$5:$G$36,16),"Empate (mesa)","—"))) | J12: =JUEZ_1!F62 | K12: =(SUM(JUEZ_1!J62:J64)+SUM(JUEZ_2!J62:J64)+SUM(JUEZ_3!J62:J64)) | L12: =IF(OR($J12="",$J12="BYE",LEFT($J12,2)="A_",LEFT($J12,2)="B_"),-1000-ROW()*0.0000001,N(K12)-ROW()*0.0000001) | N12: =ROW()-4 | O12: =IFERROR(INDEX($J$5:$J$20,MATCH(LARGE($L$5:$L$20,$N12),$L$5:$L$20,0)),"") | P12: =IFERROR(INDEX($K$5:$K$20,MATCH(LARGE($L$5:$L$20,$N12),$L$5:$L$20,0)),"") | Q12: =IF(OR($O12="",$O12="BYE",LEFT($O12,2)="A_",LEFT($O12,2)="B_"),"",IF($N12<=8,IF(AND($P12=INDEX($P$5:$P$20,9),$P12=INDEX($P$5:$P$20,8)),"Empate (mesa)","CLASIFICA"),IF($P12=INDEX($P$5:$P$20,8),"Empate (mesa)","—"))) | S12: =JUEZ_1!F86 | T12: =(SUM(JUEZ_1!J86:J88)+SUM(JUEZ_2!J86:J88)+SUM(JUEZ_3!J86:J88)) | U12: =IF(OR($S12="",$S12="BYE",LEFT($S12,2)="A_",LEFT($S12,2)="B_"),-1000-ROW()*0.0000001,N(T12)-ROW()*0.0000001) | W12: =ROW()-4 | X12: =IFERROR(INDEX($S$5:$S$12,MATCH(LARGE($U$5:$U$12,$W12),$U$5:$U$12,0)),"") | Y12: =IFERROR(INDEX($T$5:$T$12,MATCH(LARGE($U$5:$U$12,$W12),$U$5:$U$12,0)),"") | Z12: =IF(OR($X12="",$X12="BYE",LEFT($X12,2)="A_",LEFT($X12,2)="B_"),"",IF($W12<=4,IF(AND($Y12=INDEX($Y$5:$Y$12,5),$Y12=INDEX($Y$5:$Y$12,4)),"Empate (mesa)","CLASIFICA"),IF($Y12=INDEX($Y$5:$Y$12,4),"Empate (mesa)","—"))) | AB12: Benguela | AC12: =JUEZ_1!A89 | AD12: =JUEZ_1!D89 | AE12: =JUEZ_1!F89 | AF12: =(N(JUEZ_1!I89)+N(JUEZ_1!J89))+(N(JUEZ_2!I89)+N(JUEZ_2!J89))+(N(JUEZ_3!I89)+N(JUEZ_3!J89)) | AG12: =IF(AND($AF12=MAX($AF12,$AF13),$AF12>0),"🥇 MEJOR Benguela","")
A13: =JUEZ_1!D17 | B13: =(SUM(JUEZ_1!I17:I19)+SUM(JUEZ_2!I17:I19)+SUM(JUEZ_3!I17:I19)) | C13: =IF(OR($A13="",$A13="BYE",LEFT($A13,2)="A_",LEFT($A13,2)="B_"),-1000-ROW()*0.0000001,N(B13)-ROW()*0.0000001) | E13: =ROW()-4 | F13: =IFERROR(INDEX($A$5:$A$36,MATCH(LARGE($C$5:$C$36,$E13),$C$5:$C$36,0)),"") | G13: =IFERROR(INDEX($B$5:$B$36,MATCH(LARGE($C$5:$C$36,$E13),$C$5:$C$36,0)),"") | H13: =IF(OR($F13="",$F13="BYE",LEFT($F13,2)="A_",LEFT($F13,2)="B_"),"",IF($E13<=16,IF(AND($G13=INDEX($G$5:$G$36,17),$G13=INDEX($G$5:$G$36,16)),"Empate (mesa)","CLASIFICA"),IF($G13=INDEX($G$5:$G$36,16),"Empate (mesa)","—"))) | J13: =JUEZ_1!D65 | K13: =(SUM(JUEZ_1!I65:I67)+SUM(JUEZ_2!I65:I67)+SUM(JUEZ_3!I65:I67)) | L13: =IF(OR($J13="",$J13="BYE",LEFT($J13,2)="A_",LEFT($J13,2)="B_"),-1000-ROW()*0.0000001,N(K13)-ROW()*0.0000001) | N13: =ROW()-4 | O13: =IFERROR(INDEX($J$5:$J$20,MATCH(LARGE($L$5:$L$20,$N13),$L$5:$L$20,0)),"") | P13: =IFERROR(INDEX($K$5:$K$20,MATCH(LARGE($L$5:$L$20,$N13),$L$5:$L$20,0)),"") | Q13: =IF(OR($O13="",$O13="BYE",LEFT($O13,2)="A_",LEFT($O13,2)="B_"),"",IF($N13<=8,IF(AND($P13=INDEX($P$5:$P$20,9),$P13=INDEX($P$5:$P$20,8)),"Empate (mesa)","CLASIFICA"),IF($P13=INDEX($P$5:$P$20,8),"Empate (mesa)","—"))) | AB13: Benguela | AC13: =JUEZ_1!A92 | AD13: =JUEZ_1!D92 | AE13: =JUEZ_1!F92 | AF13: =(N(JUEZ_1!I92)+N(JUEZ_1!J92))+(N(JUEZ_2!I92)+N(JUEZ_2!J92))+(N(JUEZ_3!I92)+N(JUEZ_3!J92)) | AG13: =IF(AND($AF13=MAX($AF12,$AF13),$AF13>0),"🥇 MEJOR Benguela","")
A14: =JUEZ_1!F17 | B14: =(SUM(JUEZ_1!J17:J19)+SUM(JUEZ_2!J17:J19)+SUM(JUEZ_3!J17:J19)) | C14: =IF(OR($A14="",$A14="BYE",LEFT($A14,2)="A_",LEFT($A14,2)="B_"),-1000-ROW()*0.0000001,N(B14)-ROW()*0.0000001) | E14: =ROW()-4 | F14: =IFERROR(INDEX($A$5:$A$36,MATCH(LARGE($C$5:$C$36,$E14),$C$5:$C$36,0)),"") | G14: =IFERROR(INDEX($B$5:$B$36,MATCH(LARGE($C$5:$C$36,$E14),$C$5:$C$36,0)),"") | H14: =IF(OR($F14="",$F14="BYE",LEFT($F14,2)="A_",LEFT($F14,2)="B_"),"",IF($E14<=16,IF(AND($G14=INDEX($G$5:$G$36,17),$G14=INDEX($G$5:$G$36,16)),"Empate (mesa)","CLASIFICA"),IF($G14=INDEX($G$5:$G$36,16),"Empate (mesa)","—"))) | J14: =JUEZ_1!F65 | K14: =(SUM(JUEZ_1!J65:J67)+SUM(JUEZ_2!J65:J67)+SUM(JUEZ_3!J65:J67)) | L14: =IF(OR($J14="",$J14="BYE",LEFT($J14,2)="A_",LEFT($J14,2)="B_"),-1000-ROW()*0.0000001,N(K14)-ROW()*0.0000001) | N14: =ROW()-4 | O14: =IFERROR(INDEX($J$5:$J$20,MATCH(LARGE($L$5:$L$20,$N14),$L$5:$L$20,0)),"") | P14: =IFERROR(INDEX($K$5:$K$20,MATCH(LARGE($L$5:$L$20,$N14),$L$5:$L$20,0)),"") | Q14: =IF(OR($O14="",$O14="BYE",LEFT($O14,2)="A_",LEFT($O14,2)="B_"),"",IF($N14<=8,IF(AND($P14=INDEX($P$5:$P$20,9),$P14=INDEX($P$5:$P$20,8)),"Empate (mesa)","CLASIFICA"),IF($P14=INDEX($P$5:$P$20,8),"Empate (mesa)","—"))) | AB14: São Bento da Abadá | AC14: =JUEZ_1!A90 | AD14: =JUEZ_1!D90 | AE14: =JUEZ_1!F90 | AF14: =(N(JUEZ_1!I90)+N(JUEZ_1!J90))+(N(JUEZ_2!I90)+N(JUEZ_2!J90))+(N(JUEZ_3!I90)+N(JUEZ_3!J90)) | AG14: =IF(AND($AF14=MAX($AF14,$AF15),$AF14>0),"🥇 MEJOR São Bento da Abadá","")
A15: =JUEZ_1!D20 | B15: =(SUM(JUEZ_1!I20:I22)+SUM(JUEZ_2!I20:I22)+SUM(JUEZ_3!I20:I22)) | C15: =IF(OR($A15="",$A15="BYE",LEFT($A15,2)="A_",LEFT($A15,2)="B_"),-1000-ROW()*0.0000001,N(B15)-ROW()*0.0000001) | E15: =ROW()-4 | F15: =IFERROR(INDEX($A$5:$A$36,MATCH(LARGE($C$5:$C$36,$E15),$C$5:$C$36,0)),"") | G15: =IFERROR(INDEX($B$5:$B$36,MATCH(LARGE($C$5:$C$36,$E15),$C$5:$C$36,0)),"") | H15: =IF(OR($F15="",$F15="BYE",LEFT($F15,2)="A_",LEFT($F15,2)="B_"),"",IF($E15<=16,IF(AND($G15=INDEX($G$5:$G$36,17),$G15=INDEX($G$5:$G$36,16)),"Empate (mesa)","CLASIFICA"),IF($G15=INDEX($G$5:$G$36,16),"Empate (mesa)","—"))) | J15: =JUEZ_1!D68 | K15: =(SUM(JUEZ_1!I68:I70)+SUM(JUEZ_2!I68:I70)+SUM(JUEZ_3!I68:I70)) | L15: =IF(OR($J15="",$J15="BYE",LEFT($J15,2)="A_",LEFT($J15,2)="B_"),-1000-ROW()*0.0000001,N(K15)-ROW()*0.0000001) | N15: =ROW()-4 | O15: =IFERROR(INDEX($J$5:$J$20,MATCH(LARGE($L$5:$L$20,$N15),$L$5:$L$20,0)),"") | P15: =IFERROR(INDEX($K$5:$K$20,MATCH(LARGE($L$5:$L$20,$N15),$L$5:$L$20,0)),"") | Q15: =IF(OR($O15="",$O15="BYE",LEFT($O15,2)="A_",LEFT($O15,2)="B_"),"",IF($N15<=8,IF(AND($P15=INDEX($P$5:$P$20,9),$P15=INDEX($P$5:$P$20,8)),"Empate (mesa)","CLASIFICA"),IF($P15=INDEX($P$5:$P$20,8),"Empate (mesa)","—"))) | AB15: São Bento da Abadá | AC15: =JUEZ_1!A93 | AD15: =JUEZ_1!D93 | AE15: =JUEZ_1!F93 | AF15: =(N(JUEZ_1!I93)+N(JUEZ_1!J93))+(N(JUEZ_2!I93)+N(JUEZ_2!J93))+(N(JUEZ_3!I93)+N(JUEZ_3!J93)) | AG15: =IF(AND($AF15=MAX($AF14,$AF15),$AF15>0),"🥇 MEJOR São Bento da Abadá","")
A16: =JUEZ_1!F20 | B16: =(SUM(JUEZ_1!J20:J22)+SUM(JUEZ_2!J20:J22)+SUM(JUEZ_3!J20:J22)) | C16: =IF(OR($A16="",$A16="BYE",LEFT($A16,2)="A_",LEFT($A16,2)="B_"),-1000-ROW()*0.0000001,N(B16)-ROW()*0.0000001) | E16: =ROW()-4 | F16: =IFERROR(INDEX($A$5:$A$36,MATCH(LARGE($C$5:$C$36,$E16),$C$5:$C$36,0)),"") | G16: =IFERROR(INDEX($B$5:$B$36,MATCH(LARGE($C$5:$C$36,$E16),$C$5:$C$36,0)),"") | H16: =IF(OR($F16="",$F16="BYE",LEFT($F16,2)="A_",LEFT($F16,2)="B_"),"",IF($E16<=16,IF(AND($G16=INDEX($G$5:$G$36,17),$G16=INDEX($G$5:$G$36,16)),"Empate (mesa)","CLASIFICA"),IF($G16=INDEX($G$5:$G$36,16),"Empate (mesa)","—"))) | J16: =JUEZ_1!F68 | K16: =(SUM(JUEZ_1!J68:J70)+SUM(JUEZ_2!J68:J70)+SUM(JUEZ_3!J68:J70)) | L16: =IF(OR($J16="",$J16="BYE",LEFT($J16,2)="A_",LEFT($J16,2)="B_"),-1000-ROW()*0.0000001,N(K16)-ROW()*0.0000001) | N16: =ROW()-4 | O16: =IFERROR(INDEX($J$5:$J$20,MATCH(LARGE($L$5:$L$20,$N16),$L$5:$L$20,0)),"") | P16: =IFERROR(INDEX($K$5:$K$20,MATCH(LARGE($L$5:$L$20,$N16),$L$5:$L$20,0)),"") | Q16: =IF(OR($O16="",$O16="BYE",LEFT($O16,2)="A_",LEFT($O16,2)="B_"),"",IF($N16<=8,IF(AND($P16=INDEX($P$5:$P$20,9),$P16=INDEX($P$5:$P$20,8)),"Empate (mesa)","CLASIFICA"),IF($P16=INDEX($P$5:$P$20,8),"Empate (mesa)","—"))) | AB16: Siriuna | AC16: =JUEZ_1!A91 | AD16: =JUEZ_1!D91 | AE16: =JUEZ_1!F91 | AF16: =(N(JUEZ_1!I91)+N(JUEZ_1!J91))+(N(JUEZ_2!I91)+N(JUEZ_2!J91))+(N(JUEZ_3!I91)+N(JUEZ_3!J91)) | AG16: =IF(AND($AF16=MAX($AF16,$AF17),$AF16>0),"🥇 MEJOR Siriuna","")
A17: =JUEZ_1!D23 | B17: =(SUM(JUEZ_1!I23:I25)+SUM(JUEZ_2!I23:I25)+SUM(JUEZ_3!I23:I25)) | C17: =IF(OR($A17="",$A17="BYE",LEFT($A17,2)="A_",LEFT($A17,2)="B_"),-1000-ROW()*0.0000001,N(B17)-ROW()*0.0000001) | E17: =ROW()-4 | F17: =IFERROR(INDEX($A$5:$A$36,MATCH(LARGE($C$5:$C$36,$E17),$C$5:$C$36,0)),"") | G17: =IFERROR(INDEX($B$5:$B$36,MATCH(LARGE($C$5:$C$36,$E17),$C$5:$C$36,0)),"") | H17: =IF(OR($F17="",$F17="BYE",LEFT($F17,2)="A_",LEFT($F17,2)="B_"),"",IF($E17<=16,IF(AND($G17=INDEX($G$5:$G$36,17),$G17=INDEX($G$5:$G$36,16)),"Empate (mesa)","CLASIFICA"),IF($G17=INDEX($G$5:$G$36,16),"Empate (mesa)","—"))) | J17: =JUEZ_1!D71 | K17: =(SUM(JUEZ_1!I71:I73)+SUM(JUEZ_2!I71:I73)+SUM(JUEZ_3!I71:I73)) | L17: =IF(OR($J17="",$J17="BYE",LEFT($J17,2)="A_",LEFT($J17,2)="B_"),-1000-ROW()*0.0000001,N(K17)-ROW()*0.0000001) | N17: =ROW()-4 | O17: =IFERROR(INDEX($J$5:$J$20,MATCH(LARGE($L$5:$L$20,$N17),$L$5:$L$20,0)),"") | P17: =IFERROR(INDEX($K$5:$K$20,MATCH(LARGE($L$5:$L$20,$N17),$L$5:$L$20,0)),"") | Q17: =IF(OR($O17="",$O17="BYE",LEFT($O17,2)="A_",LEFT($O17,2)="B_"),"",IF($N17<=8,IF(AND($P17=INDEX($P$5:$P$20,9),$P17=INDEX($P$5:$P$20,8)),"Empate (mesa)","CLASIFICA"),IF($P17=INDEX($P$5:$P$20,8),"Empate (mesa)","—"))) | AB17: Siriuna | AC17: =JUEZ_1!A94 | AD17: =JUEZ_1!D94 | AE17: =JUEZ_1!F94 | AF17: =(N(JUEZ_1!I94)+N(JUEZ_1!J94))+(N(JUEZ_2!I94)+N(JUEZ_2!J94))+(N(JUEZ_3!I94)+N(JUEZ_3!J94)) | AG17: =IF(AND($AF17=MAX($AF16,$AF17),$AF17>0),"🥇 MEJOR Siriuna","")
A18: =JUEZ_1!F23 | B18: =(SUM(JUEZ_1!J23:J25)+SUM(JUEZ_2!J23:J25)+SUM(JUEZ_3!J23:J25)) | C18: =IF(OR($A18="",$A18="BYE",LEFT($A18,2)="A_",LEFT($A18,2)="B_"),-1000-ROW()*0.0000001,N(B18)-ROW()*0.0000001) | E18: =ROW()-4 | F18: =IFERROR(INDEX($A$5:$A$36,MATCH(LARGE($C$5:$C$36,$E18),$C$5:$C$36,0)),"") | G18: =IFERROR(INDEX($B$5:$B$36,MATCH(LARGE($C$5:$C$36,$E18),$C$5:$C$36,0)),"") | H18: =IF(OR($F18="",$F18="BYE",LEFT($F18,2)="A_",LEFT($F18,2)="B_"),"",IF($E18<=16,IF(AND($G18=INDEX($G$5:$G$36,17),$G18=INDEX($G$5:$G$36,16)),"Empate (mesa)","CLASIFICA"),IF($G18=INDEX($G$5:$G$36,16),"Empate (mesa)","—"))) | J18: =JUEZ_1!F71 | K18: =(SUM(JUEZ_1!J71:J73)+SUM(JUEZ_2!J71:J73)+SUM(JUEZ_3!J71:J73)) | L18: =IF(OR($J18="",$J18="BYE",LEFT($J18,2)="A_",LEFT($J18,2)="B_"),-1000-ROW()*0.0000001,N(K18)-ROW()*0.0000001) | N18: =ROW()-4 | O18: =IFERROR(INDEX($J$5:$J$20,MATCH(LARGE($L$5:$L$20,$N18),$L$5:$L$20,0)),"") | P18: =IFERROR(INDEX($K$5:$K$20,MATCH(LARGE($L$5:$L$20,$N18),$L$5:$L$20,0)),"") | Q18: =IF(OR($O18="",$O18="BYE",LEFT($O18,2)="A_",LEFT($O18,2)="B_"),"",IF($N18<=8,IF(AND($P18=INDEX($P$5:$P$20,9),$P18=INDEX($P$5:$P$20,8)),"Empate (mesa)","CLASIFICA"),IF($P18=INDEX($P$5:$P$20,8),"Empate (mesa)","—")))
A19: =JUEZ_1!D26 | B19: =(SUM(JUEZ_1!I26:I28)+SUM(JUEZ_2!I26:I28)+SUM(JUEZ_3!I26:I28)) | C19: =IF(OR($A19="",$A19="BYE",LEFT($A19,2)="A_",LEFT($A19,2)="B_"),-1000-ROW()*0.0000001,N(B19)-ROW()*0.0000001) | E19: =ROW()-4 | F19: =IFERROR(INDEX($A$5:$A$36,MATCH(LARGE($C$5:$C$36,$E19),$C$5:$C$36,0)),"") | G19: =IFERROR(INDEX($B$5:$B$36,MATCH(LARGE($C$5:$C$36,$E19),$C$5:$C$36,0)),"") | H19: =IF(OR($F19="",$F19="BYE",LEFT($F19,2)="A_",LEFT($F19,2)="B_"),"",IF($E19<=16,IF(AND($G19=INDEX($G$5:$G$36,17),$G19=INDEX($G$5:$G$36,16)),"Empate (mesa)","CLASIFICA"),IF($G19=INDEX($G$5:$G$36,16),"Empate (mesa)","—"))) | J19: =JUEZ_1!D74 | K19: =(SUM(JUEZ_1!I74:I76)+SUM(JUEZ_2!I74:I76)+SUM(JUEZ_3!I74:I76)) | L19: =IF(OR($J19="",$J19="BYE",LEFT($J19,2)="A_",LEFT($J19,2)="B_"),-1000-ROW()*0.0000001,N(K19)-ROW()*0.0000001) | N19: =ROW()-4 | O19: =IFERROR(INDEX($J$5:$J$20,MATCH(LARGE($L$5:$L$20,$N19),$L$5:$L$20,0)),"") | P19: =IFERROR(INDEX($K$5:$K$20,MATCH(LARGE($L$5:$L$20,$N19),$L$5:$L$20,0)),"") | Q19: =IF(OR($O19="",$O19="BYE",LEFT($O19,2)="A_",LEFT($O19,2)="B_"),"",IF($N19<=8,IF(AND($P19=INDEX($P$5:$P$20,9),$P19=INDEX($P$5:$P$20,8)),"Empate (mesa)","CLASIFICA"),IF($P19=INDEX($P$5:$P$20,8),"Empate (mesa)","—")))
A20: =JUEZ_1!F26 | B20: =(SUM(JUEZ_1!J26:J28)+SUM(JUEZ_2!J26:J28)+SUM(JUEZ_3!J26:J28)) | C20: =IF(OR($A20="",$A20="BYE",LEFT($A20,2)="A_",LEFT($A20,2)="B_"),-1000-ROW()*0.0000001,N(B20)-ROW()*0.0000001) | E20: =ROW()-4 | F20: =IFERROR(INDEX($A$5:$A$36,MATCH(LARGE($C$5:$C$36,$E20),$C$5:$C$36,0)),"") | G20: =IFERROR(INDEX($B$5:$B$36,MATCH(LARGE($C$5:$C$36,$E20),$C$5:$C$36,0)),"") | H20: =IF(OR($F20="",$F20="BYE",LEFT($F20,2)="A_",LEFT($F20,2)="B_"),"",IF($E20<=16,IF(AND($G20=INDEX($G$5:$G$36,17),$G20=INDEX($G$5:$G$36,16)),"Empate (mesa)","CLASIFICA"),IF($G20=INDEX($G$5:$G$36,16),"Empate (mesa)","—"))) | J20: =JUEZ_1!F74 | K20: =(SUM(JUEZ_1!J74:J76)+SUM(JUEZ_2!J74:J76)+SUM(JUEZ_3!J74:J76)) | L20: =IF(OR($J20="",$J20="BYE",LEFT($J20,2)="A_",LEFT($J20,2)="B_"),-1000-ROW()*0.0000001,N(K20)-ROW()*0.0000001) | N20: =ROW()-4 | O20: =IFERROR(INDEX($J$5:$J$20,MATCH(LARGE($L$5:$L$20,$N20),$L$5:$L$20,0)),"") | P20: =IFERROR(INDEX($K$5:$K$20,MATCH(LARGE($L$5:$L$20,$N20),$L$5:$L$20,0)),"") | Q20: =IF(OR($O20="",$O20="BYE",LEFT($O20,2)="A_",LEFT($O20,2)="B_"),"",IF($N20<=8,IF(AND($P20=INDEX($P$5:$P$20,9),$P20=INDEX($P$5:$P$20,8)),"Empate (mesa)","CLASIFICA"),IF($P20=INDEX($P$5:$P$20,8),"Empate (mesa)","—")))
A21: =JUEZ_1!D29 | B21: =(SUM(JUEZ_1!I29:I31)+SUM(JUEZ_2!I29:I31)+SUM(JUEZ_3!I29:I31)) | C21: =IF(OR($A21="",$A21="BYE",LEFT($A21,2)="A_",LEFT($A21,2)="B_"),-1000-ROW()*0.0000001,N(B21)-ROW()*0.0000001) | E21: =ROW()-4 | F21: =IFERROR(INDEX($A$5:$A$36,MATCH(LARGE($C$5:$C$36,$E21),$C$5:$C$36,0)),"") | G21: =IFERROR(INDEX($B$5:$B$36,MATCH(LARGE($C$5:$C$36,$E21),$C$5:$C$36,0)),"") | H21: =IF(OR($F21="",$F21="BYE",LEFT($F21,2)="A_",LEFT($F21,2)="B_"),"",IF($E21<=16,IF(AND($G21=INDEX($G$5:$G$36,17),$G21=INDEX($G$5:$G$36,16)),"Empate (mesa)","CLASIFICA"),IF($G21=INDEX($G$5:$G$36,16),"Empate (mesa)","—")))
A22: =JUEZ_1!F29 | B22: =(SUM(JUEZ_1!J29:J31)+SUM(JUEZ_2!J29:J31)+SUM(JUEZ_3!J29:J31)) | C22: =IF(OR($A22="",$A22="BYE",LEFT($A22,2)="A_",LEFT($A22,2)="B_"),-1000-ROW()*0.0000001,N(B22)-ROW()*0.0000001) | E22: =ROW()-4 | F22: =IFERROR(INDEX($A$5:$A$36,MATCH(LARGE($C$5:$C$36,$E22),$C$5:$C$36,0)),"") | G22: =IFERROR(INDEX($B$5:$B$36,MATCH(LARGE($C$5:$C$36,$E22),$C$5:$C$36,0)),"") | H22: =IF(OR($F22="",$F22="BYE",LEFT($F22,2)="A_",LEFT($F22,2)="B_"),"",IF($E22<=16,IF(AND($G22=INDEX($G$5:$G$36,17),$G22=INDEX($G$5:$G$36,16)),"Empate (mesa)","CLASIFICA"),IF($G22=INDEX($G$5:$G$36,16),"Empate (mesa)","—")))
A23: =JUEZ_1!D32 | B23: =(SUM(JUEZ_1!I32:I34)+SUM(JUEZ_2!I32:I34)+SUM(JUEZ_3!I32:I34)) | C23: =IF(OR($A23="",$A23="BYE",LEFT($A23,2)="A_",LEFT($A23,2)="B_"),-1000-ROW()*0.0000001,N(B23)-ROW()*0.0000001) | E23: =ROW()-4 | F23: =IFERROR(INDEX($A$5:$A$36,MATCH(LARGE($C$5:$C$36,$E23),$C$5:$C$36,0)),"") | G23: =IFERROR(INDEX($B$5:$B$36,MATCH(LARGE($C$5:$C$36,$E23),$C$5:$C$36,0)),"") | H23: =IF(OR($F23="",$F23="BYE",LEFT($F23,2)="A_",LEFT($F23,2)="B_"),"",IF($E23<=16,IF(AND($G23=INDEX($G$5:$G$36,17),$G23=INDEX($G$5:$G$36,16)),"Empate (mesa)","CLASIFICA"),IF($G23=INDEX($G$5:$G$36,16),"Empate (mesa)","—")))
A24: =JUEZ_1!F32 | B24: =(SUM(JUEZ_1!J32:J34)+SUM(JUEZ_2!J32:J34)+SUM(JUEZ_3!J32:J34)) | C24: =IF(OR($A24="",$A24="BYE",LEFT($A24,2)="A_",LEFT($A24,2)="B_"),-1000-ROW()*0.0000001,N(B24)-ROW()*0.0000001) | E24: =ROW()-4 | F24: =IFERROR(INDEX($A$5:$A$36,MATCH(LARGE($C$5:$C$36,$E24),$C$5:$C$36,0)),"") | G24: =IFERROR(INDEX($B$5:$B$36,MATCH(LARGE($C$5:$C$36,$E24),$C$5:$C$36,0)),"") | H24: =IF(OR($F24="",$F24="BYE",LEFT($F24,2)="A_",LEFT($F24,2)="B_"),"",IF($E24<=16,IF(AND($G24=INDEX($G$5:$G$36,17),$G24=INDEX($G$5:$G$36,16)),"Empate (mesa)","CLASIFICA"),IF($G24=INDEX($G$5:$G$36,16),"Empate (mesa)","—")))
A25: =JUEZ_1!D35 | B25: =(SUM(JUEZ_1!I35:I37)+SUM(JUEZ_2!I35:I37)+SUM(JUEZ_3!I35:I37)) | C25: =IF(OR($A25="",$A25="BYE",LEFT($A25,2)="A_",LEFT($A25,2)="B_"),-1000-ROW()*0.0000001,N(B25)-ROW()*0.0000001) | E25: =ROW()-4 | F25: =IFERROR(INDEX($A$5:$A$36,MATCH(LARGE($C$5:$C$36,$E25),$C$5:$C$36,0)),"") | G25: =IFERROR(INDEX($B$5:$B$36,MATCH(LARGE($C$5:$C$36,$E25),$C$5:$C$36,0)),"") | H25: =IF(OR($F25="",$F25="BYE",LEFT($F25,2)="A_",LEFT($F25,2)="B_"),"",IF($E25<=16,IF(AND($G25=INDEX($G$5:$G$36,17),$G25=INDEX($G$5:$G$36,16)),"Empate (mesa)","CLASIFICA"),IF($G25=INDEX($G$5:$G$36,16),"Empate (mesa)","—")))
A26: =JUEZ_1!F35 | B26: =(SUM(JUEZ_1!J35:J37)+SUM(JUEZ_2!J35:J37)+SUM(JUEZ_3!J35:J37)) | C26: =IF(OR($A26="",$A26="BYE",LEFT($A26,2)="A_",LEFT($A26,2)="B_"),-1000-ROW()*0.0000001,N(B26)-ROW()*0.0000001) | E26: =ROW()-4 | F26: =IFERROR(INDEX($A$5:$A$36,MATCH(LARGE($C$5:$C$36,$E26),$C$5:$C$36,0)),"") | G26: =IFERROR(INDEX($B$5:$B$36,MATCH(LARGE($C$5:$C$36,$E26),$C$5:$C$36,0)),"") | H26: =IF(OR($F26="",$F26="BYE",LEFT($F26,2)="A_",LEFT($F26,2)="B_"),"",IF($E26<=16,IF(AND($G26=INDEX($G$5:$G$36,17),$G26=INDEX($G$5:$G$36,16)),"Empate (mesa)","CLASIFICA"),IF($G26=INDEX($G$5:$G$36,16),"Empate (mesa)","—")))
A27: =JUEZ_1!D38 | B27: =(SUM(JUEZ_1!I38:I40)+SUM(JUEZ_2!I38:I40)+SUM(JUEZ_3!I38:I40)) | C27: =IF(OR($A27="",$A27="BYE",LEFT($A27,2)="A_",LEFT($A27,2)="B_"),-1000-ROW()*0.0000001,N(B27)-ROW()*0.0000001) | E27: =ROW()-4 | F27: =IFERROR(INDEX($A$5:$A$36,MATCH(LARGE($C$5:$C$36,$E27),$C$5:$C$36,0)),"") | G27: =IFERROR(INDEX($B$5:$B$36,MATCH(LARGE($C$5:$C$36,$E27),$C$5:$C$36,0)),"") | H27: =IF(OR($F27="",$F27="BYE",LEFT($F27,2)="A_",LEFT($F27,2)="B_"),"",IF($E27<=16,IF(AND($G27=INDEX($G$5:$G$36,17),$G27=INDEX($G$5:$G$36,16)),"Empate (mesa)","CLASIFICA"),IF($G27=INDEX($G$5:$G$36,16),"Empate (mesa)","—")))
A28: =JUEZ_1!F38 | B28: =(SUM(JUEZ_1!J38:J40)+SUM(JUEZ_2!J38:J40)+SUM(JUEZ_3!J38:J40)) | C28: =IF(OR($A28="",$A28="BYE",LEFT($A28,2)="A_",LEFT($A28,2)="B_"),-1000-ROW()*0.0000001,N(B28)-ROW()*0.0000001) | E28: =ROW()-4 | F28: =IFERROR(INDEX($A$5:$A$36,MATCH(LARGE($C$5:$C$36,$E28),$C$5:$C$36,0)),"") | G28: =IFERROR(INDEX($B$5:$B$36,MATCH(LARGE($C$5:$C$36,$E28),$C$5:$C$36,0)),"") | H28: =IF(OR($F28="",$F28="BYE",LEFT($F28,2)="A_",LEFT($F28,2)="B_"),"",IF($E28<=16,IF(AND($G28=INDEX($G$5:$G$36,17),$G28=INDEX($G$5:$G$36,16)),"Empate (mesa)","CLASIFICA"),IF($G28=INDEX($G$5:$G$36,16),"Empate (mesa)","—")))
A29: =JUEZ_1!D41 | B29: =(SUM(JUEZ_1!I41:I43)+SUM(JUEZ_2!I41:I43)+SUM(JUEZ_3!I41:I43)) | C29: =IF(OR($A29="",$A29="BYE",LEFT($A29,2)="A_",LEFT($A29,2)="B_"),-1000-ROW()*0.0000001,N(B29)-ROW()*0.0000001) | E29: =ROW()-4 | F29: =IFERROR(INDEX($A$5:$A$36,MATCH(LARGE($C$5:$C$36,$E29),$C$5:$C$36,0)),"") | G29: =IFERROR(INDEX($B$5:$B$36,MATCH(LARGE($C$5:$C$36,$E29),$C$5:$C$36,0)),"") | H29: =IF(OR($F29="",$F29="BYE",LEFT($F29,2)="A_",LEFT($F29,2)="B_"),"",IF($E29<=16,IF(AND($G29=INDEX($G$5:$G$36,17),$G29=INDEX($G$5:$G$36,16)),"Empate (mesa)","CLASIFICA"),IF($G29=INDEX($G$5:$G$36,16),"Empate (mesa)","—")))
A30: =JUEZ_1!F41 | B30: =(SUM(JUEZ_1!J41:J43)+SUM(JUEZ_2!J41:J43)+SUM(JUEZ_3!J41:J43)) | C30: =IF(OR($A30="",$A30="BYE",LEFT($A30,2)="A_",LEFT($A30,2)="B_"),-1000-ROW()*0.0000001,N(B30)-ROW()*0.0000001) | E30: =ROW()-4 | F30: =IFERROR(INDEX($A$5:$A$36,MATCH(LARGE($C$5:$C$36,$E30),$C$5:$C$36,0)),"") | G30: =IFERROR(INDEX($B$5:$B$36,MATCH(LARGE($C$5:$C$36,$E30),$C$5:$C$36,0)),"") | H30: =IF(OR($F30="",$F30="BYE",LEFT($F30,2)="A_",LEFT($F30,2)="B_"),"",IF($E30<=16,IF(AND($G30=INDEX($G$5:$G$36,17),$G30=INDEX($G$5:$G$36,16)),"Empate (mesa)","CLASIFICA"),IF($G30=INDEX($G$5:$G$36,16),"Empate (mesa)","—")))
A31: =JUEZ_1!D44 | B31: =(SUM(JUEZ_1!I44:I46)+SUM(JUEZ_2!I44:I46)+SUM(JUEZ_3!I44:I46)) | C31: =IF(OR($A31="",$A31="BYE",LEFT($A31,2)="A_",LEFT($A31,2)="B_"),-1000-ROW()*0.0000001,N(B31)-ROW()*0.0000001) | E31: =ROW()-4 | F31: =IFERROR(INDEX($A$5:$A$36,MATCH(LARGE($C$5:$C$36,$E31),$C$5:$C$36,0)),"") | G31: =IFERROR(INDEX($B$5:$B$36,MATCH(LARGE($C$5:$C$36,$E31),$C$5:$C$36,0)),"") | H31: =IF(OR($F31="",$F31="BYE",LEFT($F31,2)="A_",LEFT($F31,2)="B_"),"",IF($E31<=16,IF(AND($G31=INDEX($G$5:$G$36,17),$G31=INDEX($G$5:$G$36,16)),"Empate (mesa)","CLASIFICA"),IF($G31=INDEX($G$5:$G$36,16),"Empate (mesa)","—")))
A32: =JUEZ_1!F44 | B32: =(SUM(JUEZ_1!J44:J46)+SUM(JUEZ_2!J44:J46)+SUM(JUEZ_3!J44:J46)) | C32: =IF(OR($A32="",$A32="BYE",LEFT($A32,2)="A_",LEFT($A32,2)="B_"),-1000-ROW()*0.0000001,N(B32)-ROW()*0.0000001) | E32: =ROW()-4 | F32: =IFERROR(INDEX($A$5:$A$36,MATCH(LARGE($C$5:$C$36,$E32),$C$5:$C$36,0)),"") | G32: =IFERROR(INDEX($B$5:$B$36,MATCH(LARGE($C$5:$C$36,$E32),$C$5:$C$36,0)),"") | H32: =IF(OR($F32="",$F32="BYE",LEFT($F32,2)="A_",LEFT($F32,2)="B_"),"",IF($E32<=16,IF(AND($G32=INDEX($G$5:$G$36,17),$G32=INDEX($G$5:$G$36,16)),"Empate (mesa)","CLASIFICA"),IF($G32=INDEX($G$5:$G$36,16),"Empate (mesa)","—")))
A33: =JUEZ_1!D47 | B33: =(SUM(JUEZ_1!I47:I49)+SUM(JUEZ_2!I47:I49)+SUM(JUEZ_3!I47:I49)) | C33: =IF(OR($A33="",$A33="BYE",LEFT($A33,2)="A_",LEFT($A33,2)="B_"),-1000-ROW()*0.0000001,N(B33)-ROW()*0.0000001) | E33: =ROW()-4 | F33: =IFERROR(INDEX($A$5:$A$36,MATCH(LARGE($C$5:$C$36,$E33),$C$5:$C$36,0)),"") | G33: =IFERROR(INDEX($B$5:$B$36,MATCH(LARGE($C$5:$C$36,$E33),$C$5:$C$36,0)),"") | H33: =IF(OR($F33="",$F33="BYE",LEFT($F33,2)="A_",LEFT($F33,2)="B_"),"",IF($E33<=16,IF(AND($G33=INDEX($G$5:$G$36,17),$G33=INDEX($G$5:$G$36,16)),"Empate (mesa)","CLASIFICA"),IF($G33=INDEX($G$5:$G$36,16),"Empate (mesa)","—")))
A34: =JUEZ_1!F47 | B34: =(SUM(JUEZ_1!J47:J49)+SUM(JUEZ_2!J47:J49)+SUM(JUEZ_3!J47:J49)) | C34: =IF(OR($A34="",$A34="BYE",LEFT($A34,2)="A_",LEFT($A34,2)="B_"),-1000-ROW()*0.0000001,N(B34)-ROW()*0.0000001) | E34: =ROW()-4 | F34: =IFERROR(INDEX($A$5:$A$36,MATCH(LARGE($C$5:$C$36,$E34),$C$5:$C$36,0)),"") | G34: =IFERROR(INDEX($B$5:$B$36,MATCH(LARGE($C$5:$C$36,$E34),$C$5:$C$36,0)),"") | H34: =IF(OR($F34="",$F34="BYE",LEFT($F34,2)="A_",LEFT($F34,2)="B_"),"",IF($E34<=16,IF(AND($G34=INDEX($G$5:$G$36,17),$G34=INDEX($G$5:$G$36,16)),"Empate (mesa)","CLASIFICA"),IF($G34=INDEX($G$5:$G$36,16),"Empate (mesa)","—")))
A35: =JUEZ_1!D50 | B35: =(SUM(JUEZ_1!I50:I52)+SUM(JUEZ_2!I50:I52)+SUM(JUEZ_3!I50:I52)) | C35: =IF(OR($A35="",$A35="BYE",LEFT($A35,2)="A_",LEFT($A35,2)="B_"),-1000-ROW()*0.0000001,N(B35)-ROW()*0.0000001) | E35: =ROW()-4 | F35: =IFERROR(INDEX($A$5:$A$36,MATCH(LARGE($C$5:$C$36,$E35),$C$5:$C$36,0)),"") | G35: =IFERROR(INDEX($B$5:$B$36,MATCH(LARGE($C$5:$C$36,$E35),$C$5:$C$36,0)),"") | H35: =IF(OR($F35="",$F35="BYE",LEFT($F35,2)="A_",LEFT($F35,2)="B_"),"",IF($E35<=16,IF(AND($G35=INDEX($G$5:$G$36,17),$G35=INDEX($G$5:$G$36,16)),"Empate (mesa)","CLASIFICA"),IF($G35=INDEX($G$5:$G$36,16),"Empate (mesa)","—")))
A36: =JUEZ_1!F50 | B36: =(SUM(JUEZ_1!J50:J52)+SUM(JUEZ_2!J50:J52)+SUM(JUEZ_3!J50:J52)) | C36: =IF(OR($A36="",$A36="BYE",LEFT($A36,2)="A_",LEFT($A36,2)="B_"),-1000-ROW()*0.0000001,N(B36)-ROW()*0.0000001) | E36: =ROW()-4 | F36: =IFERROR(INDEX($A$5:$A$36,MATCH(LARGE($C$5:$C$36,$E36),$C$5:$C$36,0)),"") | G36: =IFERROR(INDEX($B$5:$B$36,MATCH(LARGE($C$5:$C$36,$E36),$C$5:$C$36,0)),"") | H36: =IF(OR($F36="",$F36="BYE",LEFT($F36,2)="A_",LEFT($F36,2)="B_"),"",IF($E36<=16,IF(AND($G36=INDEX($G$5:$G$36,17),$G36=INDEX($G$5:$G$36,16)),"Empate (mesa)","CLASIFICA"),IF($G36=INDEX($G$5:$G$36,16),"Empate (mesa)","—")))

Sheet CLASIF_A_F
A1: CLASIFICACIÓN · Cat A Femenino · suma toques × 3 jueces
J3: FASE OCTAVAS · pasan 8 a Semifinal | S3: FASE SEMIFINAL · pasan 4 a la Final | AB3: FASE FINAL · sale el CAMPEÓN
A4: Competidor | B4: Puntos | C4: clave | E4: Puesto | F4: Competidor | G4: Puntos | H4: Estado | J4: Competidor | K4: Puntos | L4: clave | N4: Puesto | O4: Competidor | P4: Puntos | Q4: Estado | S4: Competidor | T4: Puntos | U4: clave | W4: Puesto | X4: Competidor | Y4: Puntos | Z4: Estado | AB4: Competidor | AC4: Puntos | AD4: clave | AF4: Puesto | AG4: Competidor | AH4: Puntos | AI4: Resultado
A5: =JUEZ_1!D98 | B5: =(SUM(JUEZ_1!I98:I100)+SUM(JUEZ_2!I98:I100)+SUM(JUEZ_3!I98:I100)) | C5: =IF(OR($A5="",$A5="BYE",LEFT($A5,2)="A_",LEFT($A5,2)="B_"),-1000-ROW()*0.0000001,N(B5)-ROW()*0.0000001) | E5: =ROW()-4 | F5: =IFERROR(INDEX($A$5:$A$36,MATCH(LARGE($C$5:$C$36,$E5),$C$5:$C$36,0)),"") | G5: =IFERROR(INDEX($B$5:$B$36,MATCH(LARGE($C$5:$C$36,$E5),$C$5:$C$36,0)),"") | H5: =IF(OR($F5="",$F5="BYE",LEFT($F5,2)="A_",LEFT($F5,2)="B_"),"",IF($E5<=16,IF(AND($G5=INDEX($G$5:$G$36,17),$G5=INDEX($G$5:$G$36,16)),"Empate (mesa)","CLASIFICA"),IF($G5=INDEX($G$5:$G$36,16),"Empate (mesa)","—"))) | J5: =JUEZ_1!D146 | K5: =(SUM(JUEZ_1!I146:I148)+SUM(JUEZ_2!I146:I148)+SUM(JUEZ_3!I146:I148)) | L5: =IF(OR($J5="",$J5="BYE",LEFT($J5,2)="A_",LEFT($J5,2)="B_"),-1000-ROW()*0.0000001,N(K5)-ROW()*0.0000001) | N5: =ROW()-4 | O5: =IFERROR(INDEX($J$5:$J$20,MATCH(LARGE($L$5:$L$20,$N5),$L$5:$L$20,0)),"") | P5: =IFERROR(INDEX($K$5:$K$20,MATCH(LARGE($L$5:$L$20,$N5),$L$5:$L$20,0)),"") | Q5: =IF(OR($O5="",$O5="BYE",LEFT($O5,2)="A_",LEFT($O5,2)="B_"),"",IF($N5<=8,IF(AND($P5=INDEX($P$5:$P$20,9),$P5=INDEX($P$5:$P$20,8)),"Empate (mesa)","CLASIFICA"),IF($P5=INDEX($P$5:$P$20,8),"Empate (mesa)","—"))) | S5: =JUEZ_1!D170 | T5: =(SUM(JUEZ_1!I170:I172)+SUM(JUEZ_2!I170:I172)+SUM(JUEZ_3!I170:I172)) | U5: =IF(OR($S5="",$S5="BYE",LEFT($S5,2)="A_",LEFT($S5,2)="B_"),-1000-ROW()*0.0000001,N(T5)-ROW()*0.0000001) | W5: =ROW()-4 | X5: =IFERROR(INDEX($S$5:$S$12,MATCH(LARGE($U$5:$U$12,$W5),$U$5:$U$12,0)),"") | Y5: =IFERROR(INDEX($T$5:$T$12,MATCH(LARGE($U$5:$U$12,$W5),$U$5:$U$12,0)),"") | Z5: =IF(OR($X5="",$X5="BYE",LEFT($X5,2)="A_",LEFT($X5,2)="B_"),"",IF($W5<=4,IF(AND($Y5=INDEX($Y$5:$Y$12,5),$Y5=INDEX($Y$5:$Y$12,4)),"Empate (mesa)","CLASIFICA"),IF($Y5=INDEX($Y$5:$Y$12,4),"Empate (mesa)","—"))) | AB5: =JUEZ_1!D182 | AC5: =(SUM(JUEZ_1!I182:I184)+SUM(JUEZ_2!I182:I184)+SUM(JUEZ_3!I182:I184)) | AD5: =IF(OR($AB5="",$AB5="BYE",LEFT($AB5,2)="A_",LEFT($AB5,2)="B_"),-1000-ROW()*0.0000001,N(AC5)-ROW()*0.0000001) | AF5: =ROW()-4 | AG5: =IFERROR(INDEX($AB$5:$AB$8,MATCH(LARGE($AD$5:$AD$8,$AF5),$AD$5:$AD$8,0)),"") | AH5: =IFERROR(INDEX($AC$5:$AC$8,MATCH(LARGE($AD$5:$AD$8,$AF5),$AD$5:$AD$8,0)),"") | AI5: =IF(OR($AG5="",$AG5="BYE",LEFT($AG5,2)="A_",LEFT($AG5,2)="B_"),"",IF($AF5=1,IF($AH5=INDEX($AH$5:$AH$8,2),"Empate 1º (mesa)","🏆 CAMPEÓN"),IF($AF5=2,"2º Subcampeón",IF($AF5=3,"3er puesto","4º puesto"))))
A6: =JUEZ_1!F98 | B6: =(SUM(JUEZ_1!J98:J100)+SUM(JUEZ_2!J98:J100)+SUM(JUEZ_3!J98:J100)) | C6: =IF(OR($A6="",$A6="BYE",LEFT($A6,2)="A_",LEFT($A6,2)="B_"),-1000-ROW()*0.0000001,N(B6)-ROW()*0.0000001) | E6: =ROW()-4 | F6: =IFERROR(INDEX($A$5:$A$36,MATCH(LARGE($C$5:$C$36,$E6),$C$5:$C$36,0)),"") | G6: =IFERROR(INDEX($B$5:$B$36,MATCH(LARGE($C$5:$C$36,$E6),$C$5:$C$36,0)),"") | H6: =IF(OR($F6="",$F6="BYE",LEFT($F6,2)="A_",LEFT($F6,2)="B_"),"",IF($E6<=16,IF(AND($G6=INDEX($G$5:$G$36,17),$G6=INDEX($G$5:$G$36,16)),"Empate (mesa)","CLASIFICA"),IF($G6=INDEX($G$5:$G$36,16),"Empate (mesa)","—"))) | J6: =JUEZ_1!F146 | K6: =(SUM(JUEZ_1!J146:J148)+SUM(JUEZ_2!J146:J148)+SUM(JUEZ_3!J146:J148)) | L6: =IF(OR($J6="",$J6="BYE",LEFT($J6,2)="A_",LEFT($J6,2)="B_"),-1000-ROW()*0.0000001,N(K6)-ROW()*0.0000001) | N6: =ROW()-4 | O6: =IFERROR(INDEX($J$5:$J$20,MATCH(LARGE($L$5:$L$20,$N6),$L$5:$L$20,0)),"") | P6: =IFERROR(INDEX($K$5:$K$20,MATCH(LARGE($L$5:$L$20,$N6),$L$5:$L$20,0)),"") | Q6: =IF(OR($O6="",$O6="BYE",LEFT($O6,2)="A_",LEFT($O6,2)="B_"),"",IF($N6<=8,IF(AND($P6=INDEX($P$5:$P$20,9),$P6=INDEX($P$5:$P$20,8)),"Empate (mesa)","CLASIFICA"),IF($P6=INDEX($P$5:$P$20,8),"Empate (mesa)","—"))) | S6: =JUEZ_1!F170 | T6: =(SUM(JUEZ_1!J170:J172)+SUM(JUEZ_2!J170:J172)+SUM(JUEZ_3!J170:J172)) | U6: =IF(OR($S6="",$S6="BYE",LEFT($S6,2)="A_",LEFT($S6,2)="B_"),-1000-ROW()*0.0000001,N(T6)-ROW()*0.0000001) | W6: =ROW()-4 | X6: =IFERROR(INDEX($S$5:$S$12,MATCH(LARGE($U$5:$U$12,$W6),$U$5:$U$12,0)),"") | Y6: =IFERROR(INDEX($T$5:$T$12,MATCH(LARGE($U$5:$U$12,$W6),$U$5:$U$12,0)),"") | Z6: =IF(OR($X6="",$X6="BYE",LEFT($X6,2)="A_",LEFT($X6,2)="B_"),"",IF($W6<=4,IF(AND($Y6=INDEX($Y$5:$Y$12,5),$Y6=INDEX($Y$5:$Y$12,4)),"Empate (mesa)","CLASIFICA"),IF($Y6=INDEX($Y$5:$Y$12,4),"Empate (mesa)","—"))) | AB6: =JUEZ_1!F182 | AC6: =(SUM(JUEZ_1!J182:J184)+SUM(JUEZ_2!J182:J184)+SUM(JUEZ_3!J182:J184)) | AD6: =IF(OR($AB6="",$AB6="BYE",LEFT($AB6,2)="A_",LEFT($AB6,2)="B_"),-1000-ROW()*0.0000001,N(AC6)-ROW()*0.0000001) | AF6: =ROW()-4 | AG6: =IFERROR(INDEX($AB$5:$AB$8,MATCH(LARGE($AD$5:$AD$8,$AF6),$AD$5:$AD$8,0)),"") | AH6: =IFERROR(INDEX($AC$5:$AC$8,MATCH(LARGE($AD$5:$AD$8,$AF6),$AD$5:$AD$8,0)),"") | AI6: =IF(OR($AG6="",$AG6="BYE",LEFT($AG6,2)="A_",LEFT($AG6,2)="B_"),"",IF($AF6=1,IF($AH6=INDEX($AH$5:$AH$8,2),"Empate 1º (mesa)","🏆 CAMPEÓN"),IF($AF6=2,"2º Subcampeón",IF($AF6=3,"3er puesto","4º puesto"))))
A7: =JUEZ_1!D101 | B7: =(SUM(JUEZ_1!I101:I103)+SUM(JUEZ_2!I101:I103)+SUM(JUEZ_3!I101:I103)) | C7: =IF(OR($A7="",$A7="BYE",LEFT($A7,2)="A_",LEFT($A7,2)="B_"),-1000-ROW()*0.0000001,N(B7)-ROW()*0.0000001) | E7: =ROW()-4 | F7: =IFERROR(INDEX($A$5:$A$36,MATCH(LARGE($C$5:$C$36,$E7),$C$5:$C$36,0)),"") | G7: =IFERROR(INDEX($B$5:$B$36,MATCH(LARGE($C$5:$C$36,$E7),$C$5:$C$36,0)),"") | H7: =IF(OR($F7="",$F7="BYE",LEFT($F7,2)="A_",LEFT($F7,2)="B_"),"",IF($E7<=16,IF(AND($G7=INDEX($G$5:$G$36,17),$G7=INDEX($G$5:$G$36,16)),"Empate (mesa)","CLASIFICA"),IF($G7=INDEX($G$5:$G$36,16),"Empate (mesa)","—"))) | J7: =JUEZ_1!D149 | K7: =(SUM(JUEZ_1!I149:I151)+SUM(JUEZ_2!I149:I151)+SUM(JUEZ_3!I149:I151)) | L7: =IF(OR($J7="",$J7="BYE",LEFT($J7,2)="A_",LEFT($J7,2)="B_"),-1000-ROW()*0.0000001,N(K7)-ROW()*0.0000001) | N7: =ROW()-4 | O7: =IFERROR(INDEX($J$5:$J$20,MATCH(LARGE($L$5:$L$20,$N7),$L$5:$L$20,0)),"") | P7: =IFERROR(INDEX($K$5:$K$20,MATCH(LARGE($L$5:$L$20,$N7),$L$5:$L$20,0)),"") | Q7: =IF(OR($O7="",$O7="BYE",LEFT($O7,2)="A_",LEFT($O7,2)="B_"),"",IF($N7<=8,IF(AND($P7=INDEX($P$5:$P$20,9),$P7=INDEX($P$5:$P$20,8)),"Empate (mesa)","CLASIFICA"),IF($P7=INDEX($P$5:$P$20,8),"Empate (mesa)","—"))) | S7: =JUEZ_1!D173 | T7: =(SUM(JUEZ_1!I173:I175)+SUM(JUEZ_2!I173:I175)+SUM(JUEZ_3!I173:I175)) | U7: =IF(OR($S7="",$S7="BYE",LEFT($S7,2)="A_",LEFT($S7,2)="B_"),-1000-ROW()*0.0000001,N(T7)-ROW()*0.0000001) | W7: =ROW()-4 | X7: =IFERROR(INDEX($S$5:$S$12,MATCH(LARGE($U$5:$U$12,$W7),$U$5:$U$12,0)),"") | Y7: =IFERROR(INDEX($T$5:$T$12,MATCH(LARGE($U$5:$U$12,$W7),$U$5:$U$12,0)),"") | Z7: =IF(OR($X7="",$X7="BYE",LEFT($X7,2)="A_",LEFT($X7,2)="B_"),"",IF($W7<=4,IF(AND($Y7=INDEX($Y$5:$Y$12,5),$Y7=INDEX($Y$5:$Y$12,4)),"Empate (mesa)","CLASIFICA"),IF($Y7=INDEX($Y$5:$Y$12,4),"Empate (mesa)","—"))) | AB7: =JUEZ_1!D185 | AC7: =(SUM(JUEZ_1!I185:I187)+SUM(JUEZ_2!I185:I187)+SUM(JUEZ_3!I185:I187)) | AD7: =IF(OR($AB7="",$AB7="BYE",LEFT($AB7,2)="A_",LEFT($AB7,2)="B_"),-1000-ROW()*0.0000001,N(AC7)-ROW()*0.0000001) | AF7: =ROW()-4 | AG7: =IFERROR(INDEX($AB$5:$AB$8,MATCH(LARGE($AD$5:$AD$8,$AF7),$AD$5:$AD$8,0)),"") | AH7: =IFERROR(INDEX($AC$5:$AC$8,MATCH(LARGE($AD$5:$AD$8,$AF7),$AD$5:$AD$8,0)),"") | AI7: =IF(OR($AG7="",$AG7="BYE",LEFT($AG7,2)="A_",LEFT($AG7,2)="B_"),"",IF($AF7=1,IF($AH7=INDEX($AH$5:$AH$8,2),"Empate 1º (mesa)","🏆 CAMPEÓN"),IF($AF7=2,"2º Subcampeón",IF($AF7=3,"3er puesto","4º puesto"))))
A8: =JUEZ_1!F101 | B8: =(SUM(JUEZ_1!J101:J103)+SUM(JUEZ_2!J101:J103)+SUM(JUEZ_3!J101:J103)) | C8: =IF(OR($A8="",$A8="BYE",LEFT($A8,2)="A_",LEFT($A8,2)="B_"),-1000-ROW()*0.0000001,N(B8)-ROW()*0.0000001) | E8: =ROW()-4 | F8: =IFERROR(INDEX($A$5:$A$36,MATCH(LARGE($C$5:$C$36,$E8),$C$5:$C$36,0)),"") | G8: =IFERROR(INDEX($B$5:$B$36,MATCH(LARGE($C$5:$C$36,$E8),$C$5:$C$36,0)),"") | H8: =IF(OR($F8="",$F8="BYE",LEFT($F8,2)="A_",LEFT($F8,2)="B_"),"",IF($E8<=16,IF(AND($G8=INDEX($G$5:$G$36,17),$G8=INDEX($G$5:$G$36,16)),"Empate (mesa)","CLASIFICA"),IF($G8=INDEX($G$5:$G$36,16),"Empate (mesa)","—"))) | J8: =JUEZ_1!F149 | K8: =(SUM(JUEZ_1!J149:J151)+SUM(JUEZ_2!J149:J151)+SUM(JUEZ_3!J149:J151)) | L8: =IF(OR($J8="",$J8="BYE",LEFT($J8,2)="A_",LEFT($J8,2)="B_"),-1000-ROW()*0.0000001,N(K8)-ROW()*0.0000001) | N8: =ROW()-4 | O8: =IFERROR(INDEX($J$5:$J$20,MATCH(LARGE($L$5:$L$20,$N8),$L$5:$L$20,0)),"") | P8: =IFERROR(INDEX($K$5:$K$20,MATCH(LARGE($L$5:$L$20,$N8),$L$5:$L$20,0)),"") | Q8: =IF(OR($O8="",$O8="BYE",LEFT($O8,2)="A_",LEFT($O8,2)="B_"),"",IF($N8<=8,IF(AND($P8=INDEX($P$5:$P$20,9),$P8=INDEX($P$5:$P$20,8)),"Empate (mesa)","CLASIFICA"),IF($P8=INDEX($P$5:$P$20,8),"Empate (mesa)","—"))) | S8: =JUEZ_1!F173 | T8: =(SUM(JUEZ_1!J173:J175)+SUM(JUEZ_2!J173:J175)+SUM(JUEZ_3!J173:J175)) | U8: =IF(OR($S8="",$S8="BYE",LEFT($S8,2)="A_",LEFT($S8,2)="B_"),-1000-ROW()*0.0000001,N(T8)-ROW()*0.0000001) | W8: =ROW()-4 | X8: =IFERROR(INDEX($S$5:$S$12,MATCH(LARGE($U$5:$U$12,$W8),$U$5:$U$12,0)),"") | Y8: =IFERROR(INDEX($T$5:$T$12,MATCH(LARGE($U$5:$U$12,$W8),$U$5:$U$12,0)),"") | Z8: =IF(OR($X8="",$X8="BYE",LEFT($X8,2)="A_",LEFT($X8,2)="B_"),"",IF($W8<=4,IF(AND($Y8=INDEX($Y$5:$Y$12,5),$Y8=INDEX($Y$5:$Y$12,4)),"Empate (mesa)","CLASIFICA"),IF($Y8=INDEX($Y$5:$Y$12,4),"Empate (mesa)","—"))) | AB8: =JUEZ_1!F185 | AC8: =(SUM(JUEZ_1!J185:J187)+SUM(JUEZ_2!J185:J187)+SUM(JUEZ_3!J185:J187)) | AD8: =IF(OR($AB8="",$AB8="BYE",LEFT($AB8,2)="A_",LEFT($AB8,2)="B_"),-1000-ROW()*0.0000001,N(AC8)-ROW()*0.0000001) | AF8: =ROW()-4 | AG8: =IFERROR(INDEX($AB$5:$AB$8,MATCH(LARGE($AD$5:$AD$8,$AF8),$AD$5:$AD$8,0)),"") | AH8: =IFERROR(INDEX($AC$5:$AC$8,MATCH(LARGE($AD$5:$AD$8,$AF8),$AD$5:$AD$8,0)),"") | AI8: =IF(OR($AG8="",$AG8="BYE",LEFT($AG8,2)="A_",LEFT($AG8,2)="B_"),"",IF($AF8=1,IF($AH8=INDEX($AH$5:$AH$8,2),"Empate 1º (mesa)","🏆 CAMPEÓN"),IF($AF8=2,"2º Subcampeón",IF($AF8=3,"3er puesto","4º puesto"))))
A9: =JUEZ_1!D104 | B9: =(SUM(JUEZ_1!I104:I106)+SUM(JUEZ_2!I104:I106)+SUM(JUEZ_3!I104:I106)) | C9: =IF(OR($A9="",$A9="BYE",LEFT($A9,2)="A_",LEFT($A9,2)="B_"),-1000-ROW()*0.0000001,N(B9)-ROW()*0.0000001) | E9: =ROW()-4 | F9: =IFERROR(INDEX($A$5:$A$36,MATCH(LARGE($C$5:$C$36,$E9),$C$5:$C$36,0)),"") | G9: =IFERROR(INDEX($B$5:$B$36,MATCH(LARGE($C$5:$C$36,$E9),$C$5:$C$36,0)),"") | H9: =IF(OR($F9="",$F9="BYE",LEFT($F9,2)="A_",LEFT($F9,2)="B_"),"",IF($E9<=16,IF(AND($G9=INDEX($G$5:$G$36,17),$G9=INDEX($G$5:$G$36,16)),"Empate (mesa)","CLASIFICA"),IF($G9=INDEX($G$5:$G$36,16),"Empate (mesa)","—"))) | J9: =JUEZ_1!D152 | K9: =(SUM(JUEZ_1!I152:I154)+SUM(JUEZ_2!I152:I154)+SUM(JUEZ_3!I152:I154)) | L9: =IF(OR($J9="",$J9="BYE",LEFT($J9,2)="A_",LEFT($J9,2)="B_"),-1000-ROW()*0.0000001,N(K9)-ROW()*0.0000001) | N9: =ROW()-4 | O9: =IFERROR(INDEX($J$5:$J$20,MATCH(LARGE($L$5:$L$20,$N9),$L$5:$L$20,0)),"") | P9: =IFERROR(INDEX($K$5:$K$20,MATCH(LARGE($L$5:$L$20,$N9),$L$5:$L$20,0)),"") | Q9: =IF(OR($O9="",$O9="BYE",LEFT($O9,2)="A_",LEFT($O9,2)="B_"),"",IF($N9<=8,IF(AND($P9=INDEX($P$5:$P$20,9),$P9=INDEX($P$5:$P$20,8)),"Empate (mesa)","CLASIFICA"),IF($P9=INDEX($P$5:$P$20,8),"Empate (mesa)","—"))) | S9: =JUEZ_1!D176 | T9: =(SUM(JUEZ_1!I176:I178)+SUM(JUEZ_2!I176:I178)+SUM(JUEZ_3!I176:I178)) | U9: =IF(OR($S9="",$S9="BYE",LEFT($S9,2)="A_",LEFT($S9,2)="B_"),-1000-ROW()*0.0000001,N(T9)-ROW()*0.0000001) | W9: =ROW()-4 | X9: =IFERROR(INDEX($S$5:$S$12,MATCH(LARGE($U$5:$U$12,$W9),$U$5:$U$12,0)),"") | Y9: =IFERROR(INDEX($T$5:$T$12,MATCH(LARGE($U$5:$U$12,$W9),$U$5:$U$12,0)),"") | Z9: =IF(OR($X9="",$X9="BYE",LEFT($X9,2)="A_",LEFT($X9,2)="B_"),"",IF($W9<=4,IF(AND($Y9=INDEX($Y$5:$Y$12,5),$Y9=INDEX($Y$5:$Y$12,4)),"Empate (mesa)","CLASIFICA"),IF($Y9=INDEX($Y$5:$Y$12,4),"Empate (mesa)","—")))
A10: =JUEZ_1!F104 | B10: =(SUM(JUEZ_1!J104:J106)+SUM(JUEZ_2!J104:J106)+SUM(JUEZ_3!J104:J106)) | C10: =IF(OR($A10="",$A10="BYE",LEFT($A10,2)="A_",LEFT($A10,2)="B_"),-1000-ROW()*0.0000001,N(B10)-ROW()*0.0000001) | E10: =ROW()-4 | F10: =IFERROR(INDEX($A$5:$A$36,MATCH(LARGE($C$5:$C$36,$E10),$C$5:$C$36,0)),"") | G10: =IFERROR(INDEX($B$5:$B$36,MATCH(LARGE($C$5:$C$36,$E10),$C$5:$C$36,0)),"") | H10: =IF(OR($F10="",$F10="BYE",LEFT($F10,2)="A_",LEFT($F10,2)="B_"),"",IF($E10<=16,IF(AND($G10=INDEX($G$5:$G$36,17),$G10=INDEX($G$5:$G$36,16)),"Empate (mesa)","CLASIFICA"),IF($G10=INDEX($G$5:$G$36,16),"Empate (mesa)","—"))) | J10: =JUEZ_1!F152 | K10: =(SUM(JUEZ_1!J152:J154)+SUM(JUEZ_2!J152:J154)+SUM(JUEZ_3!J152:J154)) | L10: =IF(OR($J10="",$J10="BYE",LEFT($J10,2)="A_",LEFT($J10,2)="B_"),-1000-ROW()*0.0000001,N(K10)-ROW()*0.0000001) | N10: =ROW()-4 | O10: =IFERROR(INDEX($J$5:$J$20,MATCH(LARGE($L$5:$L$20,$N10),$L$5:$L$20,0)),"") | P10: =IFERROR(INDEX($K$5:$K$20,MATCH(LARGE($L$5:$L$20,$N10),$L$5:$L$20,0)),"") | Q10: =IF(OR($O10="",$O10="BYE",LEFT($O10,2)="A_",LEFT($O10,2)="B_"),"",IF($N10<=8,IF(AND($P10=INDEX($P$5:$P$20,9),$P10=INDEX($P$5:$P$20,8)),"Empate (mesa)","CLASIFICA"),IF($P10=INDEX($P$5:$P$20,8),"Empate (mesa)","—"))) | S10: =JUEZ_1!F176 | T10: =(SUM(JUEZ_1!J176:J178)+SUM(JUEZ_2!J176:J178)+SUM(JUEZ_3!J176:J178)) | U10: =IF(OR($S10="",$S10="BYE",LEFT($S10,2)="A_",LEFT($S10,2)="B_"),-1000-ROW()*0.0000001,N(T10)-ROW()*0.0000001) | W10: =ROW()-4 | X10: =IFERROR(INDEX($S$5:$S$12,MATCH(LARGE($U$5:$U$12,$W10),$U$5:$U$12,0)),"") | Y10: =IFERROR(INDEX($T$5:$T$12,MATCH(LARGE($U$5:$U$12,$W10),$U$5:$U$12,0)),"") | Z10: =IF(OR($X10="",$X10="BYE",LEFT($X10,2)="A_",LEFT($X10,2)="B_"),"",IF($W10<=4,IF(AND($Y10=INDEX($Y$5:$Y$12,5),$Y10=INDEX($Y$5:$Y$12,4)),"Empate (mesa)","CLASIFICA"),IF($Y10=INDEX($Y$5:$Y$12,4),"Empate (mesa)","—"))) | AB10: 🥇 PREMIO MEJOR JUEGO POR TOQUE (Final)
A11: =JUEZ_1!D107 | B11: =(SUM(JUEZ_1!I107:I109)+SUM(JUEZ_2!I107:I109)+SUM(JUEZ_3!I107:I109)) | C11: =IF(OR($A11="",$A11="BYE",LEFT($A11,2)="A_",LEFT($A11,2)="B_"),-1000-ROW()*0.0000001,N(B11)-ROW()*0.0000001) | E11: =ROW()-4 | F11: =IFERROR(INDEX($A$5:$A$36,MATCH(LARGE($C$5:$C$36,$E11),$C$5:$C$36,0)),"") | G11: =IFERROR(INDEX($B$5:$B$36,MATCH(LARGE($C$5:$C$36,$E11),$C$5:$C$36,0)),"") | H11: =IF(OR($F11="",$F11="BYE",LEFT($F11,2)="A_",LEFT($F11,2)="B_"),"",IF($E11<=16,IF(AND($G11=INDEX($G$5:$G$36,17),$G11=INDEX($G$5:$G$36,16)),"Empate (mesa)","CLASIFICA"),IF($G11=INDEX($G$5:$G$36,16),"Empate (mesa)","—"))) | J11: =JUEZ_1!D155 | K11: =(SUM(JUEZ_1!I155:I157)+SUM(JUEZ_2!I155:I157)+SUM(JUEZ_3!I155:I157)) | L11: =IF(OR($J11="",$J11="BYE",LEFT($J11,2)="A_",LEFT($J11,2)="B_"),-1000-ROW()*0.0000001,N(K11)-ROW()*0.0000001) | N11: =ROW()-4 | O11: =IFERROR(INDEX($J$5:$J$20,MATCH(LARGE($L$5:$L$20,$N11),$L$5:$L$20,0)),"") | P11: =IFERROR(INDEX($K$5:$K$20,MATCH(LARGE($L$5:$L$20,$N11),$L$5:$L$20,0)),"") | Q11: =IF(OR($O11="",$O11="BYE",LEFT($O11,2)="A_",LEFT($O11,2)="B_"),"",IF($N11<=8,IF(AND($P11=INDEX($P$5:$P$20,9),$P11=INDEX($P$5:$P$20,8)),"Empate (mesa)","CLASIFICA"),IF($P11=INDEX($P$5:$P$20,8),"Empate (mesa)","—"))) | S11: =JUEZ_1!D179 | T11: =(SUM(JUEZ_1!I179:I181)+SUM(JUEZ_2!I179:I181)+SUM(JUEZ_3!I179:I181)) | U11: =IF(OR($S11="",$S11="BYE",LEFT($S11,2)="A_",LEFT($S11,2)="B_"),-1000-ROW()*0.0000001,N(T11)-ROW()*0.0000001) | W11: =ROW()-4 | X11: =IFERROR(INDEX($S$5:$S$12,MATCH(LARGE($U$5:$U$12,$W11),$U$5:$U$12,0)),"") | Y11: =IFERROR(INDEX($T$5:$T$12,MATCH(LARGE($U$5:$U$12,$W11),$U$5:$U$12,0)),"") | Z11: =IF(OR($X11="",$X11="BYE",LEFT($X11,2)="A_",LEFT($X11,2)="B_"),"",IF($W11<=4,IF(AND($Y11=INDEX($Y$5:$Y$12,5),$Y11=INDEX($Y$5:$Y$12,4)),"Empate (mesa)","CLASIFICA"),IF($Y11=INDEX($Y$5:$Y$12,4),"Empate (mesa)","—"))) | AB11: Toque | AC11: Jogo | AD11: Jugador A | AE11: Jugador B | AF11: Nota jogo | AG11: Premio
A12: =JUEZ_1!F107 | B12: =(SUM(JUEZ_1!J107:J109)+SUM(JUEZ_2!J107:J109)+SUM(JUEZ_3!J107:J109)) | C12: =IF(OR($A12="",$A12="BYE",LEFT($A12,2)="A_",LEFT($A12,2)="B_"),-1000-ROW()*0.0000001,N(B12)-ROW()*0.0000001) | E12: =ROW()-4 | F12: =IFERROR(INDEX($A$5:$A$36,MATCH(LARGE($C$5:$C$36,$E12),$C$5:$C$36,0)),"") | G12: =IFERROR(INDEX($B$5:$B$36,MATCH(LARGE($C$5:$C$36,$E12),$C$5:$C$36,0)),"") | H12: =IF(OR($F12="",$F12="BYE",LEFT($F12,2)="A_",LEFT($F12,2)="B_"),"",IF($E12<=16,IF(AND($G12=INDEX($G$5:$G$36,17),$G12=INDEX($G$5:$G$36,16)),"Empate (mesa)","CLASIFICA"),IF($G12=INDEX($G$5:$G$36,16),"Empate (mesa)","—"))) | J12: =JUEZ_1!F155 | K12: =(SUM(JUEZ_1!J155:J157)+SUM(JUEZ_2!J155:J157)+SUM(JUEZ_3!J155:J157)) | L12: =IF(OR($J12="",$J12="BYE",LEFT($J12,2)="A_",LEFT($J12,2)="B_"),-1000-ROW()*0.0000001,N(K12)-ROW()*0.0000001) | N12: =ROW()-4 | O12: =IFERROR(INDEX($J$5:$J$20,MATCH(LARGE($L$5:$L$20,$N12),$L$5:$L$20,0)),"") | P12: =IFERROR(INDEX($K$5:$K$20,MATCH(LARGE($L$5:$L$20,$N12),$L$5:$L$20,0)),"") | Q12: =IF(OR($O12="",$O12="BYE",LEFT($O12,2)="A_",LEFT($O12,2)="B_"),"",IF($N12<=8,IF(AND($P12=INDEX($P$5:$P$20,9),$P12=INDEX($P$5:$P$20,8)),"Empate (mesa)","CLASIFICA"),IF($P12=INDEX($P$5:$P$20,8),"Empate (mesa)","—"))) | S12: =JUEZ_1!F179 | T12: =(SUM(JUEZ_1!J179:J181)+SUM(JUEZ_2!J179:J181)+SUM(JUEZ_3!J179:J181)) | U12: =IF(OR($S12="",$S12="BYE",LEFT($S12,2)="A_",LEFT($S12,2)="B_"),-1000-ROW()*0.0000001,N(T12)-ROW()*0.0000001) | W12: =ROW()-4 | X12: =IFERROR(INDEX($S$5:$S$12,MATCH(LARGE($U$5:$U$12,$W12),$U$5:$U$12,0)),"") | Y12: =IFERROR(INDEX($T$5:$T$12,MATCH(LARGE($U$5:$U$12,$W12),$U$5:$U$12,0)),"") | Z12: =IF(OR($X12="",$X12="BYE",LEFT($X12,2)="A_",LEFT($X12,2)="B_"),"",IF($W12<=4,IF(AND($Y12=INDEX($Y$5:$Y$12,5),$Y12=INDEX($Y$5:$Y$12,4)),"Empate (mesa)","CLASIFICA"),IF($Y12=INDEX($Y$5:$Y$12,4),"Empate (mesa)","—"))) | AB12: Benguela | AC12: =JUEZ_1!A182 | AD12: =JUEZ_1!D182 | AE12: =JUEZ_1!F182 | AF12: =(N(JUEZ_1!I182)+N(JUEZ_1!J182))+(N(JUEZ_2!I182)+N(JUEZ_2!J182))+(N(JUEZ_3!I182)+N(JUEZ_3!J182)) | AG12: =IF(AND($AF12=MAX($AF12,$AF13),$AF12>0),"🥇 MEJOR Benguela","")
A13: =JUEZ_1!D110 | B13: =(SUM(JUEZ_1!I110:I112)+SUM(JUEZ_2!I110:I112)+SUM(JUEZ_3!I110:I112)) | C13: =IF(OR($A13="",$A13="BYE",LEFT($A13,2)="A_",LEFT($A13,2)="B_"),-1000-ROW()*0.0000001,N(B13)-ROW()*0.0000001) | E13: =ROW()-4 | F13: =IFERROR(INDEX($A$5:$A$36,MATCH(LARGE($C$5:$C$36,$E13),$C$5:$C$36,0)),"") | G13: =IFERROR(INDEX($B$5:$B$36,MATCH(LARGE($C$5:$C$36,$E13),$C$5:$C$36,0)),"") | H13: =IF(OR($F13="",$F13="BYE",LEFT($F13,2)="A_",LEFT($F13,2)="B_"),"",IF($E13<=16,IF(AND($G13=INDEX($G$5:$G$36,17),$G13=INDEX($G$5:$G$36,16)),"Empate (mesa)","CLASIFICA"),IF($G13=INDEX($G$5:$G$36,16),"Empate (mesa)","—"))) | J13: =JUEZ_1!D158 | K13: =(SUM(JUEZ_1!I158:I160)+SUM(JUEZ_2!I158:I160)+SUM(JUEZ_3!I158:I160)) | L13: =IF(OR($J13="",$J13="BYE",LEFT($J13,2)="A_",LEFT($J13,2)="B_"),-1000-ROW()*0.0000001,N(K13)-ROW()*0.0000001) | N13: =ROW()-4 | O13: =IFERROR(INDEX($J$5:$J$20,MATCH(LARGE($L$5:$L$20,$N13),$L$5:$L$20,0)),"") | P13: =IFERROR(INDEX($K$5:$K$20,MATCH(LARGE($L$5:$L$20,$N13),$L$5:$L$20,0)),"") | Q13: =IF(OR($O13="",$O13="BYE",LEFT($O13,2)="A_",LEFT($O13,2)="B_"),"",IF($N13<=8,IF(AND($P13=INDEX($P$5:$P$20,9),$P13=INDEX($P$5:$P$20,8)),"Empate (mesa)","CLASIFICA"),IF($P13=INDEX($P$5:$P$20,8),"Empate (mesa)","—"))) | AB13: Benguela | AC13: =JUEZ_1!A185 | AD13: =JUEZ_1!D185 | AE13: =JUEZ_1!F185 | AF13: =(N(JUEZ_1!I185)+N(JUEZ_1!J185))+(N(JUEZ_2!I185)+N(JUEZ_2!J185))+(N(JUEZ_3!I185)+N(JUEZ_3!J185)) | AG13: =IF(AND($AF13=MAX($AF12,$AF13),$AF13>0),"🥇 MEJOR Benguela","")
A14: =JUEZ_1!F110 | B14: =(SUM(JUEZ_1!J110:J112)+SUM(JUEZ_2!J110:J112)+SUM(JUEZ_3!J110:J112)) | C14: =IF(OR($A14="",$A14="BYE",LEFT($A14,2)="A_",LEFT($A14,2)="B_"),-1000-ROW()*0.0000001,N(B14)-ROW()*0.0000001) | E14: =ROW()-4 | F14: =IFERROR(INDEX($A$5:$A$36,MATCH(LARGE($C$5:$C$36,$E14),$C$5:$C$36,0)),"") | G14: =IFERROR(INDEX($B$5:$B$36,MATCH(LARGE($C$5:$C$36,$E14),$C$5:$C$36,0)),"") | H14: =IF(OR($F14="",$F14="BYE",LEFT($F14,2)="A_",LEFT($F14,2)="B_"),"",IF($E14<=16,IF(AND($G14=INDEX($G$5:$G$36,17),$G14=INDEX($G$5:$G$36,16)),"Empate (mesa)","CLASIFICA"),IF($G14=INDEX($G$5:$G$36,16),"Empate (mesa)","—"))) | J14: =JUEZ_1!F158 | K14: =(SUM(JUEZ_1!J158:J160)+SUM(JUEZ_2!J158:J160)+SUM(JUEZ_3!J158:J160)) | L14: =IF(OR($J14="",$J14="BYE",LEFT($J14,2)="A_",LEFT($J14,2)="B_"),-1000-ROW()*0.0000001,N(K14)-ROW()*0.0000001) | N14: =ROW()-4 | O14: =IFERROR(INDEX($J$5:$J$20,MATCH(LARGE($L$5:$L$20,$N14),$L$5:$L$20,0)),"") | P14: =IFERROR(INDEX($K$5:$K$20,MATCH(LARGE($L$5:$L$20,$N14),$L$5:$L$20,0)),"") | Q14: =IF(OR($O14="",$O14="BYE",LEFT($O14,2)="A_",LEFT($O14,2)="B_"),"",IF($N14<=8,IF(AND($P14=INDEX($P$5:$P$20,9),$P14=INDEX($P$5:$P$20,8)),"Empate (mesa)","CLASIFICA"),IF($P14=INDEX($P$5:$P$20,8),"Empate (mesa)","—"))) | AB14: São Bento da Abadá | AC14: =JUEZ_1!A183 | AD14: =JUEZ_1!D183 | AE14: =JUEZ_1!F183 | AF14: =(N(JUEZ_1!I183)+N(JUEZ_1!J183))+(N(JUEZ_2!I183)+N(JUEZ_2!J183))+(N(JUEZ_3!I183)+N(JUEZ_3!J183)) | AG14: =IF(AND($AF14=MAX($AF14,$AF15),$AF14>0),"🥇 MEJOR São Bento da Abadá","")
A15: =JUEZ_1!D113 | B15: =(SUM(JUEZ_1!I113:I115)+SUM(JUEZ_2!I113:I115)+SUM(JUEZ_3!I113:I115)) | C15: =IF(OR($A15="",$A15="BYE",LEFT($A15,2)="A_",LEFT($A15,2)="B_"),-1000-ROW()*0.0000001,N(B15)-ROW()*0.0000001) | E15: =ROW()-4 | F15: =IFERROR(INDEX($A$5:$A$36,MATCH(LARGE($C$5:$C$36,$E15),$C$5:$C$36,0)),"") | G15: =IFERROR(INDEX($B$5:$B$36,MATCH(LARGE($C$5:$C$36,$E15),$C$5:$C$36,0)),"") | H15: =IF(OR($F15="",$F15="BYE",LEFT($F15,2)="A_",LEFT($F15,2)="B_"),"",IF($E15<=16,IF(AND($G15=INDEX($G$5:$G$36,17),$G15=INDEX($G$5:$G$36,16)),"Empate (mesa)","CLASIFICA"),IF($G15=INDEX($G$5:$G$36,16),"Empate (mesa)","—"))) | J15: =JUEZ_1!D161 | K15: =(SUM(JUEZ_1!I161:I163)+SUM(JUEZ_2!I161:I163)+SUM(JUEZ_3!I161:I163)) | L15: =IF(OR($J15="",$J15="BYE",LEFT($J15,2)="A_",LEFT($J15,2)="B_"),-1000-ROW()*0.0000001,N(K15)-ROW()*0.0000001) | N15: =ROW()-4 | O15: =IFERROR(INDEX($J$5:$J$20,MATCH(LARGE($L$5:$L$20,$N15),$L$5:$L$20,0)),"") | P15: =IFERROR(INDEX($K$5:$K$20,MATCH(LARGE($L$5:$L$20,$N15),$L$5:$L$20,0)),"") | Q15: =IF(OR($O15="",$O15="BYE",LEFT($O15,2)="A_",LEFT($O15,2)="B_"),"",IF($N15<=8,IF(AND($P15=INDEX($P$5:$P$20,9),$P15=INDEX($P$5:$P$20,8)),"Empate (mesa)","CLASIFICA"),IF($P15=INDEX($P$5:$P$20,8),"Empate (mesa)","—"))) | AB15: São Bento da Abadá | AC15: =JUEZ_1!A186 | AD15: =JUEZ_1!D186 | AE15: =JUEZ_1!F186 | AF15: =(N(JUEZ_1!I186)+N(JUEZ_1!J186))+(N(JUEZ_2!I186)+N(JUEZ_2!J186))+(N(JUEZ_3!I186)+N(JUEZ_3!J186)) | AG15: =IF(AND($AF15=MAX($AF14,$AF15),$AF15>0),"🥇 MEJOR São Bento da Abadá","")
A16: =JUEZ_1!F113 | B16: =(SUM(JUEZ_1!J113:J115)+SUM(JUEZ_2!J113:J115)+SUM(JUEZ_3!J113:J115)) | C16: =IF(OR($A16="",$A16="BYE",LEFT($A16,2)="A_",LEFT($A16,2)="B_"),-1000-ROW()*0.0000001,N(B16)-ROW()*0.0000001) | E16: =ROW()-4 | F16: =IFERROR(INDEX($A$5:$A$36,MATCH(LARGE($C$5:$C$36,$E16),$C$5:$C$36,0)),"") | G16: =IFERROR(INDEX($B$5:$B$36,MATCH(LARGE($C$5:$C$36,$E16),$C$5:$C$36,0)),"") | H16: =IF(OR($F16="",$F16="BYE",LEFT($F16,2)="A_",LEFT($F16,2)="B_"),"",IF($E16<=16,IF(AND($G16=INDEX($G$5:$G$36,17),$G16=INDEX($G$5:$G$36,16)),"Empate (mesa)","CLASIFICA"),IF($G16=INDEX($G$5:$G$36,16),"Empate (mesa)","—"))) | J16: =JUEZ_1!F161 | K16: =(SUM(JUEZ_1!J161:J163)+SUM(JUEZ_2!J161:J163)+SUM(JUEZ_3!J161:J163)) | L16: =IF(OR($J16="",$J16="BYE",LEFT($J16,2)="A_",LEFT($J16,2)="B_"),-1000-ROW()*0.0000001,N(K16)-ROW()*0.0000001) | N16: =ROW()-4 | O16: =IFERROR(INDEX($J$5:$J$20,MATCH(LARGE($L$5:$L$20,$N16),$L$5:$L$20,0)),"") | P16: =IFERROR(INDEX($K$5:$K$20,MATCH(LARGE($L$5:$L$20,$N16),$L$5:$L$20,0)),"") | Q16: =IF(OR($O16="",$O16="BYE",LEFT($O16,2)="A_",LEFT($O16,2)="B_"),"",IF($N16<=8,IF(AND($P16=INDEX($P$5:$P$20,9),$P16=INDEX($P$5:$P$20,8)),"Empate (mesa)","CLASIFICA"),IF($P16=INDEX($P$5:$P$20,8),"Empate (mesa)","—"))) | AB16: Siriuna | AC16: =JUEZ_1!A184 | AD16: =JUEZ_1!D184 | AE16: =JUEZ_1!F184 | AF16: =(N(JUEZ_1!I184)+N(JUEZ_1!J184))+(N(JUEZ_2!I184)+N(JUEZ_2!J184))+(N(JUEZ_3!I184)+N(JUEZ_3!J184)) | AG16: =IF(AND($AF16=MAX($AF16,$AF17),$AF16>0),"🥇 MEJOR Siriuna","")
A17: =JUEZ_1!D116 | B17: =(SUM(JUEZ_1!I116:I118)+SUM(JUEZ_2!I116:I118)+SUM(JUEZ_3!I116:I118)) | C17: =IF(OR($A17="",$A17="BYE",LEFT($A17,2)="A_",LEFT($A17,2)="B_"),-1000-ROW()*0.0000001,N(B17)-ROW()*0.0000001) | E17: =ROW()-4 | F17: =IFERROR(INDEX($A$5:$A$36,MATCH(LARGE($C$5:$C$36,$E17),$C$5:$C$36,0)),"") | G17: =IFERROR(INDEX($B$5:$B$36,MATCH(LARGE($C$5:$C$36,$E17),$C$5:$C$36,0)),"") | H17: =IF(OR($F17="",$F17="BYE",LEFT($F17,2)="A_",LEFT($F17,2)="B_"),"",IF($E17<=16,IF(AND($G17=INDEX($G$5:$G$36,17),$G17=INDEX($G$5:$G$36,16)),"Empate (mesa)","CLASIFICA"),IF($G17=INDEX($G$5:$G$36,16),"Empate (mesa)","—"))) | J17: =JUEZ_1!D164 | K17: =(SUM(JUEZ_1!I164:I166)+SUM(JUEZ_2!I164:I166)+SUM(JUEZ_3!I164:I166)) | L17: =IF(OR($J17="",$J17="BYE",LEFT($J17,2)="A_",LEFT($J17,2)="B_"),-1000-ROW()*0.0000001,N(K17)-ROW()*0.0000001) | N17: =ROW()-4 | O17: =IFERROR(INDEX($J$5:$J$20,MATCH(LARGE($L$5:$L$20,$N17),$L$5:$L$20,0)),"") | P17: =IFERROR(INDEX($K$5:$K$20,MATCH(LARGE($L$5:$L$20,$N17),$L$5:$L$20,0)),"") | Q17: =IF(OR($O17="",$O17="BYE",LEFT($O17,2)="A_",LEFT($O17,2)="B_"),"",IF($N17<=8,IF(AND($P17=INDEX($P$5:$P$20,9),$P17=INDEX($P$5:$P$20,8)),"Empate (mesa)","CLASIFICA"),IF($P17=INDEX($P$5:$P$20,8),"Empate (mesa)","—"))) | AB17: Siriuna | AC17: =JUEZ_1!A187 | AD17: =JUEZ_1!D187 | AE17: =JUEZ_1!F187 | AF17: =(N(JUEZ_1!I187)+N(JUEZ_1!J187))+(N(JUEZ_2!I187)+N(JUEZ_2!J187))+(N(JUEZ_3!I187)+N(JUEZ_3!J187)) | AG17: =IF(AND($AF17=MAX($AF16,$AF17),$AF17>0),"🥇 MEJOR Siriuna","")
A18: =JUEZ_1!F116 | B18: =(SUM(JUEZ_1!J116:J118)+SUM(JUEZ_2!J116:J118)+SUM(JUEZ_3!J116:J118)) | C18: =IF(OR($A18="",$A18="BYE",LEFT($A18,2)="A_",LEFT($A18,2)="B_"),-1000-ROW()*0.0000001,N(B18)-ROW()*0.0000001) | E18: =ROW()-4 | F18: =IFERROR(INDEX($A$5:$A$36,MATCH(LARGE($C$5:$C$36,$E18),$C$5:$C$36,0)),"") | G18: =IFERROR(INDEX($B$5:$B$36,MATCH(LARGE($C$5:$C$36,$E18),$C$5:$C$36,0)),"") | H18: =IF(OR($F18="",$F18="BYE",LEFT($F18,2)="A_",LEFT($F18,2)="B_"),"",IF($E18<=16,IF(AND($G18=INDEX($G$5:$G$36,17),$G18=INDEX($G$5:$G$36,16)),"Empate (mesa)","CLASIFICA"),IF($G18=INDEX($G$5:$G$36,16),"Empate (mesa)","—"))) | J18: =JUEZ_1!F164 | K18: =(SUM(JUEZ_1!J164:J166)+SUM(JUEZ_2!J164:J166)+SUM(JUEZ_3!J164:J166)) | L18: =IF(OR($J18="",$J18="BYE",LEFT($J18,2)="A_",LEFT($J18,2)="B_"),-1000-ROW()*0.0000001,N(K18)-ROW()*0.0000001) | N18: =ROW()-4 | O18: =IFERROR(INDEX($J$5:$J$20,MATCH(LARGE($L$5:$L$20,$N18),$L$5:$L$20,0)),"") | P18: =IFERROR(INDEX($K$5:$K$20,MATCH(LARGE($L$5:$L$20,$N18),$L$5:$L$20,0)),"") | Q18: =IF(OR($O18="",$O18="BYE",LEFT($O18,2)="A_",LEFT($O18,2)="B_"),"",IF($N18<=8,IF(AND($P18=INDEX($P$5:$P$20,9),$P18=INDEX($P$5:$P$20,8)),"Empate (mesa)","CLASIFICA"),IF($P18=INDEX($P$5:$P$20,8),"Empate (mesa)","—")))
A19: =JUEZ_1!D119 | B19: =(SUM(JUEZ_1!I119:I121)+SUM(JUEZ_2!I119:I121)+SUM(JUEZ_3!I119:I121)) | C19: =IF(OR($A19="",$A19="BYE",LEFT($A19,2)="A_",LEFT($A19,2)="B_"),-1000-ROW()*0.0000001,N(B19)-ROW()*0.0000001) | E19: =ROW()-4 | F19: =IFERROR(INDEX($A$5:$A$36,MATCH(LARGE($C$5:$C$36,$E19),$C$5:$C$36,0)),"") | G19: =IFERROR(INDEX($B$5:$B$36,MATCH(LARGE($C$5:$C$36,$E19),$C$5:$C$36,0)),"") | H19: =IF(OR($F19="",$F19="BYE",LEFT($F19,2)="A_",LEFT($F19,2)="B_"),"",IF($E19<=16,IF(AND($G19=INDEX($G$5:$G$36,17),$G19=INDEX($G$5:$G$36,16)),"Empate (mesa)","CLASIFICA"),IF($G19=INDEX($G$5:$G$36,16),"Empate (mesa)","—"))) | J19: =JUEZ_1!D167 | K19: =(SUM(JUEZ_1!I167:I169)+SUM(JUEZ_2!I167:I169)+SUM(JUEZ_3!I167:I169)) | L19: =IF(OR($J19="",$J19="BYE",LEFT($J19,2)="A_",LEFT($J19,2)="B_"),-1000-ROW()*0.0000001,N(K19)-ROW()*0.0000001) | N19: =ROW()-4 | O19: =IFERROR(INDEX($J$5:$J$20,MATCH(LARGE($L$5:$L$20,$N19),$L$5:$L$20,0)),"") | P19: =IFERROR(INDEX($K$5:$K$20,MATCH(LARGE($L$5:$L$20,$N19),$L$5:$L$20,0)),"") | Q19: =IF(OR($O19="",$O19="BYE",LEFT($O19,2)="A_",LEFT($O19,2)="B_"),"",IF($N19<=8,IF(AND($P19=INDEX($P$5:$P$20,9),$P19=INDEX($P$5:$P$20,8)),"Empate (mesa)","CLASIFICA"),IF($P19=INDEX($P$5:$P$20,8),"Empate (mesa)","—")))
A20: =JUEZ_1!F119 | B20: =(SUM(JUEZ_1!J119:J121)+SUM(JUEZ_2!J119:J121)+SUM(JUEZ_3!J119:J121)) | C20: =IF(OR($A20="",$A20="BYE",LEFT($A20,2)="A_",LEFT($A20,2)="B_"),-1000-ROW()*0.0000001,N(B20)-ROW()*0.0000001) | E20: =ROW()-4 | F20: =IFERROR(INDEX($A$5:$A$36,MATCH(LARGE($C$5:$C$36,$E20),$C$5:$C$36,0)),"") | G20: =IFERROR(INDEX($B$5:$B$36,MATCH(LARGE($C$5:$C$36,$E20),$C$5:$C$36,0)),"") | H20: =IF(OR($F20="",$F20="BYE",LEFT($F20,2)="A_",LEFT($F20,2)="B_"),"",IF($E20<=16,IF(AND($G20=INDEX($G$5:$G$36,17),$G20=INDEX($G$5:$G$36,16)),"Empate (mesa)","CLASIFICA"),IF($G20=INDEX($G$5:$G$36,16),"Empate (mesa)","—"))) | J20: =JUEZ_1!F167 | K20: =(SUM(JUEZ_1!J167:J169)+SUM(JUEZ_2!J167:J169)+SUM(JUEZ_3!J167:J169)) | L20: =IF(OR($J20="",$J20="BYE",LEFT($J20,2)="A_",LEFT($J20,2)="B_"),-1000-ROW()*0.0000001,N(K20)-ROW()*0.0000001) | N20: =ROW()-4 | O20: =IFERROR(INDEX($J$5:$J$20,MATCH(LARGE($L$5:$L$20,$N20),$L$5:$L$20,0)),"") | P20: =IFERROR(INDEX($K$5:$K$20,MATCH(LARGE($L$5:$L$20,$N20),$L$5:$L$20,0)),"") | Q20: =IF(OR($O20="",$O20="BYE",LEFT($O20,2)="A_",LEFT($O20,2)="B_"),"",IF($N20<=8,IF(AND($P20=INDEX($P$5:$P$20,9),$P20=INDEX($P$5:$P$20,8)),"Empate (mesa)","CLASIFICA"),IF($P20=INDEX($P$5:$P$20,8),"Empate (mesa)","—")))
A21: =JUEZ_1!D122 | B21: =(SUM(JUEZ_1!I122:I124)+SUM(JUEZ_2!I122:I124)+SUM(JUEZ_3!I122:I124)) | C21: =IF(OR($A21="",$A21="BYE",LEFT($A21,2)="A_",LEFT($A21,2)="B_"),-1000-ROW()*0.0000001,N(B21)-ROW()*0.0000001) | E21: =ROW()-4 | F21: =IFERROR(INDEX($A$5:$A$36,MATCH(LARGE($C$5:$C$36,$E21),$C$5:$C$36,0)),"") | G21: =IFERROR(INDEX($B$5:$B$36,MATCH(LARGE($C$5:$C$36,$E21),$C$5:$C$36,0)),"") | H21: =IF(OR($F21="",$F21="BYE",LEFT($F21,2)="A_",LEFT($F21,2)="B_"),"",IF($E21<=16,IF(AND($G21=INDEX($G$5:$G$36,17),$G21=INDEX($G$5:$G$36,16)),"Empate (mesa)","CLASIFICA"),IF($G21=INDEX($G$5:$G$36,16),"Empate (mesa)","—")))
A22: =JUEZ_1!F122 | B22: =(SUM(JUEZ_1!J122:J124)+SUM(JUEZ_2!J122:J124)+SUM(JUEZ_3!J122:J124)) | C22: =IF(OR($A22="",$A22="BYE",LEFT($A22,2)="A_",LEFT($A22,2)="B_"),-1000-ROW()*0.0000001,N(B22)-ROW()*0.0000001) | E22: =ROW()-4 | F22: =IFERROR(INDEX($A$5:$A$36,MATCH(LARGE($C$5:$C$36,$E22),$C$5:$C$36,0)),"") | G22: =IFERROR(INDEX($B$5:$B$36,MATCH(LARGE($C$5:$C$36,$E22),$C$5:$C$36,0)),"") | H22: =IF(OR($F22="",$F22="BYE",LEFT($F22,2)="A_",LEFT($F22,2)="B_"),"",IF($E22<=16,IF(AND($G22=INDEX($G$5:$G$36,17),$G22=INDEX($G$5:$G$36,16)),"Empate (mesa)","CLASIFICA"),IF($G22=INDEX($G$5:$G$36,16),"Empate (mesa)","—")))
A23: =JUEZ_1!D125 | B23: =(SUM(JUEZ_1!I125:I127)+SUM(JUEZ_2!I125:I127)+SUM(JUEZ_3!I125:I127)) | C23: =IF(OR($A23="",$A23="BYE",LEFT($A23,2)="A_",LEFT($A23,2)="B_"),-1000-ROW()*0.0000001,N(B23)-ROW()*0.0000001) | E23: =ROW()-4 | F23: =IFERROR(INDEX($A$5:$A$36,MATCH(LARGE($C$5:$C$36,$E23),$C$5:$C$36,0)),"") | G23: =IFERROR(INDEX($B$5:$B$36,MATCH(LARGE($C$5:$C$36,$E23),$C$5:$C$36,0)),"") | H23: =IF(OR($F23="",$F23="BYE",LEFT($F23,2)="A_",LEFT($F23,2)="B_"),"",IF($E23<=16,IF(AND($G23=INDEX($G$5:$G$36,17),$G23=INDEX($G$5:$G$36,16)),"Empate (mesa)","CLASIFICA"),IF($G23=INDEX($G$5:$G$36,16),"Empate (mesa)","—")))
A24: =JUEZ_1!F125 | B24: =(SUM(JUEZ_1!J125:J127)+SUM(JUEZ_2!J125:J127)+SUM(JUEZ_3!J125:J127)) | C24: =IF(OR($A24="",$A24="BYE",LEFT($A24,2)="A_",LEFT($A24,2)="B_"),-1000-ROW()*0.0000001,N(B24)-ROW()*0.0000001) | E24: =ROW()-4 | F24: =IFERROR(INDEX($A$5:$A$36,MATCH(LARGE($C$5:$C$36,$E24),$C$5:$C$36,0)),"") | G24: =IFERROR(INDEX($B$5:$B$36,MATCH(LARGE($C$5:$C$36,$E24),$C$5:$C$36,0)),"") | H24: =IF(OR($F24="",$F24="BYE",LEFT($F24,2)="A_",LEFT($F24,2)="B_"),"",IF($E24<=16,IF(AND($G24=INDEX($G$5:$G$36,17),$G24=INDEX($G$5:$G$36,16)),"Empate (mesa)","CLASIFICA"),IF($G24=INDEX($G$5:$G$36,16),"Empate (mesa)","—")))
